Workbook
Name db_Bln: db!$I:$I
Name db_Kode: db!$J:$J
Name db_Sum: db!$H:$H

Sheet Lembar Pengesahan
C2: LAMBAR PENGESAHAN
C3: RENCANA KERJA PROYEK (RKP)
C4: ='RKP Dermaga T2 Global - Nex'!B4 -> PEKERJAAN DERMAGA SITE SATUI - TAHAP II
C5: PT BUANA KARYA BHAKTI
C7: NO | D7: URAIAN | F7: BIAYA
D9: BIAYA UMUM DAN ADMINISTRASI
C10: I | D10: KARYAWAN | F10: ='RKP Dermaga T2 Global - Nex'!F11 -> 0
C11: II | D11: ADMINISTRASI KANTOR | F11: ='RKP Dermaga T2 Global - Nex'!F28 -> 470000000
C12: III | D12: PEMELIHARAAN | F12: ='RKP Dermaga T2 Global - Nex'!F95 -> 0
C13: IV | D13: PENGEMBANGAN KARYAWAN | F13: ='RKP Dermaga T2 Global - Nex'!F126 -> 0
C14: V | D14: PERJALANAN DINAS | F14: ='RKP Dermaga T2 Global - Nex'!F134 -> 22000000
C15: VI | D15: PENYUSUTAN/ AMORTISASI | F15: ='RKP Dermaga T2 Global - Nex'!F143 -> 0
C16: VII | D16: BEBAN BANK | F16: ='RKP Dermaga T2 Global - Nex'!F171 -> 0
C17: VIII | D17: BEBAN UMUM & ADM. LAINNYA | F17: ='RKP Dermaga T2 Global - Nex'!F174 -> 0
D18: TOTAL BIAYA UMUM DAN ADMINISTRASI | F18: =SUM(F10:F17) -> 492000000
D20: BIAYA KONSTRUKSI
C21: I | D21: CIVIL WORK | F21: ='RKP Dermaga T2 Global - Nex'!F189 -> 14242000000
C22: II | D22: MEKANIKAL | F22: ='RKP Dermaga T2 Global - Nex'!F247 -> 0
C23: III | D23: ELEKTRIKAL | F23: ='RKP Dermaga T2 Global - Nex'!F264 -> 115000000
D24: TOTAL BIAYA KONSTRUKSI | F24: =SUM(F21:F23) -> 14357000000
D26: GRAND TOTAL RKP | F26: =F18+F24 -> 14849000000
C28: * Lampiran adalah lembar yang tidak terpisahkan dari lembar pengesahan ini
E34: Banjarmasin, 20 Mei 2026
C35: Disahkan Oleh, | F35: Dibuat Oleh,
C40: ( Imam Satoto Yudiono ) | F40: ( Herry Munazar )
C41: Direktur Utama | F41: Manager Engineering & Mill Opr

Sheet RKP Dermaga T2 Global - Nex
B1: ESTIMASI BIAYA | I1: REALISASI
B3: RENCANA KERJA PROYEK (RKP)
B4: PEKERJAAN DERMAGA SITE SATUI - TAHAP II
B6: NO | C6: COA | D6: URAIAN | E6: KONTRAKTOR/ SUPPLIER | F6: BUDGET RKP | G6: NO. SPK | H6: KONTRAKTOR/ SUPPLIER | I6: REALISASI BIAYA | R6: CATATAN | T6: RENCANA SEBARAN BIAYA & TIME SCHEDULE
I7: BUDGET RAB | J7: PEKERJAAN UTAMA | N7: PEKERJAAN TAMBAHAN
J8: NILAI KONTRAK | K8: REALISASI KONTRAK | M8: SISA KONTRAK | N8: NILAI KONTRAK | O8: REALISASI PEK. TAMBAH | Q8: SISA KONTRAK | T8: TAHUN 2024 | Y8: TAHUN 2025
K9: Bi | L9: s/d Bi | O9: Bi | P9: s/d Bi | T9: AGT | U9: SEPT | V9: OKT | W9: NOV | X9: DES | Y9: JAN | Z9: FEB | AA9: MAR | AB9: APR | AC9: MEI | AD9: JUN | AE9: JUL | AF9: AGT | AG9: SEPT | AH9: OKT | AI9: NOV | AJ9: DES
B10: A | C10: 512xx00-???^ | D10: BIAYA UMUM DAN ADMINISTRASI | F10: =F11+F28+F95+F126+F129+F134+F143+F171+F174 -> 492000000 | G10: =G11+G28+G95+G126+G129+G134+G143+G171+G174 -> #REF! | H10: =H11+H28+H95+H126+H129+H134+H143+H171+H174 -> #REF! | I10: =I11+I28+I95+I126+I129+I134+I143+I171+I174 -> 0 | J10: =J11+J28+J95+J126+J129+J134+J143+J171+J174 -> 0 | K10: =K11+K28+K95+K126+K129+K134+K143+K171+K174 -> 0 | L10: =L11+L28+L95+L126+L129+L134+L143+L171+L174 -> 0 | M10: =M11+M28+M95+M126+M129+M134+M143+M171+M174 -> 0 | ... AJ10: =AJ11+AJ28+AJ95+AJ126+AJ129+AJ134+AJ143+AJ171+AJ174 -> 0
B11: I | C11: 1??^ | D11: KARYAWAN | F11: =F27 -> 0 | G11: =G27 -> 0 | H11: =H27 -> 0 | I11: =I27 -> 0 | J11: =J27 -> 0 | K11: =K27 -> 0 | L11: =L27 -> 0 | M11: =M27 -> 0 | ... AJ11: =AJ27 -> 0
C12: 51201001012 | D12: Gaji | F12: 0
C13: 51201001022 | D13: Tunjangan Cuti | F13: 0
C14: 51201001032 | D14: Tunjangan Uang Makan | F14: 0
C15: 51201001042 | D15: Tunjangan Transport | F15: 0
C16: 51201001052 | D16: Tunjangan Pengobatan | F16: 0
C17: 51201001062 | D17: Tunjangan Telekomunikasi | F17: 0
C18: 51201001072 | D18: Tunjangan Perumahan | F18: 0
C19: 51201001082 | D19: Tunjangan Hari Raya & Bonus | F19: 0
C20: 51201001092 | D20: Tunjangan Lainnya : | F20: =SUM(F21:F25) -> 0 | G20: =SUM(G21:G25) -> 0 | H20: =SUM(H21:H25) -> 0 | I20: =SUM(I21:I25) -> 0 | J20: =SUM(J21:J25) -> 0 | K20: =SUM(K21:K25) -> 0 | L20: =SUM(L21:L25) -> 0 | M20: =SUM(M21:M25) -> 0 | ... AJ20: =SUM(AJ21:AJ25) -> 0
C21: 51201002 | D21: - BPJS Ketenagakerjaan | F21: 0
C22: 51201002 | D22: - BPJS Kesehatan | F22: 0
C23: 51201002 | D23: - Subsidi BBM/Perawatan | F23: 0
C24: 51201002 | D24: - Lembur Karyawan | F24: 0
C25: 51201002 | D25: - Tunjangan lain-lain | F25: 0
C26: 51201001102 | D26: Imbalan Kerja | F26: 0
D27: TOTAL KARYAWAN | F27: =F12+F13+F14+F15+F16+F17+F18+F19+F20+F26 -> 0 | G27: =G12+G13+G14+G15+G16+G17+G18+G19+G20+G26 -> 0 | H27: =H12+H13+H14+H15+H16+H17+H18+H19+H20+H26 -> 0 | I27: =I12+I13+I14+I15+I16+I17+I18+I19+I20+I26 -> 0 | J27: =J12+J13+J14+J15+J16+J17+J18+J19+J20+J26 -> 0 | K27: =K12+K13+K14+K15+K16+K17+K18+K19+K20+K26 -> 0 | L27: =L12+L13+L14+L15+L16+L17+L18+L19+L20+L26 -> 0 | M27: =M12+M13+M14+M15+M16+M17+M18+M19+M20+M26 -> 0 | ... AJ27: =AJ12+AJ13+AJ14+AJ15+AJ16+AJ17+AJ18+AJ19+AJ20+AJ26 -> 0
B28: II | C28: 2??^ | D28: ADMINISTRASI KANTOR | F28: =F38+F43+F47+F51+F64+F84+F89+F94 -> 470000000 | G28: =G38+G43+G47+G51+G64+G84+G89+G94 -> #REF! | H28: =H38+H43+H47+H51+H64+H84+H89+H94 -> #REF! | I28: =I38+I43+I47+I51+I64+I84+I89+I94 -> 0 | J28: =J38+J43+J47+J51+J64+J84+J89+J94 -> 0 | K28: =K38+K43+K47+K51+K64+K84+K89+K94 -> 0 | L28: =L38+L43+L47+L51+L64+L84+L89+L94 -> 0 | M28: =M38+M43+M47+M51+M64+M84+M89+M94 -> 0 | ... AJ28: =AJ38+AJ43+AJ47+AJ51+AJ64+AJ84+AJ89+AJ94 -> 0
C29: 21?^ | D29: ADMINISTRASI | F29: =F38 -> 0 | G29: =G38 -> 0 | H29: =H38 -> 0 | I29: =I38 -> 0 | J29: =J38 -> 0 | K29: =K38 -> 0 | L29: =L38 -> 0 | M29: =M38 -> 0 | ... AJ29: =AJ38 -> 0
C30: 51201002112 | D30: Alat Tulis Kantor | F30: 0
C31: 51201002122 | D31: Materai | F31: 0
C32: 51201002132 | D32: Pengiriman Surat/Dokumen | F32: 0
C33: 51201002142 | D33: Cetakan/Formulir | F33: 0
C34: 51201002152 | D34: Fotocopy & Jilid | F34: 0
C35: 51201002162 | D35: Iuran & Langganan | F35: 0
C36: 51201002172 | D36: Pakaian Seragam | F36: 0
C37: 51201002182 | D37: Pengiriman Droping / Jasa Pengawalan | F37: 0
D38: SUB TOTAL ADMINISTRASI | F38: =SUM(F30:F37) -> 0 | G38: =SUM(G30:G37) -> 0 | H38: =SUM(H30:H37) -> 0 | I38: =SUM(I30:I37) -> 0 | J38: =SUM(J30:J37) -> 0 | K38: =SUM(K30:K37) -> 0 | L38: =SUM(L30:L37) -> 0 | M38: =SUM(M30:M37) -> 0 | ... AJ38: =SUM(AJ30:AJ37) -> 0
C39: 22?^ | D39: KOMUNIKASI | F39: =F43 -> 0 | G39: =G43 -> 0 | H39: =H43 -> 0 | I39: =I43 -> 0 | J39: =J43 -> 0 | K39: =K43 -> 0 | L39: =L43 -> 0 | M39: =M43 -> 0 | ... AJ39: =AJ43 -> 0
C40: 51201002212 | D40: Radio Komunikasi | F40: 0
C41: 51201002222 | D41: Telekomunikasi | F41: 0
C42: 51201002232 | D42: Vsat | F42: 0
D43: SUB TOTAL KOMUNIKASI | F43: =SUM(F40:F42) -> 0 | G43: =SUM(G40:G42) -> 0 | H43: =SUM(H40:H42) -> 0 | I43: =SUM(I40:I42) -> 0 | J43: =SUM(J40:J42) -> 0 | K43: =SUM(K40:K42) -> 0 | L43: =SUM(L40:L42) -> 0 | M43: =SUM(M40:M42) -> 0 | ... AJ43: =SUM(AJ40:AJ42) -> 0
C44: 23?^ | D44: KOMPUTER | F44: =F47 -> 0 | G44: =G47 -> 0 | H44: =H47 -> 0 | I44: =I47 -> 0 | J44: =J47 -> 0 | K44: =K47 -> 0 | L44: =L47 -> 0 | M44: =M47 -> 0 | ... AJ44: =AJ47 -> 0
C45: 51201002312 | D45: Operasional Komputer | F45: 0
C46: 51201002322 | D46: Pemeliharaan Komputer | F46: 0
D47: SUB TOTAL KOMPUTER | F47: =SUM(F45:F46) -> 0 | G47: =SUM(G45:G46) -> 0 | H47: =SUM(H45:H46) -> 0 | I47: =SUM(I45:I46) -> 0 | J47: =SUM(J45:J46) -> 0 | K47: =SUM(K45:K46) -> 0 | L47: =SUM(L45:L46) -> 0 | M47: =SUM(M45:M46) -> 0 | ... AJ47: =SUM(AJ45:AJ46) -> 0
C48: 24?^ | D48: LISTRIK | F48: =F51 -> 0 | G48: =G51 -> 0 | H48: =H51 -> 0 | I48: =I51 -> 0 | J48: =J51 -> 0 | K48: =K51 -> 0 | L48: =L51 -> 0 | M48: =M51 -> 0 | ... AJ48: =AJ51 -> 0
C49: 51201002412 | D49: Listrik | F49: 0
C50: 51201002422 | D50: Air | F50: 0
D51: SUB TOTAL LISTRIK | F51: =SUM(F49:F50) -> 0 | G51: =SUM(G49:G50) -> 0 | H51: =SUM(H49:H50) -> 0 | I51: =SUM(I49:I50) -> 0 | J51: =SUM(J49:J50) -> 0 | K51: =SUM(K49:K50) -> 0 | L51: =SUM(L49:L50) -> 0 | M51: =SUM(M49:M50) -> 0 | ... AJ51: =SUM(AJ49:AJ50) -> 0
C52: 25?^ | D52: PERIJINAN & PAJAK | F52: =F64 -> 0 | G52: =G64 -> #REF! | H52: =H64 -> #REF! | I52: =I64 -> 0 | J52: =J64 -> 0 | K52: =K64 -> 0 | L52: =L64 -> 0 | M52: =M64 -> 0 | ... AJ52: =AJ64 -> 0
C53: 51201002512 | D53: Perijinan Pusat | F53: =SUM(F55:F59) -> 0 | G53: =SUM(G55:G56) -> 1190000000 | H53: =SUM(H55:H56) -> 1190000000 | I53: 0 | J53: 0 | K53: 0 | L53: 0 | M53: 0 | N53: 0 | O53: 0 | P53: 0 | Q53: 0 | R53: 0 | S53: 0 | T53: 0 | U53: 0 | V53: 0 | W53: 0 | X53: 0 | Y53: 0 | Z53: 0 | AA53: 0 | AB53: 0 | AC53: 0 | AD53: 0 | AE53: 0 | AF53: 0 | AG53: 0 | AH53: 0 | AI53: 0 | AJ53: 0
D54: Pengurusan Perizinan Awal | G54: 1080000000 | H54: 1080000000 | I54: 0 | J54: 0 | K54: 0 | L54: 0 | M54: 0 | N54: 0 | O54: 0 | P54: 0 | Q54: 0 | R54: 0 | S54: 0 | T54: 0 | U54: 0 | V54: 0 | W54: 0 | X54: 0 | Y54: 0 | Z54: 0 | AA54: 0 | AB54: 0 | AC54: 0 | AD54: 0 | AE54: 0 | AF54: 0 | AG54: 0 | AH54: 0 | AI54: 0 | AJ54: 0
D55: Izin Prinsip SBNP | G55: 1080000000 | H55: 1080000000 | I55: 0 | J55: 0 | K55: 0 | L55: 0 | M55: 0 | N55: 0 | O55: 0 | P55: 0 | Q55: 0 | R55: 0 | S55: 0 | T55: 0 | U55: 0 | V55: 0 | W55: 0 | X55: 0 | Y55: 0 | Z55: 0 | AA55: 0 | AB55: 0 | AC55: 0 | AD55: 0 | AE55: 0 | AF55: 0 | AG55: 0 | AH55: 0 | AI55: 0 | AJ55: 0
D56: Tinjauan Lapangan dan Daftar Suar Indonesia | G56: 110000000 | H56: 110000000 | I56: 0 | J56: 0 | K56: 0 | L56: 0 | M56: 0 | N56: 0 | O56: 0 | P56: 0 | Q56: 0 | R56: 0 | S56: 0 | T56: 0 | U56: 0 | V56: 0 | W56: 0 | X56: 0 | Y56: 0 | Z56: 0 | AA56: 0 | AB56: 0 | AC56: 0 | AD56: 0 | AE56: 0 | AF56: 0 | AG56: 0 | AH56: 0 | AI56: 0 | AJ56: 0
D57: Ijin Pembangunan & Operasional | G57: 1080000000 | H57: 1080000000 | I57: 0 | J57: 0 | K57: 0 | L57: 0 | M57: 0 | N57: 0 | O57: 0 | P57: 0 | Q57: 0 | R57: 0 | S57: 0 | T57: 0 | U57: 0 | V57: 0 | W57: 0 | X57: 0 | Y57: 0 | Z57: 0 | AA57: 0 | AB57: 0 | AC57: 0 | AD57: 0 | AE57: 0 | AF57: 0 | AG57: 0 | AH57: 0 | AI57: 0 | AJ57: 0
D58: Izin & Pembangunan Suar | G58: 110000000 | H58: 110000000 | I58: 0 | J58: 0 | K58: 0 | L58: 0 | M58: 0 | N58: 0 | O58: 0 | P58: 0 | Q58: 0 | R58: 0 | S58: 0 | T58: 0 | U58: 0 | V58: 0 | W58: 0 | X58: 0 | Y58: 0 | Z58: 0 | AA58: 0 | AB58: 0 | AC58: 0 | AD58: 0 | AE58: 0 | AF58: 0 | AG58: 0 | AH58: 0 | AI58: 0 | AJ58: 0
D59: Perijinan Lainnya | F59: 0
C60: 51201002522 | D60: Perijinan Pekerja Asing | F60: 0
C61: 51201002532 | D61: Retribusi & Pungutan | F61: 0 | G61: =SUM(#REF!) -> #REF! | H61: =SUM(#REF!) -> #REF!
C62: 51201002542 | D62: Pajak & Ijin Lapor Unit | F62: 0
C63: 51201002552 | D63: Pajak HO | F63: 0
D64: SUB TOTAL PERIJINAN & PAJAK | F64: =F53+F60+F61+F62+F63 -> 0 | G64: =G53+G60+G61+G62+G63 -> #REF! | H64: =H53+H60+H61+H62+H63 -> #REF! | I64: =I53+I60+I61+I62+I63 -> 0 | J64: =J53+J60+J61+J62+J63 -> 0 | K64: =K53+K60+K61+K62+K63 -> 0 | L64: =L53+L60+L61+L62+L63 -> 0 | M64: =M53+M60+M61+M62+M63 -> 0 | ... AJ64: =AJ53+AJ60+AJ61+AJ62+AJ63 -> 0
C65: 26?^ | D65: PROFESIONAL | F65: =F84 -> 470000000 | G65: =G84 -> 0 | H65: =H84 -> 0 | I65: =I84 -> 0 | J65: =J84 -> 0 | K65: =K84 -> 0 | L65: =L84 -> 0 | M65: =M84 -> 0 | ... AJ65: =AJ84 -> 0
C66: 51201002612 | D66: Hukum & Notaris | F66: 0
C67: 51201002622 | D67: Konsultan | F67: =SUM(F72:H82) -> 470000000 | G67: =SUM(G73:G82) -> 0 | H67: =SUM(H73:H82) -> 0 | I67: =SUM(I73:I82) -> 0 | J67: =SUM(J73:J82) -> 0 | K67: =SUM(K73:K82) -> 0 | L67: =SUM(L73:L82) -> 0 | M67: =SUM(M73:M82) -> 0 | N67: =SUM(N73:N82) -> 0 | ... AJ67: =SUM(AJ73:AJ82) -> 0
D68: DP Tahap I Studi Kelayakan & Kajian Teknis
D69: Pelunasan 40% Studi Kelayakan & Kajian Teknis
D70: By Tahap I Studi Kelayakan & Kajian Teknis
D71: Pelunasan Studi Kelayakan & Kajian Teknis
D72: AMDAL
D73: Soil Test | F73: 50000000
D74: Perencanaan Civil Work | F74: 300000000
D75: Perencanaan Mekanikal | F75: 0
D76: Perencanaan Elektrikal | F76: 0
D77: Konsultan Pengawas | F77: 80000000
D78: PDA Test | F78: 40000000
D79: Static Load Test | F79: 0
D80: Core Drill | F80: 0
D81: Review Design | F81: 0
D82: Konsultan Lainnya | F82: 0
C83: 51201002632 | D83: Akuntan Publik | F83: 0
D84: SUB TOTAL PROFESIONAL | F84: =F66+F67+F83 -> 470000000 | G84: =G66+G67+G83 -> 0 | H84: =H66+H67+H83 -> 0 | I84: =I66+I67+I83 -> 0 | J84: =J66+J67+J83 -> 0 | K84: =K66+K67+K83 -> 0 | L84: =L66+L67+L83 -> 0 | M84: =M66+M67+M83 -> 0 | ... AJ84: =AJ66+AJ67+AJ83 -> 0
C85: 27?^ | D85: ASURANSI | F85: =F89 -> 0 | G85: =G89 -> 0 | H85: =H89 -> 0 | I85: =I89 -> 0 | J85: =J89 -> 0 | K85: =K89 -> 0 | L85: =L89 -> 0 | M85: =M89 -> 0 | ... AJ85: =AJ89 -> 0
C86: 51201002712 | D86: Asuransi Kebakaran
C87: 51201002722 | D87: Asuransi Kecelakaan
C88: 51201002792 | D88: Asuransi Lainnya
D89: SUB TOTAL ASURANSI | F89: =SUM(F86:F88) -> 0 | G89: =SUM(G86:G88) -> 0 | H89: =SUM(H86:H88) -> 0 | I89: =SUM(I86:I88) -> 0 | J89: =SUM(J86:J88) -> 0 | K89: =SUM(K86:K88) -> 0 | L89: =SUM(L86:L88) -> 0 | M89: =SUM(M86:M88) -> 0 | ... AJ89: =SUM(AJ86:AJ88) -> 0
C90: 28?^ | D90: SEWA | F90: =F94 -> 0 | G90: =G94 -> 0 | H90: =H94 -> 0 | I90: =I94 -> 0 | J90: =J94 -> 0 | K90: =K94 -> 0 | L90: =L94 -> 0 | M90: =M94 -> 0 | ... AJ90: =AJ94 -> 0
C91: 51201002812 | D91: Sewa Bangunan
C92: 51201002822 | D92: Sewa Tanah
C93: 51201002892 | D93: Sewa Lainnya
D94: SUB TOTAL SEWA | F94: =SUM(F91:F93) -> 0 | G94: =SUM(G91:G93) -> 0 | H94: =SUM(H91:H93) -> 0 | I94: =SUM(I91:I93) -> 0 | J94: =SUM(J91:J93) -> 0 | K94: =SUM(K91:K93) -> 0 | L94: =SUM(L91:L93) -> 0 | M94: =SUM(M91:M93) -> 0 | ... AJ94: =SUM(AJ91:AJ93) -> 0
B95: III | C95: 3??^ | D95: PEMELIHARAAN | F95: =F96+F103+F112+F116 -> 0 | G95: =G96+G103+G112+G116 -> 0 | H95: =H96+H103+H112+H116 -> 0 | I95: =I96+I103+I112+I116 -> 0 | J95: =J96+J103+J112+J116 -> 0 | K95: =K96+K103+K112+K116 -> 0 | L95: =L96+L103+L112+L116 -> 0 | M95: =M96+M103+M112+M116 -> 0 | ... AJ95: =AJ96+AJ103+AJ112+AJ116 -> 0
C96: 31?^ | D96: BANGUNAN KERJA | F96: =F102 -> 0 | G96: =G102 -> 0 | H96: =H102 -> 0 | I96: =I102 -> 0 | J96: =J102 -> 0 | K96: =K102 -> 0 | L96: =L102 -> 0 | M96: =M102 -> 0 | ... AJ96: =AJ102 -> 0
C97: 51201003112 | D97: Kantor Pusat
C98: 51201003122 | D98: Kantor Cabang
C99: 51201003132 | D99: Gudang Pusat
C100: 51201003142 | D100: Gudang Cabang
C101: 51201003192 | D101: Bangunan Permanen Lainnya
D102: SUB TOTAL BANGUNAN KERJA | F102: =SUM(F97:F101) -> 0 | G102: =SUM(G97:G101) -> 0 | H102: =SUM(H97:H101) -> 0 | I102: =SUM(I97:I101) -> 0 | J102: =SUM(J97:J101) -> 0 | K102: =SUM(K97:K101) -> 0 | L102: =SUM(L97:L101) -> 0 | M102: =SUM(M97:M101) -> 0 | ... AJ102: =SUM(AJ97:AJ101) -> 0
...

Sheet RKP CIVIL WORK
A1: RKP CIVIL WORK
A3: RENCANA KERJA PROYEK (RKP)
A4: PENAMBAHAN KAPASITAS PKS BATULAKI - LINE 3 | Q4: Analisa Kebutuhan Tiang Pancang
A6: NO | B6: URAIAN | C6: VOLUME | J6: HARGA SATUAN | K6: TOTAL | N6: Tiang Pancang uk. 25/25
C7: Panjang | D7: Lebar | E7: Tebal | F7: Jumlah | G7: Jam Kerja | H7: Hari | O7: Sat | P7: Harga KCE | Q7: Harga NBS
A9: 1 | B9: Cut & Fill | K9: =SUM(K10:K11) -> 1080000000 | N9: Tiang Pancang uk. 25/25
B10: Excavator | F10: 2 | G10: 8 | H10: 90 | J10: 500000 | K10: =F10*G10*H10*J10 -> 720000000 | N10: Middle | O10: m' | P10: 270000 | Q10: =230000 -> 230000
B11: Buldozer | F11: 1 | G11: 8 | H11: 90 | J11: 500000 | K11: =F11*G11*H11*J11 -> 360000000 | N11: Bottom | O11: m' | P11: 235000 | Q11: 200000
N12: Harga Tiang Avg | O12: m' | P12: =(P10+P11)/2 -> 252500 | Q12: =(Q10+Q11)/2 -> 215000
A13: 2 | B13: Alat Berat Konstruksi | K13: =K14 -> 720000000 | N13: By Transport Material | O13: m' | P13: 85000 | Q13: 100000
B14: Excavator | F14: 1 | G14: 8 | H14: =12*15 -> 180 | J14: 500000 | K14: =F14*G14*H14*J14 -> 720000000 | N14: Biaya Pemancangan | O14: m' | P14: 200500 | Q14: 75000
N15: By Transport Alat Pancang | Q15: =55000000/(212*8) -> 32429.245
A16: 3 | B16: Pekerjaan Tiang Pancang | C16: 8 | F16: 212 | J16: =P18 -> 538000 | K16: =C16*F16*J16 -> 912448000 | N16: Biaya Las | O16: joint | Q16: =35000/8 -> 4375
B17: Loading Ramp | N17: Handling | O17: m' | Q17: 5000
B18: Main Building I | P18: =SUM(P12:P17) -> 538000 | Q18: =SUM(Q12:Q17) -> 431804.25
B19: Main Building II
P20: =P18*C16*F16 -> 912448000 | Q20: =Q18*C16*F16 -> 732340000
A21: 4 | B21: Beton Bertulang | K21: =K22+K30 -> 16451044400
B22: Beton | F22: =SUM(F23:F28) -> 1678.678 | J22: 6000000 | K22: =F22*J22 -> 10072068000
B23: Loading Ramp | C23: 53.2 | D23: 33.8 | E23: 0.3 | F23: =C23*D23*E23 -> 539.448
B24: Main Building I | C24: 64 | D24: 14.3 | E24: 0.25 | F24: =C24*D24*E24 -> 228.8
B25: Main Building II | C25: 44 | D25: 19.3 | E25: 0.25 | F25: =C25*D25*E25 -> 212.3
B26: Pat Pit | C26: 11 | D26: 8.1 | E26: 0.3 | F26: =C26*D26*E26 -> 26.73
B27: Open Plate Concrete | E27: 0.3 | F27: =140*E27 -> 42
B28: Poer Plat, Pedestal & Balok | F28: =H28 -> 629.4 | H28: =I28*0.6 -> 629.4 | I28: 1049
B30: Besi | F30: =SUM(F31:F36) -> 335735.6 | J30: 19000 | K30: =F30*J30 -> 6378976400
F31: =F23*200 -> 107889.6
F32: =F24*200 -> 45760
F33: =F25*200 -> 42460
F34: =F26*200 -> 5346
F35: =F27*200 -> 8400
F36: =F28*200 -> 125880
A38: 5 | B38: Main Building & Supporting | K38: =K39+K40 -> 8880000000
B39: Main Building I | C39: 60 | D39: 12 | F39: =C39*D39 -> 720 | J39: 6000000 | K39: =F39*J39 -> 4320000000
B40: Main Building II | C40: 40 | D40: 19 | F40: =C40*D40 -> 760 | J40: 6000000 | K40: =F40*J40 -> 4560000000
P42: =C16*F16*P10 -> 457920000
B43: Pos Grading | C43: 4 | D43: 4 | F43: =C43*D43 -> 16 | J43: 4500000 | K43: =F43*J43 -> 72000000 | P43: 340000000
P44: =C16*F16 -> 1696
B45: Kantor Proses | C45: 3 | D45: 6 | F45: =C45*D45 -> 18 | J45: 4500000 | K45: =F45*J45 -> 81000000 | P45: =P43/P44 -> 200471.7
B47: KM/WC | C47: 3 | D47: 8 | F47: =C47*D47 -> 24 | J47: 4500000 | K47: =F47*J47 -> 108000000
B49: Longhouse G10 A | F49: 4 | J49: 1400000000 | K49: =F49*J49 -> 5600000000
K52: =K9+K13+K16+K21+K38+K43+K45+K47+K49 -> 33904492400

Sheet RKP Mekanikal
D1: PT KUMAI SENTOSA
D2: ENGINEERING MILL OPERATIONAL
B4: PEMBANGUNAN PABRIK KELAPA SAWIT LINE 3 PT BUANA KARYA BHAKTI
B5: KAPASITAS 30 TON TBS/JAM
B8: No | C8: URAIAN PEKERJAAN | E8: SPESIFIKASI | F8: JUMLAH | H8: HARGA SATUAN FABRIKASI | I8: JUMAH HARGA & INSTAL MESIN | J8: HARGA SUPPLY OWNER | K8: TOTAL HARGA | N8: ELMO & GEARMOTOR | O8: CHAIN | P8: SPROCKET
F9: QTY | G9: SAT
B11: 1 | C11: GENERAL WORKS
C12: A | D12: GA & MOBDEMOB | F12: 1 | G12: LOT | I12: 1200000000 | J12: 750000000 | K12: =I12+J12 -> 1950000000
H14: =SUM(H12:H13) -> 0 | I14: =SUM(I12:I13) -> 1200000000 | J14: =SUM(J12:J13) -> 750000000 | K14: =SUM(K12:K13) -> 1950000000
B15: 2 | C15: MECHANICAL WORKS
C16: A | D16: Fruit Reception
C17: 2 | D17: Fruit Loading Ramp No.1 dan 2 | E17: 25 Pintu, Kapasitas 15 ton/pintu lengkap dengan Hydrolik dan atap conveyor | F17: 1 | G17: Lot | H17: 2500000000 | I17: =H17*F17 -> 2500000000 | K17: =I17+J17 -> 2500000000
C18: 3 | D18: FFB Horizontal Conveyor 1 | E18: Model Scrapper. L 1200x T 1400x P 26,000mm,c/w Platform Operasional & Atap sampai platform penggerak | F18: 26 | G18: m' | H18: 23000000 | I18: =H18*F18 -> 598000000 | J18: =SUM(N18:P18) -> 343000000 | K18: =I18+J18 -> 941000000 | N18: 147000000 | O18: 135000000 | P18: 61000000
C19: 4 | D19: FFB Horizontal Conveyor 2 | E19: Model Scrapper. L 1200x T 1400x P 56,000mm,c/w Platform Operasional & Atap sampai platform penggerak | F19: 56 | G19: m' | H19: 23000000 | I19: =H19*F19 -> 1288000000 | J19: =SUM(N19:P19) -> 476000000 | K19: =I19+J19 -> 1764000000 | N19: 147000000 | O19: 268000000 | P19: 61000000
I20: =SUM(I17:I19) -> 4386000000 | J20: =SUM(J17:J19) -> 819000000 | K20: =SUM(K17:K19) -> 5205000000
C21: B | D21: Sterilizer Station
C22: 1 | D22: FFB Inclined Conveyor | E22: Model Scrapper.L 1200x T 1400x P 44,400mm, c/w Platform Operasional | F22: 44.4 | G22: m' | H22: 23000000 | I22: =H22*F22 -> 1021200000 | J22: =SUM(N22:P22) -> 426000000 | K22: =I22+J22 -> 1447200000 | N22: 147000000 | O22: 218000000 | P22: 61000000
C23: 2 | D23: FFB Distributing Conveyor c/w Chute Hydraulic | E23: Model Scrapper. L 1200x T 1400x P 22,850mm c/w Platform operasional | F23: 22.85 | G23: m' | H23: 23000000 | I23: =H23*F23 -> 5.2555e+08 | J23: =SUM(N23:P23) -> 328000000 | K23: =I23+J23 -> 853550000 | N23: 147000000 | O23: 120000000 | P23: 61000000
C24: 3 | D24: Vertical Sterilizer Cap. 27-30 Ton TBS | E24: Cap. 50M3 , Dia. 3200mm, Tebal Plate, 12mm | F24: 4 | G24: SET | H24: 120000000 | I24: =H24*F24 -> 480000000 | J24: =2050000000*4 -> 8200000000 | K24: =I24+J24 -> 8680000000
C25: 4 | D25: Vacuum Tank (Condensate Tank) | E25: Material Ms Plate.Dia.1200mm,Panjang 3000mm,Kap.11,3 M3 | F25: 4 | G25: Unit | H25: 80000000 | I25: =H25*F25 -> 320000000 | K25: =I25+J25 -> 320000000
C26: 5 | D26: Sterilizer Catwalk for 4 Sterilizer | E26: H Beam 200 x 200 | F26: 1 | G26: LOT | H26: 680000000 | I26: =H26*F26 -> 680000000 | K26: =I26+J26 -> 680000000
C27: 6 | D27: Blow Down and Blow off Chamber | E27: Matr.SUS 306 Tebal 6 6mm,.Dia.1800,Panjang.7500mm | F27: 1 | G27: Unit | H27: 300000000 | I27: =H27*F27 -> 300000000 | K27: =I27+J27 -> 300000000
C28: 7 | D28: Blow Down Exchaust Chamber | E28: Matr.SUS 306 Tebal 6 mm.Dia.1800,Panjang.7500mm | F28: 1 | G28: Unit | H28: 300000000 | I28: =H28*F28 -> 300000000 | K28: =I28+J28 -> 300000000
I30: =SUM(I22:I29) -> 3626750000 | J30: =SUM(J22:J29) -> 8954000000 | K30: =SUM(K22:K29) -> 12580750000
C31: C | D31: Threshing Station
C32: 1 | D32: SFB Auto Feeder for 4 units Sterilizer | E32: Model Scrapper. L 1800x T 1400x P 25.500mm,c/w Platform Operasional | F32: 1 | G32: Unit | H32: 765000000 | I32: =H32*F32 -> 765000000 | J32: =SUM(N32:P32) -> 340000000 | K32: =I32+J32 -> 1105000000 | N32: 147000000 | O32: 132000000 | P32: 61000000
C33: 3 | D33: Inclined Sterilized Fruit Bunch (SFB) Scrapper Conveyor | E33: Model Scrapper. L 1200x T 1400x P 23.500mm,c/w Platform Operasional | F33: 23.5 | G33: m' | H33: 23000000 | I33: =H33*F33 -> 540500000 | J33: =SUM(N33:P33) -> 331000000 | K33: =I33+J33 -> 871500000 | N33: 147000000 | O33: 123000000 | P33: 61000000
C34: 4 | D34: Distributing SFB (Chute Damper) | E34: Untuk Thresher 1 dan 2 | F34: 1 | G34: lot | H34: 55000000 | I34: =H34*F34 -> 55000000 | K34: =I34+J34 -> 55000000
C35: 5 | D35: Structure Thresher | E35: Struktur uk. 2300x5700x6000mm | F35: 2 | G35: Units | H35: 233000000 | I35: =H35*F35 -> 466000000 | K35: =I35+J35 -> 466000000
C36: 6 | D36: Thresher Drum 1&2 | E36: Dimensi 2100 x 4800 mm | F36: 2 | G36: Units | H36: 400000000 | I36: =H36*F36 -> 800000000 | J36: =SUM(N36:P36) -> 240000000 | K36: =I36+J36 -> 1040000000 | N36: =120000000*2 -> 240000000
C37: 7 | D37: Under Thresher Conveyor no. 1 & 2 | E37: Model Screw,Dia.600mm,Panjang 6.000mm | F37: 12 | G37: m' | H37: 12000000 | I37: =H37*F37 -> 144000000 | J37: =SUM(N37:P37) -> 74000000 | K37: =I37+J37 -> 218000000 | N37: =37000000*2 -> 74000000
C38: 8 | D38: Bottom Cross Conveyor | E38: Model Screw,Dia.600mm,Panjang 10,000mm | F38: 10 | G38: Unit | H38: 12000000 | I38: =H38*F38 -> 120000000 | J38: =SUM(N38:P38) -> 21000000 | K38: =I38+J38 -> 141000000 | N38: 21000000
C39: 9 | D39: Horizontal Empty Bunch Scrapper Conveyor c/w Structure, Cat Walk dan Roofing | E39: Model Scrapper. Top Deck, L 750x T 650x P 12,000mm | F39: 12 | G39: m' | H39: 21000000 | I39: =H39*F39 -> 252000000 | J39: =SUM(N39:P39) -> 79500000 | K39: =I39+J39 -> 331500000 | N39: 28000000 | O39: 38500000 | P39: 13000000
C40: 10 | D40: Inclined Empty Bunch Scrapper Conveyor No 1 c/w Structure, Cat Walk dan Roofing | E40: Model Scrapper.Bottom Deck, L 750x T 650x P 26,000mm | F40: 26 | G40: m' | H40: 21000000 | I40: =H40*F40 -> 546000000 | J40: =SUM(N40:P40) -> 129500000 | K40: =I40+J40 -> 675500000 | N40: 46000000 | O40: 70500000 | P40: 13000000
I42: =SUM(I32:I41) -> 3688500000 | J42: =SUM(J32:J41) -> 1215000000 | K42: =SUM(K32:K41) -> 4903500000
C43: D | D43: Empty Bunch Press
C44: 1 | D44: Empty Bunch Press | E44: Sinaco : Model- SBP 125-13/2 | F44: 3 | G44: Unit | H44: 20000000 | I44: =H44*F44 -> 60000000 | J44: =1323000000*3 -> 3969000000 | K44: =I44+J44 -> 4029000000
C45: 2 | D45: Empty Bunch Press Structure | E45: Dimensi 8000 mm x 8000 mm x t 3000 mm | F45: 1 | G45: Lot | H45: 250000000 | I45: =H45*F45 -> 250000000 | K45: =I45+J45 -> 250000000
C46: 3 | D46: Liquor EB Tank | E46: SS 304 6mm, Dimensi 2500mmx1500mmx t 1500mm | F46: 1 | G46: Unit | H46: 115000000 | I46: =H46*F46 -> 115000000 | K46: =I46+J46 -> 115000000
C47: 4 | D47: Liquor EB Pump | E47: Centrifugal Pump, Kap. 30 M3/Jam, Head : 30M', Ukuran Pompa 80 x 50 mm/ Motor 7.5 kw | F47: 2 | G47: Units | H47: 1500000 | I47: =H47*F47 -> 3000000 | J47: =SUM(N47:P47) -> 54000000 | K47: =I47+J47 -> 57000000 | N47: =27000000*2 -> 54000000
C48: 5 | D48: Vibrating Sludge 1 unit - Instal | E48: Vibrating Screen singgle Deck, Tapis, OD.60" | F48: 1 | G48: Unit | H48: 1500000 | I48: =H48*F48 -> 1500000 | J48: 350000000 | K48: =I48+J48 -> 351500000
C49: 6 | D49: Vertical Tank Bunch Press | E49: diameter 3.800 tinggi body 3.600 mm | F49: 1 | G49: LOT | H49: 120000000 | I49: =H49*F49 -> 120000000 | K49: =I49+J49 -> 120000000
C50: 7 | D50: Empty Bunch Press Conveyor | E50: Model Scrapper.Bottom Deck, L 750 x T 650 P 17,000mm | F50: 17 | G50: m' | H50: 21000000 | I50: =H50*F50 -> 357000000 | J50: =SUM(N50:P50) -> 91500000 | K50: =I50+J50 -> 448500000 | N50: 28000000 | O50: 50500000 | P50: 13000000
I51: =SUM(I44:I50) -> 906500000 | J51: =SUM(J44:J50) -> 4464500000 | K51: =SUM(K44:K50) -> 5371000000
C52: E | D52: Pressing Station
C53: 1 | D53: Fruit Elevator No. 1&2 | E53: 1050x850 mm x t 13,250 | F53: 2 | G53: Unit | H53: 270000000 | I53: =H53*F53 -> 540000000 | J53: =SUM(N53:P53) -> 259000000 | K53: =I53+J53 -> 799000000 | N53: =85000000*2 -> 170000000 | O53: 72600000 | P53: 16400000
C54: 2 | D54: Fruit Distributing Conveyor | E54: Model Screw,Dia.600mm,Panjang 7,000mm | F54: 7 | G54: m' | H54: 12000000 | I54: =H54*F54 -> 84000000 | J54: =SUM(N54:P54) -> 111000000 | K54: =I54+J54 -> 195000000 | N54: 22000000 | O54: 72600000 | P54: 16400000
C55: 3 | D55: Fruit Overflow Chute | E55: 800 x 400 mm, Bentuk Persegi, Ms. Plate, 4mm | F55: 1 | G55: LOT | H55: 50000000 | I55: =H55*F55 -> 50000000 | K55: =I55+J55 -> 50000000
C56: 4 | D56: Water Dilution Tank | E56: SS 304 6mm, Dimensi 2500mmx1500mmx t 1500mm | F56: 1 | G56: Unit | H56: 115000000 | I56: =H56*F56 -> 115000000 | K56: =I56+J56 -> 115000000
C57: 5 | D57: Digester & Press - P25 | E57: Kap. Digester 6000 Liter - Press 25-27 Ton FFB/hour | F57: 2 | G57: Set | H57: 60000000 | I57: =H57*F57 -> 120000000 | J57: =1500000000*F57 -> 3000000000 | K57: =I57+J57 -> 3120000000
C58: 6 | D58: Digester & Pressing Structure | E58: HB-150 Dimensi lt.press 11000x7800mm | F58: 86 | G58: m2 | H58: 14000000 | I58: =H58*F58 -> 1204000000 | K58: =I58+J58 -> 1204000000
C59: 7 | D59: Crude Oil Collecting Gutter | E59: Pipa SS sch.40,Dia,12",panjang, 7600mm | F59: 1 | G59: Unit | H59: 120000000 | I59: =H59*F59 -> 120000000 | K59: =I59+J59 -> 120000000
C60: 8 | D60: Sand Trap Tank | E60: Material SS 304 6 mm. Dia.1900, Tinggi 3600mm | F60: 1 | G60: Unit | H60: 215000000 | I60: =H60*F60 -> 215000000 | K60: =I60+J60 -> 215000000
I61: =SUM(I53:I60) -> 2448000000 | J61: =SUM(J53:J60) -> 3370000000 | K61: =SUM(K53:K60) -> 5818000000
C62: F | D62: Clarification Station
C63: 1 | D63: Alfalaval for St. Clarifikasi | E63: Pengadaan 1 Paket Kap. 45 TPH FFB | F63: 1 | G63: Lot | H63: 0 | I63: =H63*F63 -> 0 | J63: 4000000000 | K63: =I63+J63 -> 4000000000
C64: 2 | D64: Vibrating Screen Structure for 2 unit c/w Instal | E64: Vibrating Screen Double Deck, Tapis, OD.60" | F64: 2 | G64: Unit | H64: 48000000 | I64: =H64*F64 -> 96000000 | J64: 800000000 | K64: =I64+J64 -> 896000000
C65: 3 | D65: Horizontal Waste Conveyor | E65: Screw, Diameter 300 x 6000 mm | F65: 6 | G65: m' | H65: 8000000 | I65: =H65*F65 -> 48000000 | J65: =SUM(N65:P65) -> 15000000 | K65: =I65+J65 -> 63000000 | N65: 15000000
C66: 4 | D66: Inclined Waste Conveyor | E66: Screw, Diameter 300 x 8000 mm | F66: 8 | G66: m' | H66: 8000000 | I66: =H66*F66 -> 64000000 | J66: =SUM(N66:P66) -> 15000000 | K66: =I66+J66 -> 79000000 | N66: 15000000
C67: 5 | D67: Crude Oil Tank (COT) | E67: Material SS 6mm , P 3000x L 3000x T 1.800 mm | F67: 1 | G67: LOT | H67: 190000000 | I67: =H67*F67 -> 190000000 | K67: =I67+J67 -> 190000000
C68: 6 | D68: Crude Oil Tank Pumps | E68: 11 Kw | F68: 2 | G68: Unit | H68: 1500000 | I68: =H68*F68 -> 3000000 | J68: =SUM(N68:P68) -> 90000000 | K68: =I68+J68 -> 93000000 | N68: =45000000*2 -> 90000000
C69: 7 | D69: Continius Setling Tank (CST) | E69: 120 ton | F69: 1 | G69: Set | H69: 1350000000 | I69: =H69*F69 -> 1350000000 | K69: =I69+J69 -> 1350000000
C70: 8 | D70: Pure Oil Tank | E70: Kap 30 Ton Crude Oil | F70: 1 | G70: Set | H70: 400000000 | I70: =H70*F70 -> 400000000 | K70: =I70+J70 -> 400000000
C71: 9 | D71: Vibrating Sludge 1 unit - Instal | E71: Vibrating Screen singgle Deck, Tapis, OD.60" | F71: 1 | G71: Unit | H71: 1500000 | I71: =H71*F71 -> 1500000 | J71: 350000000 | K71: =I71+J71 -> 351500000
C72: 10 | D72: Sludge Tank | E72: Kap 35 Ton Sludge | F72: 1 | G72: Set | H72: 400000000 | I72: =H72*F72 -> 400000000 | K72: =I72+J72 -> 400000000
C73: 11 | D73: Sludge Tank Pump | E73: 15 KW - Kew Pump SSC | F73: 2 | G73: Unit | H73: 1500000 | I73: =H73*F73 -> 3000000 | J73: =SUM(N73:P73) -> 70000000 | K73: =I73+J73 -> 73000000 | N73: 70000000
C74: 12 | D74: Struktur Vaccum driyer | E74: HB 150 | F74: 30 | G74: m2 | H74: 14000000 | I74: =H74*F74 -> 420000000 | K74: =I74+J74 -> 420000000
C75: 13 | D75: Vacuum Oil Dried | F75: 1 | G75: Unit | H75: 8000000 | I75: =H75*F75 -> 8000000 | K75: =I75+J75 -> 8000000
C76: 14 | D76: Oil Transfer Pump (standby) | F76: 2 | G76: Unit | H76: 1500000 | I76: =H76*F76 -> 3000000 | J76: =SUM(N76:P76) -> 140000000 | K76: =I76+J76 -> 143000000 | N76: =70000000*2 -> 140000000
C77: 15 | D77: Sand Cyclone Stage 1 (SSC) | F77: 1 | G77: Set | H77: 1500000 | I77: =H77*F77 -> 1500000 | K77: =I77+J77 -> 1500000
C78: 16 | D78: Sand Cyclone Stage 2 (STC) | F78: 1 | G78: Set | H78: 1500000 | I78: =H78*F78 -> 1500000 | K78: =I78+J78 -> 1500000
C79: 17 | D79: Buffer Sludge HSS | E79: Material SS 6mm , 1500x1500x3000 mm | F79: 1 | G79: LOT | H79: 125000000 | I79: =H79*F79 -> 125000000 | K79: =I79+J79 -> 125000000
C80: 18 | D80: Buffer Hot Water Tank | E80: Material MS 6mm , 1500x1500x3000 mm | F80: 1 | G80: LOT | H80: 90000000 | I80: =H80*F80 -> 90000000 | K80: =I80+J80 -> 90000000
C81: 19 | D81: Light Phase Tank HSS | E81: Material SS 6mm , 1500x1500x3000 mm | F81: 1 | G81: LOT | H81: 125000000 | I81: =H81*F81 -> 125000000 | K81: =I81+J81 -> 125000000
C82: 20 | D82: Light Phase Tank HSS Pump | E82: 15 KW - Kew Pump STC | F82: 2 | G82: Unit | H82: 1500000 | I82: =H82*F82 -> 3000000 | J82: =SUM(N82:P82) -> 70000000 | K82: =I82+J82 -> 73000000 | N82: 70000000
C83: 21 | D83: Hot Water Tank | E83: Kap 30 Ton , 2850x4500 mm tinggi | F83: 1 | G83: LOT | H83: 134000000 | I83: =H83*F83 -> 134000000 | K83: =I83+J83 -> 134000000
C84: 22 | D84: Hot Water Tank Pump | E84: 7,5 kw | F84: 2 | G84: Unit | H84: 1500000 | I84: =H84*F84 -> 3000000 | J84: =SUM(N84:P84) -> 44000000 | K84: =I84+J84 -> 47000000 | N84: =22000000*2 -> 44000000
C85: 23 | D85: Hight Speed Separator | E85: Alfalafal | F85: 3 | G85: Unit | H85: 5000000 | I85: =H85*F85 -> 15000000 | K85: =I85+J85 -> 15000000
C86: 24 | D86: Bak Final Effluent | E86: Civil work | F86: 1 | G86: LOT | I86: =H86*F86 -> 0 | K86: =I86+J86 -> 0
C87: 25 | D87: Final Effluent Pump | E87: 15 kw | F87: 2 | G87: Unit | H87: 1500000 | I87: =H87*F87 -> 3000000 | J87: =SUM(N87:P87) -> 140000000 | K87: =I87+J87 -> 143000000 | N87: =70000000*2 -> 140000000
C88: 26 | D88: Fat-Pit Pump | E88: 11 kw | F88: 2 | G88: LOT | H88: 1500000 | I88: =H88*F88 -> 3000000 | J88: =SUM(N88:P88) -> 90000000 | K88: =I88+J88 -> 93000000 | N88: =45000000*2 -> 90000000
C89: 27 | D89: Air Compressor | E89: 2 Stage | F89: 1 | G89: Unit | H89: 0 | I89: =H89*F89 -> 0 | J89: 26000000 | K89: =I89+J89 -> 26000000
I90: =SUM(I63:I89) -> 3490500000 | J90: =SUM(J63:J89) -> 5850000000 | K90: =SUM(K63:K89) -> 9340500000
C91: G | D91: Nut & Kernel
C92: 1 | D92: Cake Breaker Conveyor No. 1 (Under Press) c/w Cat Walk | E92: Model Screw,Plate 8mm,Dia.800mm,panjang. 26,240mm | F92: 26.24 | G92: m' | H92: 34000000 | I92: =H92*F92 -> 892160000 | J92: =SUM(N92:P92) -> 51000000 | K92: =I92+J92 -> 943160000 | N92: 51000000
C93: 2 | D93: Depericarper | E93: Kap. 45 Ton TBS/Jam | F93: 1 | G93: Unit | H93: 95000000 | I93: =H93*F93 -> 95000000 | K93: =I93+J93 -> 95000000
C94: 3 | D94: Nut Polishing drum | E94: Dia. 1000mm x P 6000 mm, model roller | F94: 1 | G94: Unit | H94: 270000000 | I94: =H94*F94 -> 270000000 | J94: =SUM(N94:P94) -> 45000000 | K94: =I94+J94 -> 315000000 | N94: 45000000
C95: 4 | D95: Nut Cross Conveyor (Augher) | E95: Type Screw, Dia. 300 x 4500 mm | F95: 4.5 | G95: Unit | H95: 8000000 | I95: =H95*F95 -> 36000000 | J95: =SUM(N95:P95) -> 15000000 | K95: =I95+J95 -> 51000000 | N95: 15000000
C96: 5 | D96: Fiber Transport System (Separating Column C/W Ducting) | F96: 1 | G96: LOT | H96: 150000000 | I96: =H96*F96 -> 150000000 | K96: =I96+J96 -> 150000000
C97: 6 | D97: Fiber Cyclone | E97: Dia. 3200mm,plate 8mm Liner 4mm Creosabro | F97: 1 | G97: Unit | H97: 290000000 | I97: =H97*F97 -> 290000000 | K97: =I97+J97 -> 290000000
C98: 7 | D98: Airlock Fiber Cyclone | E98: Dia. 800,Plate 10 mm | F98: 1 | G98: Unit | H98: 35000000 | I98: =H98*F98 -> 35000000 | J98: =SUM(N98:P98) -> 31000000 | K98: =I98+J98 -> 66000000 | N98: 31000000
C99: 8 | D99: Fan Fiber Cyclone | E99: CHICAGO D-10B.36.1/2 SISW Cls. III | F99: 1 | G99: Unit | H99: 3500000 | I99: =H99*F99 -> 3500000 | J99: 135000000 | K99: =I99+J99 -> 138500000
C100: 9 | D100: Structure Fibre Cyclone C/W Platform, Cat Walk dan Ralling | E100: HB 150 jarak 8x6 meter | F100: 1 | G100: LOT | H100: 350000000 | I100: =H100*F100 -> 350000000 | K100: =I100+J100 -> 350000000
C101: 10 | D101: Nut Cyclone & Destoner, ducting set | E101: Diameter 1500 mm | F101: 1 | G101: LOT | H101: 128000000 | I101: =H101*F101 -> 128000000 | K101: =I101+J101 -> 128000000
C102: 11 | D102: Airlock Nut Cyclone | F102: 1 | G102: LOT | H102: 25000000 | I102: =H102*F102 -> 25000000 | J102: 15000000 | K102: =I102+J102 -> 40000000 | N102: 15000000
C103: 12 | D103: Nut Transport Fan & Ducting set | E103: CHICAGO D-16.LS.19 Cls. II | F103: 1 | G103: LOT | H103: 40000000 | I103: =H103*F103 -> 40000000 | J103: 106000000 | K103: =I103+J103 -> 146000000
C104: 13 | D104: Nut Grading Drum | E104: Matr.plate 8mm, dia = 1000 panjang 3600,Model center shaft | F104: 1 | G104: Unit | H104: 150000000 | I104: =H104*F104 -> 150000000 | J104: =SUM(N104:P104) -> 43000000 | K104: =I104+J104 -> 193000000 | N104: 43000000
C105: 14 | D105: Nut Hopper | E105: 5x3 | F105: 1 | G105: Unit | H105: 250000000 | I105: =H105*F105 -> 250000000 | K105: =I105+J105 -> 250000000
C106: 15 | D106: Vibrating Feeder | E106: Kapasitas 5 Ton/Jam | F106: 2 | G106: Units | H106: 1500000 | I106: =H106*F106 -> 3000000 | J106: 15000000 | K106: =I106+J106 -> 18000000
C107: 16 | D107: Ripple Mill | E107: Kap.4 Ton Nut/Jam | F107: 2 | G107: Units | H107: 3000000 | I107: =H107*F107 -> 6000000 | J107: =55000000*2 -> 110000000 | K107: =I107+J107 -> 116000000
...

Sheet RKP Elektrikal
C1: PT BUANA KARYA BHAKTI
C2: ENGINEERING MILL OPERATIONAL
B5: PEMBANGUNAN PABRIK KELAPA SAWIT LINE 3 PT BUANA KARYA BHAKTI
C6: KAPASITAS 30 TON TBS/JAM | L6: KABEL POWER TO MCC
B7: NO | C7: DESCRIPTION | D7: QUANTITY | F7: MERK | G7: SPECIFICATION | H7: UNIT PRICE | I7: TOTAL PRICE | L7: Item | M7: Description | N7: HP | O7: KW | P7: KHA | Q7: MCCB (A) | R7: Qty | T7: TYPE | W7: Merek | X7: Unit Price | Y7: Total Price | Z7: Merek | AA7: Unit Price | AB7: Total Price | AD7: 1 | AE7: LVMDP
AD8: NO | AE8: DESCRIPTION | AF8: Q T Y | AH8: BRAND
B9: I | C9: OWNER SUPPLY | L9: =1 -> 1 | M9: Kabel Power Loading Ramp | N9: =N46 -> 73.756215 | O9: =O46 -> 55 | P9: =P46 -> 130.625 | Q9: 160 | R9: =115*T9 -> 460 | S9: mtr | T9: 4 | U9: x | V9: NYY - 1 x 95 mm | Z9: Supreme | AA9: 171861 | AB9: =AA9*R9 -> 79056060 | AD9: 1 | AE9: Dimensi : 2100(H) x 8000(W) x 1000(D)mm Steel Sheet 2mm, Marine Coating RAL 7032 | AF9: 1 | AG9: UNIT | AH9: SERION
B10: A | C10: General Work & Mob | L10: =L9+1 -> 2 | M10: Kabel Power Sterilizer Station | N10: =N71 -> 211.21098 | O10: =O71 -> 157.5 | P10: =P71 -> 374.0625 | Q10: 500 | R10: =(102+15+4)*T10 -> 484 | S10: mtr | T10: 4 | U10: x | V10: NYY - 1 x 240 mm | Z10: Supreme | AA10: 433894 | AB10: =AA10*R10 -> 210004696 | AH10: Add LVMDP
B11: 1 | C11: General Work & Mob | D11: 1 | E11: LOT | H11: 180000000 | I11: =H11 -> 180000000 | L11: =L10+1 -> 3 | M11: Kabel Power Press & Digester & Thresher | N11: =N97 -> 365.42852 | O11: =O97 -> 272.5 | P11: =P97 -> 647.1875 | Q11: 800 | R11: =(10+82+35+12)*T11 -> 973 | S11: mtr | T11: 7 | U11: x | V11: NYY - 1 x 240 mm | Z11: Supreme | AA11: 433894 | AB11: =AA11*R11 -> 422178862
C12: SUB TOTAL | I12: =I11 -> 180000000 | L12: =L11+1 -> 4 | M12: Kabel Power EFB Press | N12: =N112 -> 386.61667 | O12: =O112 -> 288.3 | P12: =P112 -> 684.7125 | Q12: 800 | R12: =(102+20+55+4)*T12 -> 1267 | S12: mtr | T12: 7 | U12: x | V12: NYY - 1 x 240 mm | Z12: Supreme | AA12: 433894 | AB12: =AA12*R12 -> 549743698 | AD12: 2 | AE12: BUSBAR & SUPPORT & WIRING CONTROL | AF12: 1 | AG12: LOT | AH12: IMPORT
L13: =L12+1 -> 5 | M13: Kabel Power Kernel & Depericarper | N13: =N165 -> 509.9907 | O13: =O165 -> 380.3 | P13: =P165 -> 903.2125 | Q13: 1000 | R13: 812 | S13: mtr | T13: 7 | U13: x | V13: NYY - 1 x 300 mm | Z13: Supreme | AA13: 522477 | AB13: =AA13*R13 -> 424251324 | AD13: F | AE13: OUTGOING FEEDER :
B14: II | C14: PABRIKASI DAN INSTALASI | L14: =L13+1 -> 6 | M14: Kabel Power Klarifikasi | N14: =N210 -> 448.03548 | O14: =O210 -> 334.1 | P14: =P210 -> 793.4875 | Q14: 800 | R14: 1057 | S14: mtr | T14: 7 | U14: x | V14: NYY - 1 x 240 mm | Z14: Supreme | AA14: 433894 | AB14: =AA14*R14 -> 458625958 | AD14: 1 | AE14: MCCB+TM200D (140-200)A 3P 50kA CVS250N, (LV525452) MCC-1 ST.Loading Ramp & S | AF14: 1 | AG14: pc | AH14: Schneider
B15: A | C15: General Work & Mob | L15: =L14+1 -> 7 | M15: Kabel Power Main Ligthting | N15: - | O15: - | P15: - | Q15: 60 | R15: 130 | S15: mtr | T15: 1 | U15: x | V15: NYY - 4 x 10 mm | Z15: Supreme | AA15: 512292 | AB15: =AA15*R15 -> 66597960 | AD15: 2 | AE15: Ampere Meter Via CT(0-200)A, 96x96mm (FT-96-A) | AF15: 1 | AG15: pc | AH15: FORT
B16: 1 | C16: Transportasi Akomodasi | D16: 1 | E16: LOT | H16: 600000000 | I16: =H16 -> 600000000 | L16: =L15+1 -> 8 | M16: Kabel Power to HSS 01 | N16: =N190 -> 60.345994 | O16: =O190 -> 45 | P16: =P190 -> 106.875 | Q16: 125 | R16: 25 | S16: mtr | T16: 1 | U16: x | V16: NYY - 4 x 35 mm | Z16: Supreme | AA16: 272006 | AB16: =AA16*R16 -> 6800150 | AD16: 3 | AE16: CT. 200/5A MSY-30, Burden 2,5 VA (Class 0,5) | AF16: 1 | AG16: pc | AH16: FORT
B17: 2 | C17: Jasa dan Consumable | D17: 1 | E17: LOT | H17: 1300000000 | I17: =H17 -> 1300000000 | L17: =L16+1 -> 9 | M17: Kabel Power to HSS 02 | N17: =N192 -> 60.345994 | O17: =O192 -> 45 | P17: =P192 -> 106.875 | Q17: 125 | R17: 25 | S17: mtr | T17: 1 | U17: x | V17: NYY - 4 x 35 mm | Z17: Supreme | AA17: 272006 | AB17: =AA17*R17 -> 6800150 | AD17: 4 | AE17: MCCB+TM500D (350-500)A 3P 50kA CVS630N (LV563315) MCC-2 STERILIZER | AF17: 1 | AG17: pc | AH17: Schneider
C18: SUB TOTAL | I18: =SUM(I16:I17) -> 1900000000 | L18: =L17+1 -> 10 | M18: Kabel Power to HSS 03 | N18: =N194 -> 60.345994 | O18: =O194 -> 45 | P18: =P194 -> 106.875 | Q18: 125 | R18: 25 | S18: mtr | T18: 1 | U18: x | V18: NYY - 4 x 35 mm | Z18: Supreme | AA18: 272006 | AB18: =AA18*R18 -> 6800150 | AD18: 5 | AE18: Ampere Meter Via CT(0-500)A, 96x96mm (FT-96-A) | AF18: 1 | AG18: pc | AH18: FORT
L19: =L18+1 -> 11 | M19: Kabel Workshop | N19: - | O19: - | P19: - | Q19: 125 | R19: 21 | S19: mtr | T19: 1 | U19: x | V19: NYY - 4 x 35 mm | Z19: Supreme | AA19: 272006 | AB19: =AA19*R19 -> 5712126 | AD19: 6 | AE19: CT. 500/5A MSY-40, Burden 5 VA (Class 0,5) | AF19: 1 | AG19: pc | AH19: FORT
B20: B | C20: Pekerjaan | L20: =L19+1 -> 12 | M20: O/G from MCC-3 to Panel B. Press 01 | N20: =N100 -> 120.69199 | O20: =O100 -> 90 | P20: =P100 -> 213.75 | Q20: 250 | R20: 6 | S20: mtr | T20: 4 | U20: x | V20: NYY - 1 x 95 mm | Z20: Supreme | AA20: 171861 | AB20: =AA20*R20 -> 1031166 | AD20: 7 | AE20: MCCB 800A 3P 50kA NS800N, (33472) + Mic 2.0 Manual Operated MCC-3 ST. Thresher & Press | AF20: 1 | AG20: pc | AH20: Schneider
B21: 1 | C21: Panel LVMDP dan MCC All Stasiun | D21: 1 | E21: LOT | I21: 2500000000 | L21: =L20+1 -> 13 | M21: O/G from MCC-3 to Panel B. Press 02 | N21: =N102 -> 120.69199 | O21: =O102 -> 90 | P21: =P102 -> 213.75 | Q21: 250 | R21: 5 | S21: mtr | T21: 4 | U21: x | V21: NYY - 1 x 95 mm | Z21: Supreme | AA21: 171861 | AB21: =AA21*R21 -> 859305 | AD21: 8 | AE21: Ampere Meter Via CT(0-800)A, 96x96mm (FT-96-A) | AF21: 1 | AG21: pc | AH21: FORT
B22: 2 | C22: Add Busbar LVMDP Existing | D22: 1 | E22: LOT | I22: 1630000000 | L22: =L21+1 -> 14 | M22: O/G from MCC-3 to Panel B. Press 03 | N22: =N104 -> 120.69199 | O22: =O104 -> 90 | P22: =P104 -> 213.75 | Q22: 250 | R22: 6 | S22: mtr | T22: 4 | U22: x | V22: NYY - 1 x 95 mm | Z22: Supreme | AA22: 171861 | AB22: =AA22*R22 -> 1031166 | AD22: 9 | AE22: CT. 800/5A MSY-60, Burden 10 VA (Class 0,5) | AF22: 1 | AG22: pc | AH22: FORT
B23: 3 | C23: Kabel Power to MCC | D23: 1 | E23: LOT | F23: Supreme | H23: =AA31 -> 3000000000 | I23: =H23 -> 3000000000 | L23: =L22+1 -> 15 | M23: O/G from MLDB ke LDB-1 Loading Ramp | N23: - | O23: - | P23: - | Q23: 32 | R23: 75 | S23: mtr | T23: 1 | U23: x | V23: NYY - 4 x 4 mm | Z23: Supreme | AA23: 38801.5 | AB23: =AA23*R23 -> 2910112.5 | AD23: 10 | AE23: MCCB 800A 3P 50kA NS800N, (33472) + Mic 2.0 Manual Operated MCC-4 ST. Bunch Press | AF23: 1 | AG23: pc | AH23: Schneider
B24: 4 | C24: Kabel Power Electromotor | D24: 1 | E24: LOT | F24: Supreme | H24: =AA214 -> 4e+08 | I24: =H24 -> 4e+08 | L24: =L23+1 -> 16 | M24: O/G from MLDB ke LDB-2 Sterilizer | N24: - | O24: - | P24: - | Q24: 32 | R24: 60 | S24: mtr | T24: 1 | U24: x | V24: NYY - 4 x 4 mm | Z24: Supreme | AA24: 38801.5 | AB24: =AA24*R24 -> 2328090 | AD24: 11 | AE24: Ampere Meter Via CT(0-800)A, 96x96mm (FT-96-A) | AF24: 1 | AG24: pc | AH24: FORT
B25: 5 | C25: Penerangan Pabrik | D25: 1 | E25: LOT | H25: =V229 -> 180000000 | I25: =H25 -> 180000000 | L25: =L24+1 -> 17 | M25: O/G from MLDB ke LDB-3 Thresher & Press | N25: - | O25: - | P25: - | Q25: 32 | R25: 25 | S25: mtr | T25: 1 | U25: x | V25: NYY - 4 x 4 mm | Z25: Supreme | AA25: 38801.5 | AB25: =AA25*R25 -> 970037.5 | AD25: 12 | AE25: CT. 800/5A MSY-60, Burden 10 VA (Class 0,5) | AF25: 1 | AG25: pc | AH25: FORT
B26: 6 | C26: Lighting Protection (Penyalur Petir) | D26: 1 | E26: LOT | H26: =V244 -> 60000000 | I26: =H26 -> 60000000 | L26: =L25+1 -> 18 | M26: O/G from MLDB ke LDB-4 Bunch Press | N26: - | O26: - | P26: - | Q26: 32 | R26: 80 | S26: mtr | T26: 1 | U26: x | V26: NYY - 4 x 4 mm | Z26: Supreme | AA26: 38801.5 | AB26: =AA26*R26 -> 3104120 | AD26: 13 | AE26: MCCB (400-1000)A 3P 50kA NS1000N, (33472) + Mic 2.0 Manual Operated MCC- 5 ST. NUT & KERNEL | AF26: 1 | AG26: pc | AH26: Schneider
B27: 7 | C27: Earthing System (Grounding) | D27: 1 | E27: LOT | H27: =V305 -> 80000000 | I27: =H27 -> 80000000 | L27: =L26+1 -> 19 | M27: O/G from MLDB ke LDB-5 (Nut & Kernel) | N27: - | O27: - | P27: - | Q27: 32 | R27: 30 | S27: mtr | T27: 1 | U27: x | V27: NYY - 4 x 4 mm | Z27: Supreme | AA27: 38801.5 | AB27: =AA27*R27 -> 1164045 | AD27: 14 | AE27: Ampere Meter Via CT(0-1000)A, 96x96mm (FT-96-A) | AF27: 1 | AG27: pc | AH27: FORT
B28: 8 | C28: Supply Tray Cable | D28: 1 | E28: LOT | H28: =V292 -> 250000000 | I28: =H28 -> 250000000 | L28: =L27+1 -> 20 | M28: O/G from MLDB ke LDB-6 (Klarifikasi) | N28: - | O28: - | P28: - | Q28: 32 | R28: 15 | S28: mtr | T28: 1 | U28: x | V28: NYY - 4 x 4 mm | Z28: Supreme | AA28: 38801.5 | AB28: =AA28*R28 -> 582022.5 | AD28: 15 | AE28: CT. 1000/5A MSY-60, Burden 10 VA (Class 0,5) | AF28: 1 | AG28: pc | AH28: FORT
B29: 9 | C29: Steam Kontrol | D29: 1 | E29: LOT | H29: =V318 -> 150000000 | I29: =H29 -> 150000000 | L29: =L28+1 -> 21 | M29: Kabel Ground NYA 50, 16,10 mm | R29: 1 | S29: LOT | AA29: 105000000 | AB29: =AA29*R29 -> 105000000 | AD29: 19 | AE29: MCCB 800A 3P 50kA NS800N, (33472) + Mic 2.0 Manual Operated MCC- 6 ST. KLARIFIKASI | AF29: 1 | AG29: pc | AH29: Schneider
L30: TOTAL | AA30: =SUM(AB9:AB29) -> 2.3555512e+09 | AD30: 20 | AE30: Ampere Meter Via CT(0-800)A, 96x96mm (FT-96-A) | AF30: 1 | AG30: pc | AH30: FORT
C31: SUB TOTAL | I31: =SUM(I21:I29) -> 8250000000 | L31: TOTAL PEMBULATAN + KENAIKAN HARGA 10% + PPn 11% | AA31: =AA30*121%+149783049.815 -> 3000000000 | AD31: 21 | AE31: CT. 800/5A MSY-60, Burden 10 VA (Class 0,5) | AF31: 1 | AG31: pc | AH31: FORT
AD32: 55 | AE32: MCCB 60A 3P 25kA EZC250N3200 SDB - 03 MAIN LIGHTING DISTRIBUTION BOARD | AF32: 1 | AG32: pc | AH32: Schneider
B33: TOTAL | I33: =SUM(I12,I18,I31) -> 10330000000 | L33: KABEL POWER ELECTROMOTOR | AD33: 56 | AE33: Ampere Meter Via CT(0-200)A, 96x96mm (FT-96-A) | AF33: 1 | AG33: pc | AH33: FORT
L34: Item | M34: Description | N34: HP | O34: KW | P34: KHA | Q34: Starter | R34: Qty | T34: TYPE | W34: Merek | X34: Unit Price | Y34: Total Price | Z34: Merek | AA34: Unit Price | AB34: Total Price | AD34: 57 | AE34: CT. 60/5A MSY-30, Burden 2,5 VA (Class 0,5) | AF34: 1 | AG34: pc | AH34: FORT
L36: 1 | M36: Loading Ramp
AE37: 1 (Satu) Unit Panel CAPACITOR BANK, 700kVAR/400VAC, 14 STEP (1, 1, 1, 1, 1, 1, 1, 1, 1, 1, 1, 1, 1, 1.)
L38: 1.1 | M38: Pompa Hidrolic Power Pack No. 1 | N38: =1.34102209*O38 -> 7.3756215 | O38: 5.5 | P38: =O38*1.9*1.25 -> 13.0625 | Q38: DOL | R38: 10 | S38: mtr | T38: 1 | U38: x | V38: NYY - 4 x 2,5 mm | W38: Voksel | X38: 25695.6 | Y38: =X38*R38 -> 256956 | Z38: Supreme | AA38: 24920.4 | AB38: =AA38*R38 -> 249204
L39: 1.2 | M39: Pompa Hidrolic Power Pack No. 2 | N39: =1.34102209*O39 -> 7.3756215 | O39: 5.5 | P39: =O39*1.9*1.25 -> 13.0625 | Q39: DOL | R39: 60 | S39: mtr | T39: 1 | U39: x | V39: NYY - 4 x 2,5 mm | W39: Voksel | X39: 25695.6 | Y39: =X39*R39 -> 1541736 | Z39: Supreme | AA39: 24920.4 | AB39: =AA39*R39 -> 1495224 | AE39: Komposisi Komponen :
L40: 1.3 | M40: FFB Horizontal Conveyor No..1 | N40: =1.34102209*O40 -> 29.502486 | O40: 22 | P40: =O40*1.9*1.25 -> 52.25 | Q40: SD | R40: 20 | S40: mtr | T40: 1 | U40: x | V40: NYY - 4 x 10 mm | W40: Voksel | X40: 56011.9 | Y40: =X40*R40 -> 1120238 | Z40: Supreme | AA40: 54322.1 | AB40: =AA40*R40 -> 1086442 | AD40: 1 | AE40: LBS 800A 3P, GGL-800/3 | AF40: 1 | AG40: pc | AH40: FORT
R41: 20 | S41: mtr | T41: 1 | U41: x | V41: NYY - 3 x 10 mm | W41: Voksel | X41: 69310.5 | Y41: =X41*R41 -> 1386210 | Z41: Supreme | AA41: 67219.5 | AB41: =AA41*R41 -> 1344390 | AD41: 2 | AE41: MCCB 100A 3P 18kA EZC250F3125 | AF41: 28 | AG41: pcs | AH41: Schneider
L42: 1.4 | M42: FFB Horizontal Conveyor No..2 | N42: =1.34102209*O42 -> 29.502486 | O42: 22 | P42: =O42*1.9*1.25 -> 52.25 | Q42: SD | R42: 25 | S42: mtr | T42: 1 | U42: x | V42: NYY - 4 x 10 mm | W42: Voksel | X42: 56011.9 | Y42: =X42*R42 -> 1400297.5 | Z42: Supreme | AA42: 86674.9 | AB42: =AA42*R42 -> 2166872.5 | AD42: 3 | AE42: Contactor 3P AC220V LC1-D100M7 For 50 kVAR | AF42: 28 | AG42: pcs | AH42: Schneider
R43: 25 | S43: mtr | T43: 1 | U43: x | V43: NYY - 3 x 10 mm | W43: Voksel | X43: 69310.5 | Y43: =X43*R43 -> 1732762.5 | Z43: Supreme | AA43: 67219.5 | AB43: =AA43*R43 -> 1680487.5 | AD43: 4 | AE43: Aux. Contact LAD8N11 | AF43: 28 | AG43: pcs | AH43: Schneider
L44: 1.5 | M44: Remote | R44: =SUM(R40,R42)*2 -> 90 | S44: mtr | T44: 1 | U44: x | V44: NYY - 3 x 1,5 mm | W44: Voksel | X44: 14481.95 | Y44: =X44*R44 -> 1303375.5 | Z44: Supreme | AA44: 14045.05 | AB44: =AA44*R44 -> 1264054.5 | AD44: 5 | AE44: Capacitors 400VAC SL-2D (N415075) For 50 kVAR | AF44: 28 | AG44: pcs | AH44: Nokian
AD45: 6 | AE45: Power Factor Regulator 14 Step, 50Hz, Aux.Volt 380-415Vac (PFR 120-415-50) | AF45: 1 | AG45: pc | AH45: MIKRO
L46: TOTAL | N46: =SUM(N38:N45) -> 73.756215 | O46: =SUM(O38:O45) -> 55 | P46: =SUM(P38:P45) -> 130.625 | AB46: =SUM(AB38:AB45) -> 9286674.5 | AD46: 7 | AE46: Pilot Lamp Transformer PLR-25 / PLR 25 (25mm) AC220V R,Y,G (R,S,T) | AF46: 3 | AG46: pcs | AH46: Auspicious
L47: 2 | M47: Stasiun Sterilizer | AD47: 8 | AE47: Pilot Lamp (w/Led) AC220V SA-PL22D..Green (On) | AF47: 14 | AG47: pcs | AH47: SALZER
AD48: 9 | AE48: Pilot Lamp (w/Led) AC220V SA-PL22D..Green (Man-Auto) | AF48: 2 | AG48: pcs | AH48: SALZER
L49: 2.1 | M49: FFB Inclined Conveyor | N49: =1.34102209*O49 -> 29.502486 | O49: 22 | P49: =O49*1.9*1.25 -> 52.25 | Q49: SD | R49: 35 | S49: mtr | T49: 1 | U49: x | V49: NYY - 4 x 10 mm | W49: Voksel | X49: 56011.9 | Y49: =X49*R49 -> 1960416.5 | Z49: Supreme | AA49: 54322.1 | AB49: =AA49*R49 -> 1901273.5 | AD49: 10 | AE49: Pushbutton 1n/o XA2EA31 (Green)- On & XA2EA42 (Red)- Off | AF49: 14 | AG49: pcs | AH49: Schneider
R50: 35 | S50: mtr | T50: 1 | U50: x | V50: NYY - 3 x 10 mm | W50: Voksel | X50: 69310.5 | Y50: =X50*R50 -> 2425867.5 | Z50: Supreme | AA50: 67219.5 | AB50: =AA50*R50 -> 2352682.5 | AD50: 11 | AE50: Selector Switch SFT20-3-3, 3pss (A,O,M), 3P | AF50: 1 | AG50: pc | AH50: FORT
L51: 2.2 | M51: FFB Distributing Conveyor | N51: =1.34102209*O51 -> 14.751243 | O51: 11 | P51: =O51*1.9*1.25 -> 26.125 | Q51: SD | R51: 35 | S51: mtr | T51: 1 | U51: x | V51: NYY - 4 x 6 mm | W51: Voksel | X51: 56011.9 | Y51: =X51*R51 -> 1960416.5 | Z51: Supreme | AA51: 54322.1 | AB51: =AA51*R51 -> 1901273.5 | AD51: 12 | AE51: CT. 2000/5A MSQ-816FT, Burden 25 VA(Class 1,0) (Spite Core) | AF51: 1 | AG51: pc | AH51: FORT
R52: 35 | S52: mtr | T52: 1 | U52: x | V52: NYY - 3 x 6 mm | W52: Voksel | X52: 42713.3 | Y52: =X52*R52 -> 1494965.5 | Z52: Supreme | AA52: 41424.7 | AB52: =AA52*R52 -> 1449864.5 | AD52: 13 | AE52: Ceiling Exhaust Fan AC220V, 10 inch – FV-25TGU | AF52: 2 | AG52: pcs | AH52: Panasonic
L53: 2.3 | M53: SFB Horizontal Conveyor | N53: =1.34102209*O53 -> 29.502486 | O53: 22 | P53: =O53*1.9*1.25 -> 52.25 | Q53: Inverter | R53: 17 | S53: mtr | T53: 1 | U53: x | V53: NYY - 4 x 16 mm | W53: Voksel | X53: 56011.9 | Y53: =X53*R53 -> 952202.3 | Z53: Supreme | AA53: 133783.2 | AB53: =AA53*R53 -> 2274314.4 | AD53: 14 | AE53: Lamp Panel Led T5 5Watt (30cm) FTS - 1005L | AF53: 3 | AG53: pcs | AH53: FORT
L54: 2.4 | M54: SFB Inclined Conveyor | N54: =1.34102209*O54 -> 14.751243 | O54: 11 | P54: =O54*1.9*1.25 -> 26.125 | Q54: SD | R54: =27+11+4 -> 42 | S54: mtr | T54: 1 | U54: x | V54: NYY - 4 x 6 mm | W54: Voksel | X54: 56011.9 | Y54: =X54*R54 -> 2352499.8 | Z54: Supreme | AA54: 54322.1 | AB54: =AA54*R54 -> 2281528.2 | AD54: 15 | AE54: Limit Switch/ Micro Switch CZ-7121 | AF54: 3 | AG54: pcs | AH54: FORT
R55: =27+11+4 -> 42 | S55: mtr | T55: 1 | U55: x | V55: NYY - 3 x 6 mm | W55: Voksel | X55: 42713.3 | Y55: =X55*R55 -> 1793958.6 | Z55: Supreme | AA55: 41424.7 | AB55: =AA55*R55 -> 1739837.4 | AD55: 16 | AE55: Relay + Socket MKS2P AC220V + PF083A-E | AF55: 14 | AG55: pcs | AH55: Omron
M56: hydraulic rod | N56: =1.34102209*O56 -> 5.3640884 | O56: 4 | P56: =O56*1.9*1.25 -> 9.5 | Q56: DOL | R56: 20 | S56: mtr | T56: 1 | U56: x | V56: NYY - 4 x 2,5 mm | W56: Voksel | X56: 25695.6 | Y56: =X56*R56 -> 513912 | Z56: Supreme | AA56: 24920.4 | AB56: =AA56*R56 -> 498408 | AD56: 17 | AE56: MCB 6A 1P 6kA(IEC 60898-1) iC60N A9F74106 For Control | AF56: 7 | AG56: pcs | AH56: Schneider
L57: 2.5 | M57: hydraulic door sterilizer | W57: Voksel | X57: 0 | Y57: =U57*X57 -> 0 | AD57: 18 | AE57: MCB 6A 1P 6kA(IEC 60898-1) iC60N A9F74106 For Control | AF57: 14 | AG57: pcs | AH57: Schneider
M58: - Pump hydraulic door No..1&2 | N58: =1.34102209*O58 -> 5.3640884 | O58: 4 | P58: =O58*1.9*1.25 -> 9.5 | Q58: DOL | R58: 20 | S58: mtr | T58: 1 | U58: x | V58: NYY - 4 x 2,5 mm | W58: Voksel | X58: 25695.6 | Y58: =X58*R58 -> 513912 | Z58: Supreme | AA58: 24920.4 | AB58: =AA58*R58 -> 498408 | AD58: 19 | AE58: Accessories & Wiring material | AF58: 1 | AG58: lot | AH58: SERION
M59: - Pump hydraulic door No..3&4 | N59: =1.34102209*O59 -> 5.3640884 | O59: 4 | P59: =O59*1.9*1.25 -> 9.5 | Q59: DOL | R59: 20 | S59: mtr | T59: 1 | U59: x | V59: NYY - 4 x 2,5 mm | W59: Voksel | X59: 25695.6 | Y59: =X59*R59 -> 513912 | Z59: Supreme | AA59: 24920.4 | AB59: =AA59*R59 -> 498408
L60: 2.6 | M60: Auger Screw Conveyor rebusan No..1 | N60: =1.34102209*O60 -> 24.808909 | O60: 18.5 | P60: =O60*1.9*1.25 -> 43.9375 | Q60: SD | R60: 10 | S60: mtr | T60: 1 | U60: x | V60: NYY - 4 x 10 mm | W60: Voksel | X60: 56011.9 | Y60: =X60*R60 -> 560119 | Z60: Supreme | AA60: 54322.1 | AB60: =AA60*R60 -> 543221 | AE60: TOTAL | AF60: 1 | AG60: UNIT
R61: 10 | S61: mtr | T61: 1 | U61: x | V61: NYY - 3 x 10 mm | W61: Voksel | X61: 69310.5 | Y61: =X61*R61 -> 693105 | Z61: Supreme | AA61: 67219.5 | AB61: =AA61*R61 -> 672195
L62: 2.7 | M62: Auger Screw Conveyor rebusan No..2 | N62: =1.34102209*O62 -> 24.808909 | O62: 18.5 | P62: =O62*1.9*1.25 -> 43.9375 | Q62: SD | R62: 15 | S62: mtr | T62: 1 | U62: x | V62: NYY - 4 x 10 mm | W62: Voksel | X62: 56011.9 | Y62: =X62*R62 -> 840178.5 | Z62: Supreme | AA62: 54322.1 | AB62: =AA62*R62 -> 814831.5 | AD62: 2 | AE62: PANEL MCC - 1 LOADING RAMP & STERILIZER
R63: 15 | S63: mtr | T63: 1 | U63: x | V63: NYY - 3 x 10 mm | W63: Voksel | X63: 69310.5 | Y63: =X63*R63 -> 1039657.5 | Z63: Supreme | AA63: 67219.5 | AB63: =AA63*R63 -> 1008292.5 | AD63: NO | AE63: DESCRIPTION | AF63: Q T Y | AH63: BRAND
L64: 2.8 | M64: Auger Screw Conveyor rebusan No..3 | N64: =1.34102209*O64 -> 24.808909 | O64: 18.5 | P64: =O64*1.9*1.25 -> 43.9375 | Q64: SD | R64: 20 | S64: mtr | T64: 1 | U64: x | V64: NYY - 4 x 10 mm | W64: Voksel | X64: 56011.9 | Y64: =X64*R64 -> 1120238 | Z64: Supreme | AA64: 54322.1 | AB64: =AA64*R64 -> 1086442 | AD64: 1 | AE64: Dimensi : 1800(H) x 600(W) x 600(D)mm Steel Sheet 2mm, Marine Coating RAL 7032 | AF64: 1 | AG64: UNIT | AH64: SERION
R65: 20 | S65: mtr | T65: 1 | U65: x | V65: NYY - 3 x 10 mm | W65: Voksel | X65: 69310.5 | Y65: =X65*R65 -> 1386210 | Z65: Supreme | AA65: 67219.5 | AB65: =AA65*R65 -> 1344390 | AD65: 2 | AE65: BUSBAR & SUPPORT & WIRING CONTROL | AF65: 1 | AG65: LOT | AH65: IMPORT
L66: 2.9 | M66: Auger Screw Conveyor rebusan No..4 | N66: =1.34102209*O66 -> 24.808909 | O66: 18.5 | P66: =O66*1.9*1.25 -> 43.9375 | Q66: SD | R66: 25 | S66: mtr | T66: 1 | U66: x | V66: NYY - 4 x 10 mm | W66: Voksel | X66: 56011.9 | Y66: =X66*R66 -> 1400297.5 | Z66: Supreme | AA66: 54322.1 | AB66: =AA66*R66 -> 1358052.5
R67: 25 | S67: mtr | T67: 1 | U67: x | V67: NYY - 3 x 10 mm | W67: Voksel | X67: 69310.5 | Y67: =X67*R67 -> 1732762.5 | Z67: Supreme | AA67: 67219.5 | AB67: =AA67*R67 -> 1680487.5 | AE67: INCOMING :
L68: 2.10 | M68: Air Compresor | N68: =1.34102209*O68 -> 7.3756215 | O68: 5.5 | P68: =O68*1.9*1.25 -> 13.0625 | Q68: DOL | R68: 30 | S68: mtr | T68: 1 | U68: x | V68: NYY - 4 x 2,5 mm | W68: Voksel | X68: 25695.6 | Y68: =X68*R68 -> 770868 | Z68: Supreme | AA68: 24920.4 | AB68: =AA68*R68 -> 747612 | AD68: 1 | AE68: MCCB 160A 3P 36kA EZC250H3160 (36 kA @4150v ) | AF68: 1 | AG68: pc | AH68: Schneider
L69: 2.11 | M69: Remote | R69: =SUM(R54,R49,R51)*2 -> 224 | S69: mtr | T69: 1 | U69: x | V69: NYY - 3 x 1,5 mm | W69: Voksel | X69: 14481.95 | Y69: =X69*R69 -> 3243956.8 | Z69: Supreme | AA69: 14045.05 | AB69: =AA69*R69 -> 3146091.2 | AD69: 2 | AE69: Pilot Lamp Transformer PLR-25 / PLR 25 (25mm) AC220V R,Y,G (R,S,T) | AF69: 3 | AG69: pcs | AH69: AusPicious
AD70: 3 | AE70: Ampere Meter Via CT(0-150)A, 96x96mm (FT-96-A) | AF70: 1 | AG70: pc | AH70: FORT
L71: TOTAL | N71: =SUM(N49:N70) -> 211.21098 | O71: =SUM(O49:O70) -> 157.5 | P71: =SUM(P49:P70) -> 374.0625 | AB71: =SUM(AB49:AB70) -> 27797613 | AD71: 4 | AE71: Ampere Selector Switch 4pss (SFT20-4) | AF71: 1 | AG71: pc | AH71: FORT
L72: 3 | M72: Stasiun Thresher & Press | AD72: 5 | AE72: Volt Meter (0-500)V, 96x96mm (FT-96V) | AF72: 1 | AG72: pc | AH72: FORT
AD73: 6 | AE73: Volt Selector Switch 7pss (SFT20-7) | AF73: 1 | AG73: pc | AH73: FORT
L74: 3.1 | M74: Thresher Drump No..1 | N74: =1.34102209*O74 -> 24.808909 | O74: 18.5 | P74: =O74*1.9*1.25 -> 43.9375 | Q74: SD | R74: =23+4 -> 27 | S74: mtr | T74: 1 | U74: x | V74: NYY - 4 x 10 mm | W74: Voksel | X74: 89371.1 | Y74: =X74*R74 -> 2413019.7 | Z74: Supreme | AA74: 86674.9 | AB74: =AA74*R74 -> 2340222.3 | AD74: 7 | AE74: CT. 150/5A MSY-30, Burden 2,5 VA (Class 0,5) | AF74: 3 | AG74: pcs | AH74: FORT
R75: =23+4 -> 27 | S75: mtr | T75: 1 | U75: x | V75: NYY - 3 x 10 mm | W75: Voksel | X75: 69310.5 | Y75: =X75*R75 -> 1871383.5 | Z75: Supreme | AA75: 67219.5 | AB75: =AA75*R75 -> 1814926.5 | AD75: 8 | AE75: MCB 6A 1P 6kA(IEC 60898-1) iC60N A9F74106 For Control | AF75: 4 | AG75: pcs | AH75: Schneider
L76: 3.2 | M76: Thresher Drump No..2 | N76: =1.34102209*O76 -> 24.808909 | O76: 18.5 | P76: =O76*1.9*1.25 -> 43.9375 | Q76: SD | R76: =R75+4 -> 31 | S76: mtr | T76: 1 | U76: x | V76: NYY - 4 x 10 mm | W76: Voksel | X76: 89371.1 | Y76: =X76*R76 -> 2770504.1 | Z76: Supreme | AA76: 86674.9 | AB76: =AA76*R76 -> 2686921.9 | AD76: 9 | AE76: Fan (motor) Filter C/With Exit Filter 148,5x148,5mm (FKL6622.100) | AF76: 2 | AG76: pcs | AH76: Ten T
R77: =R75+4 -> 31 | S77: mtr | T77: 1 | U77: x | V77: NYY - 3 x 10 mm | W77: Voksel | X77: 69310.5 | Y77: =X77*R77 -> 2148625.5 | Z77: Supreme | AA77: 67219.5 | AB77: =AA77*R77 -> 2083804.5 | AD77: 10 | AE77: Exit Filter 148,5x148,5mm (FKL6622.300) | AF77: 2 | AG77: pcs | AH77: Ten T
L78: 3.3 | M78: Under Thresher Conveyor No..1 | N78: =1.34102209*O78 -> 5.3640884 | O78: 4 | P78: =O78*1.9*1.25 -> 9.5 | Q78: DOL | R78: 20 | S78: mtr | T78: 1 | U78: x | V78: NYY - 4 x 2,5 mm | W78: Voksel | X78: 25695.6 | Y78: =X78*R78 -> 513912 | Z78: Supreme | AA78: 24920.4 | AB78: =AA78*R78 -> 498408 | AD78: 11 | AE78: Lamp Panel Led T5 5Watt (30cm) FTS - 1005L | AF78: 1 | AG78: pc | AH78: FORT
L79: 3.4 | M79: Under Thresher Conveyor No..2 | N79: =1.34102209*O79 -> 5.3640884 | O79: 4 | P79: =O79*1.9*1.25 -> 9.5 | Q79: DOL | R79: 25 | S79: mtr | T79: 1 | U79: x | V79: NYY - 4 x 2,5 mm | W79: Voksel | X79: 25695.6 | Y79: =X79*R79 -> 642390 | Z79: Supreme | AA79: 24920.4 | AB79: =AA79*R79 -> 623010 | AD79: 12 | AE79: Limit Switch/ Micro Switch CZ-7121 | AF79: 1 | AG79: pc | AH79: FORT
L80: 3.5 | M80: Horizontal EBC | N80: =1.34102209*O80 -> 5.3640884 | O80: 4 | P80: =O80*1.9*1.25 -> 9.5 | Q80: DOL | R80: =25+4 -> 29 | S80: mtr | T80: 1 | U80: x | V80: NYY - 4 x 2,5 mm | W80: Voksel | X80: 25695.6 | Y80: =X80*R80 -> 745172.4 | Z80: Supreme | AA80: 24920.4 | AB80: =AA80*R80 -> 722691.6 | AD80: 13 | AE80: Mini Fuse 2A + Holder RT18 | AF80: 1 | AG80: pc | AH80: Axle
L81: 3.6 | M81: Inclined EBC | N81: =1.34102209*O81 -> 10.057666 | O81: 7.5 | P81: =O81*1.9*1.25 -> 17.8125 | Q81: SD | R81: =R80+25 -> 54 | S81: mtr | T81: 1 | U81: x | V81: NYY - 4 x 4 mm | W81: Voksel | X81: 40008.5 | Y81: =X81*R81 -> 2160459 | Z81: Supreme | AA81: 38801.5 | AB81: =AA81*R81 -> 2095281 | AD81: 14 | AE81: c/w BUSBAR + Accessories & Wiring material | AF81: 1 | AG81: lot | AH81: SERION
Q82: SD | R82: 54 | S82: mtr | T82: 1 | U82: x | V82: NYY - 4 x 4 mm | W82: Voksel | X82: 40008.5 | Y82: =X82*R82 -> 2160459 | Z82: Supreme | AA82: 38801.5 | AB82: =AA82*R82 -> 2095281 | AE82: Cable Gland PG-36 ; 22 - 32mm, White (Plastic) | AF82: 1 | AG82: pc | AH82: FORT
L83: 3.7 | M83: Bottom Cross Conveyor | N83: =1.34102209*O83 -> 7.3756215 | O83: 5.5 | P83: =O83*1.9*1.25 -> 13.0625 | Q83: DOL | R83: =31+3 -> 34 | S83: mtr | T83: 1 | U83: x | V83: NYY - 4 x 2,5 mm | W83: Voksel | X83: 25695.6 | Y83: =X83*R83 -> 873650.4 | Z83: Supreme | AA83: 24920.4 | AB83: =AA83*R83 -> 847293.6
M84: Fruit Elevator No..1 | N84: =1.34102209*O84 -> 14.751243 | O84: 11 | P84: =O84*1.9*1.25 -> 26.125 | Q84: SD | R84: 32 | S84: mtr | T84: 1 | U84: x | V84: NYY - 4 x 6 mm | W84: Voksel | X84: 56011.9 | Y84: =X84*R84 -> 1792380.8 | Z84: Supreme | AA84: 54322.1 | AB84: =AA84*R84 -> 1738307.2 | AE84: OUTGOING Motor Starter :
R85: 32 | S85: mtr | T85: 1 | U85: x | V85: NYY - 3 x 6 mm | W85: Voksel | X85: 42713.3 | Y85: =X85*R85 -> 1366825.6 | Z85: Supreme | AA85: 41424.7 | AB85: =AA85*R85 -> 1325590.4
L86: 3.9 | M86: Fruit Elevator No..2 | N86: =1.34102209*O86 -> 14.751243 | O86: 11 | P86: =O86*1.9*1.25 -> 26.125 | Q86: SD | R86: 36 | S86: mtr | T86: 1 | U86: x | V86: NYY - 4 x 6 mm | W86: Voksel | X86: 56011.9 | Y86: =X86*R86 -> 2016428.4 | Z86: Supreme | AA86: 54322.1 | AB86: =AA86*R86 -> 1955595.6 | AE86: 2(Dua) Set. DOL STARTER 5,5kW
R87: 36 | S87: mtr | T87: 1 | U87: x | V87: NYY - 3 x 6 mm | W87: Voksel | X87: 42713.3 | Y87: =X87*R87 -> 1537678.8 | Z87: Supreme | AA87: 41424.7 | AB87: =AA87*R87 -> 1491289.2 | AD87: 1 | AE87: Pompa Hidrolic LR-1
L88: 3.10 | M88: Fruit Distributing Conveyor | N88: =1.34102209*O88 -> 7.3756215 | O88: 5.5 | P88: =O88*1.9*1.25 -> 13.0625 | Q88: DOL | R88: 20 | S88: mtr | T88: 1 | U88: x | V88: NYY - 4 x 2,5 mm | W88: Voksel | X88: 25695.6 | Y88: =X88*R88 -> 513912 | Z88: Supreme | AA88: 24920.4 | AB88: =AA88*R88 -> 498408 | AD88: 2 | AE88: Pompa Hidrolic LR-2
L89: 3.11 | M89: Digester No..1 | N89: =1.34102209*O89 -> 60.345994 | O89: 45 | P89: =O89*1.9*1.25 -> 106.875 | Q89: SS | R89: 14 | S89: mtr | T89: 1 | U89: x | V89: NYY - 4 x 35 mm | W89: Voksel | X89: 288962.8 | Y89: =X89*R89 -> 4045479.2 | Z89: Supreme | AA89: 280245.2 | AB89: =AA89*R89 -> 3923432.8
L90: 3.12 | M90: Digester No..2 | N90: =1.34102209*O90 -> 60.345994 | O90: 45 | P90: =O90*1.9*1.25 -> 106.875 | Q90: SS | R90: 14 | S90: mtr | T90: 1 | U90: x | V90: NYY - 4 x 35 mm | W90: Voksel | X90: 288962.8 | Y90: =X90*R90 -> 4045479.2 | Z90: Supreme | AA90: 280245.2 | AB90: =AA90*R90 -> 3923432.8 | AD90: 1 | AE90: Motor Circuit Breaker 5,5kW (9-14)A, 50 Icu(kA) GV2L16 | AF90: 2 | AG90: pcs | AH90: Schneider
L91: 3.15 | M91: Press No..1 | N91: =1.34102209*O91 -> 60.345994 | O91: 45 | P91: =O91*1.9*1.25 -> 106.875 | Q91: SS | R91: 9 | S91: mtr | T91: 1 | U91: x | V91: NYY - 4 x 35 mm | W91: Voksel | X91: 288962.8 | Y91: =X91*R91 -> 2600665.2 | Z91: Supreme | AA91: 280245.2 | AB91: =AA91*R91 -> 2522206.8 | AD91: 2 | AE91: Contactor 3P AC220V LC1-D12M7, 5,5kW | AF91: 2 | AG91: pcs | AH91: Schneider
L92: 3.16 | M92: Press No..2 | N92: =1.34102209*O92 -> 60.345994 | O92: 45 | P92: =O92*1.9*1.25 -> 106.875 | Q92: SS | R92: 9 | S92: mtr | T92: 1 | U92: x | V92: NYY - 4 x 35 mm | W92: Voksel | X92: 288962.8 | Y92: =X92*R92 -> 2600665.2 | Z92: Supreme | AA92: 280245.2 | AB92: =AA92*R92 -> 2522206.8 | AD92: 3 | AE92: Aux. Contact LADN11 | AF92: 2 | AG92: pcs | AH92: Schneider
L93: 3.19 | M93: Power Pack Pres No..1 | N93: =1.34102209*O93 -> 2.0115331 | O93: 1.5 | P93: =O93*1.9*1.25 -> 3.5625 | Q93: DOL | R93: 9 | S93: mtr | T93: 1 | U93: x | V93: NYY - 4 x 2,5 mm | W93: Voksel | X93: 25695.6 | Y93: =X93*R93 -> 231260.4 | Z93: Supreme | AA93: 24920.4 | AB93: =AA93*R93 -> 224283.6 | AD93: 4 | AE93: TOR LRD-16 (9-13)A | AF93: 2 | AG93: pcs | AH93: Schneider
L94: 3.20 | M94: Power Pack Pres No..2 | N94: =1.34102209*O94 -> 2.0115331 | O94: 1.5 | P94: =O94*1.9*1.25 -> 3.5625 | Q94: DOL | R94: 9 | S94: mtr | T94: 1 | U94: x | V94: NYY - 4 x 2,5 mm | W94: Voksel | X94: 25695.6 | Y94: =X94*R94 -> 231260.4 | Z94: Supreme | AA94: 24920.4 | AB94: =AA94*R94 -> 224283.6 | AD94: 5 | AE94: Illuminated Pushbutton AC220V XB5-AW3. 3M5-G/4M5-R/5M5-Y On/Off | AF94: 4 | AG94: pcs | AH94: SALZER
L95: 3.23 | M95: Remote | R95: =SUM(R80,R81,R84,R86,R88)*1.5 -> 256.5 | S95: mtr | T95: 1 | U95: x | V95: NYY - 3 x 1,5 mm | W95: Voksel | X95: 14481.95 | Y95: =X95*R95 -> 3714620.2 | Z95: Supreme | AA95: 14045.05 | AB95: =AA95*R95 -> 3602555.3 | AD95: 6 | AE95: Pilot Lamp AC220V XB5-AVM5 Trip ( Yellow ) | AF95: 2 | AG95: pcs | AH95: SALZER
AD96: 7 | AE96: Selector Switch XB5-AD33, 2NO 3pss (A,O,M) | AF96: 2 | AG96: pcs | AH96: SALZER
L97: TOTAL | N97: =SUM(N74:N95) -> 365.42852 | O97: =SUM(O74:O95) -> 272.5 | P97: =SUM(P74:P95) -> 647.1875 | AB97: =SUM(AB74:AB95) -> 39759433 | AD97: 8 | AE97: Relay + Socket My-4 AC220V (1lot) | AF97: 4 | AG97: pcs | AH97: Omron
L98: 4 | M98: B. Press | AD98: 9 | AE98: Mini Fuse 2A + Holder RT18 | AF98: 2 | AG98: pcs | AH98: Axle
AD99: 10 | AE99: Accessories & Wiring Material | AF99: 1 | AG99: lot | AH99: SERION
L100: 4.1 | M100: Bunch Press No..1 | N100: =1.34102209*O100 -> 120.69199 | O100: 90 | P100: =O100*1.9*1.25 -> 213.75 | Q100: SD | R100: 11 | S100: mtr | T100: 4 | U100: x | V100: NYY - 1 x 95 mm | W100: Voksel | X100: 749455 | Y100: =X100*R100 -> 8244005 | Z100: Supreme | AA100: 171861 | AB100: =AA100*R100*T100 -> 7561884 | AE100: Cable Gland PG-21 ; 13 - 18mm, White (Plastic) | AF100: 2 | AG100: pcs | AH100: FORT
R101: 11 | S101: mtr | T101: 3 | U101: x | V101: NYY - 1 x 95 mm | W101: Voksel | X101: 561246 | Y101: =X101*R101 -> 6173706 | Z101: Supreme | AA101: 171861 | AB101: =AA101*R101*T101 -> 5671413
L102: 4.2 | M102: Bunch Press No..2 | N102: =1.34102209*O102 -> 120.69199 | O102: 90 | P102: =O102*1.9*1.25 -> 213.75 | Q102: SD | R102: 8 | S102: mtr | T102: 4 | U102: x | V102: NYY - 1 x 95 mm | W102: Voksel | X102: 749455 | Y102: =X102*R102 -> 5995640 | Z102: Supreme | AA102: 171861 | AB102: =AA102*R102*T102 -> 5499552 | AE102: 2(Dua) Set. STARTER STAR DELTA 22kW
R103: 8 | S103: mtr | T103: 3 | U103: x | V103: NYY - 1 x 95 mm | W103: Voksel | X103: 561246 | Y103: =X103*R103 -> 4489968 | Z103: Supreme | AA103: 171861 | AB103: =AA103*R103*T103 -> 4124664 | AD103: 1 | AE103: FFB Horizontal Conveyor no. 1 (Interlock dengan Conveyor satunya)
...

Sheet Realisasi (2)
B3: TIME SCHEDULE PAYMENT PEMBANGUNAN PKS PT. KUMAI SENTOSA
B4: Sd Juni 2024 | L4: Ket: | N4: Sudah Lunas
N5: Belum Lunas
O6: 2017 | Q6: 2018 | R6: 2019 | S6: 2020 | T6: 0121 | U6: 0221 | V6: 0321 | W6: 0421 | X6: 0521 | Y6: 0621 | Z6: 0721 | AA6: 0821 | AB6: 0921 | AC6: 1021 | AD6: 1121 | AE6: 1221 | AG6: 0122 | AH6: 0222 | AI6: 0322 | AJ6: 0422 | AK6: 0522 | AL6: 0622 | AM6: 0722 | AN6: 0822 | AO6: 0922 | AP6: 1022 | AQ6: 1122 | AR6: 1222 | AT6: 0123 | AU6: 0223 | AV6: 0323 | AW6: 0423 | AX6: 0523 | AY6: 0623 | AZ6: 0723 | BA6: 0823 | BB6: 0923 | BC6: 1023 | BD6: 1123 | BE6: 1223 | BG6: 0124 | BH6: 0224 | BI6: 0324 | BJ6: 0424 | BK6: 0524 | BL6: 0624 | BM6: 0724 | BN6: 0824 | BO6: 0924 | BP6: 1024 | BQ6: 1124 | BR6: 1224
B7: NO | C7: URAIAN | D7: KONTRAKTOR/ SUPPLIER | E7: BUDGET RKP | F7: NO. SPK | G7: KONTRAKTOR/ SUPPLIER | H7: VARIAN BUDGET | I7: BUDGET RAB | J7: NILAI KONTRAK | K7: REALISASI KONTRAK | L7: PEKERJAAN TAMBAHAN | M7: SISA KONTRAK | N7: CATATAN | O7: 2017 | P7: TOTAL | Q7: 2018 | R7: 2019 | S7: 2020 | T7: TAHUN 2021 | AF7: 2021 | AG7: TAHUN 2022 | AS7: 2022 | AT7: 2023 | BG7: 2024 | BT7: SD INI | BU7: CONTROL
Q8: JUMLAH | R8: JUMLAH | S8: JUMLAH | T8: JANUARI | U8: FEBRUARI | V8: MARET | W8: APRIL | X8: MEI | Y8: JUNI | Z8: JULI | AA8: AGUSTUS | AB8: SEPTEMBER | AC8: OKTOBER | AD8: NOPEMBER | AE8: DESEMBER | AF8: JUMLAH | AG8: JANUARI | AH8: FEBRUARI | AI8: MARET | AJ8: APRIL | AK8: MEI | AL8: JUNI | AM8: JULI | AN8: AGUSTUS | AO8: SEPTEMBER | AP8: OKTOBER | AQ8: NOPEMBER | AR8: DESEMBER | AS8: JUMLAH | AT8: JANUARI | AU8: FEBRUARI | AV8: MARET | AW8: APRIL | AX8: MEI | AY8: JUNI | AZ8: JULI | BA8: AGUSTUS | BB8: SEPTEMBER | BC8: OKTOBER | BD8: NOPEMBER | BE8: DESEMBER | BF8: JUMLAH | BG8: JANUARI | BH8: FEBRUARI | BI8: MARET | BJ8: APRIL | BK8: MEI | BL8: JUNI | BM8: JULI | BN8: AGUSTUS | BO8: SEPTEMBER | BP8: OKTOBER | BQ8: NOPEMBER | BR8: DESEMBER | BS8: JUMLAH | BT8: JUMLAH
B9: I | C9: CIVIL WORK
B10: A | C10: PERSIAPAN & PENGUJIAN
A11: A1 | B11: 1 | C11: Konsultan Civil Work | D11: PT. Drei Meta Dinamika | E11: 749250000 | F11: 010/SPK/KS-HO/PIPS/V/2021 | G11: PT. Drei Meta Dinamika | H11: =+IF(E11>K11,E11-K11,0) -> 4159000 | I11: 745091000 | J11: 745091000 | K11: =+O11+Q11+R11+S11+AF11+AS11+BF11+BS11 -> 745091000 | L11: 0 | M11: =J11-K11 -> 0 | N11: -Sudah Lunas | O11: =+SUMIFS(db_Sum,db_Bln,O$6,db_Kode,$A11) -> 0 | P11: =+IF(H11=0,E11-K11,0) -> 0 | Q11: =+SUMIFS(db_Sum,db_Bln,Q$6,db_Kode,$A11) -> 0 | R11: =+SUMIFS(db_Sum,db_Bln,R$6,db_Kode,$A11) -> 0 | S11: =+SUMIFS(db_Sum,db_Bln,S$6,db_Kode,$A11) -> 0 | T11: =+SUMIFS(db_Sum,db_Bln,T$6,db_Kode,$A11) -> 0 | U11: =+SUMIFS(db_Sum,db_Bln,U$6,db_Kode,$A11) -> 0 | V11: =+SUMIFS(db_Sum,db_Bln,V$6,db_Kode,$A11) -> 0 | W11: =+SUMIFS(db_Sum,db_Bln,W$6,db_Kode,$A11) -> 0 | X11: =+SUMIFS(db_Sum,db_Bln,X$6,db_Kode,$A11) -> 0 | ... AE11: =+SUMIFS(db_Sum,db_Bln,AE$6,db_Kode,$A11) -> 76010000 | AF11: =+SUM(T11:AE11) -> 304040000 | AG11: =+SUMIFS(db_Sum,db_Bln,AG$6,db_Kode,$A11) -> 153450000 | AH11: =+SUMIFS(db_Sum,db_Bln,AH$6,db_Kode,$A11) -> 0 | AJ11: =+SUMIFS(db_Sum,db_Bln,AJ$6,db_Kode,$A11) -> 0 | AK11: =+SUMIFS(db_Sum,db_Bln,AK$6,db_Kode,$A11) -> 0 | AL11: =+SUMIFS(db_Sum,db_Bln,AL$6,db_Kode,$A11) -> 0 | AM11: =+SUMIFS(db_Sum,db_Bln,AM$6,db_Kode,$A11) -> 287601000 | AN11: =+SUMIFS(db_Sum,db_Bln,AN$6,db_Kode,$A11) -> 0 | AO11: =+SUMIFS(db_Sum,db_Bln,AO$6,db_Kode,$A11) -> 0 | AP11: =+SUMIFS(db_Sum,db_Bln,AP$6,db_Kode,$A11) -> 0 | AQ11: =+SUMIFS(db_Sum,db_Bln,AQ$6,db_Kode,$A11) -> 0 | AR11: =+SUMIFS(db_Sum,db_Bln,AR$6,db_Kode,$A11) -> 0 | AS11: =+SUM(AG11:AR11) -> 441051000 | AT11: =+SUMIFS(db_Sum,db_Bln,AT$6,db_Kode,$A11) -> 0 | AU11: =+SUMIFS(db_Sum,db_Bln,AU$6,db_Kode,$A11) -> 0 | AV11: =+SUMIFS(db_Sum,db_Bln,AV$6,db_Kode,$A11) -> 0 | AW11: =+SUMIFS(db_Sum,db_Bln,AW$6,db_Kode,$A11) -> 0 | AX11: =+SUMIFS(db_Sum,db_Bln,AX$6,db_Kode,$A11) -> 0 | AY11: =+SUMIFS(db_Sum,db_Bln,AY$6,db_Kode,$A11) -> 0 | AZ11: =+SUMIFS(db_Sum,db_Bln,AZ$6,db_Kode,$A11) -> 0 | BA11: =+SUMIFS(db_Sum,db_Bln,BA$6,db_Kode,$A11) -> 0 | ... BE11: =+SUMIFS(db_Sum,db_Bln,BE$6,db_Kode,$A11) -> 0 | BF11: =+SUM(AT11:BE11) -> 0 | BG11: =+SUMIFS(db_Sum,db_Bln,BG$6,db_Kode,$A11) -> 0 | BH11: =+SUMIFS(db_Sum,db_Bln,BH$6,db_Kode,$A11) -> 0 | BI11: =+SUMIFS(db_Sum,db_Bln,BI$6,db_Kode,$A11) -> 0 | BJ11: =+SUMIFS(db_Sum,db_Bln,BJ$6,db_Kode,$A11) -> 0 | BK11: =+SUMIFS(db_Sum,db_Bln,BK$6,db_Kode,$A11) -> 0 | BL11: =+SUMIFS(db_Sum,db_Bln,BL$6,db_Kode,$A11) -> 0 | BS11: =+SUM(BG11:BR11) -> 0 | BT11: =+SUM(O11,Q11,R11,S11,AF11,AS11,BF11+BS11) -> 745091000 | BU11: =+IF(K11-BT11=0,"OK","ERROR") -> OK
A12: A2 | B12: 2 | C12: PDA Test | D12: PT. Testindo | E12: 50505000 | F12: 10/SPK/KS-PKS/MILL-HO/V/2022 | G12: PT. Testindo | H12: =+IF(E12>K12,E12-K12,0) -> 2775000 | I12: 47730000 | J12: 47730000 | K12: =+O12+Q12+R12+S12+AF12+AS12+BF12+BS12 -> 47730000 | L12: 0 | M12: =J12-K12 -> 0 | N12: -Sudah Lunas | O12: =+SUMIFS(db_Sum,db_Bln,O$6,db_Kode,$A12) -> 0 | P12: =H12 -> 2775000 | Q12: =+SUMIFS(db_Sum,db_Bln,Q$6,db_Kode,$A12) -> 0 | R12: =+SUMIFS(db_Sum,db_Bln,R$6,db_Kode,$A12) -> 0 | S12: =+SUMIFS(db_Sum,db_Bln,S$6,db_Kode,$A12) -> 0 | T12: =+SUMIFS(db_Sum,db_Bln,T$6,db_Kode,$A12) -> 0 | U12: =+SUMIFS(db_Sum,db_Bln,U$6,db_Kode,$A12) -> 0 | V12: =+SUMIFS(db_Sum,db_Bln,V$6,db_Kode,$A12) -> 0 | W12: =+SUMIFS(db_Sum,db_Bln,W$6,db_Kode,$A12) -> 0 | X12: =+SUMIFS(db_Sum,db_Bln,X$6,db_Kode,$A12) -> 0 | ... AE12: =+SUMIFS(db_Sum,db_Bln,AE$6,db_Kode,$A12) -> 0 | AF12: =+SUM(T12:AE12) -> 0 | AG12: =+SUMIFS(db_Sum,db_Bln,AG$6,db_Kode,$A12) -> 0 | AH12: =+SUMIFS(db_Sum,db_Bln,AH$6,db_Kode,$A12) -> 0 | AI12: =+SUMIFS(db_Sum,db_Bln,AI$6,db_Kode,$A12) -> 0 | AJ12: =+SUMIFS(db_Sum,db_Bln,AJ$6,db_Kode,$A12) -> 0 | AK12: =+SUMIFS(db_Sum,db_Bln,AK$6,db_Kode,$A12) -> 47730000 | AL12: =+SUMIFS(db_Sum,db_Bln,AL$6,db_Kode,$A12) -> 0 | AM12: =+SUMIFS(db_Sum,db_Bln,AM$6,db_Kode,$A12) -> 0 | AN12: =+SUMIFS(db_Sum,db_Bln,AN$6,db_Kode,$A12) -> 0 | ... AR12: =+SUMIFS(db_Sum,db_Bln,AR$6,db_Kode,$A12) -> 0 | AS12: =+SUM(AG12:AR12) -> 47730000 | AT12: =+SUMIFS(db_Sum,db_Bln,AT$6,db_Kode,$A12) -> 0 | AU12: =+SUMIFS(db_Sum,db_Bln,AU$6,db_Kode,$A12) -> 0 | AV12: =+SUMIFS(db_Sum,db_Bln,AV$6,db_Kode,$A12) -> 0 | AW12: =+SUMIFS(db_Sum,db_Bln,AW$6,db_Kode,$A12) -> 0 | AX12: =+SUMIFS(db_Sum,db_Bln,AX$6,db_Kode,$A12) -> 0 | AY12: =+SUMIFS(db_Sum,db_Bln,AY$6,db_Kode,$A12) -> 0 | AZ12: =+SUMIFS(db_Sum,db_Bln,AZ$6,db_Kode,$A12) -> 0 | BA12: =+SUMIFS(db_Sum,db_Bln,BA$6,db_Kode,$A12) -> 0 | ... BE12: =+SUMIFS(db_Sum,db_Bln,BE$6,db_Kode,$A12) -> 0 | BF12: =+SUM(AT12:BE12) -> 0 | BG12: =+SUMIFS(db_Sum,db_Bln,BG$6,db_Kode,$A12) -> 0 | BH12: =+SUMIFS(db_Sum,db_Bln,BH$6,db_Kode,$A12) -> 0 | BI12: =+SUMIFS(db_Sum,db_Bln,BI$6,db_Kode,$A12) -> 0 | BJ12: =+SUMIFS(db_Sum,db_Bln,BJ$6,db_Kode,$A12) -> 0 | BK12: =+SUMIFS(db_Sum,db_Bln,BK$6,db_Kode,$A12) -> 0 | BS12: =+SUM(BG12:BR12) -> 0 | BT12: =+SUM(O12,Q12,R12,S12,AF12,AS12,BF12+BS12) -> 47730000 | BU12: =+IF(K12-BT12=0,"OK","ERROR") -> OK
A13: A3 | B13: 3 | C13: Soil Investigasi | D13: PT. Tiyasa Total Rekayasa | E13: 295548600 | F13: 18/SPK/KS-PKS/MILL-HO/VII/2022 | G13: PT. Tiyasa Total Rekayasa | H13: =E13-K13 -> 39638100 | I13: 295548600 | J13: 295548600 | K13: 255910500 | L13: 0 | M13: 0 | N13: -Pekerjaan Final pada 86,59% (Sudah Lunas) | O13: =+SUMIFS(db_Sum,db_Bln,O$6,db_Kode,$A13) -> 0 | P13: =+IF(H13=0,E13-K13,0) -> 0 | Q13: =+SUMIFS(db_Sum,db_Bln,Q$6,db_Kode,$A13) -> 0 | R13: =+SUMIFS(db_Sum,db_Bln,R$6,db_Kode,$A13) -> 0 | S13: =+SUMIFS(db_Sum,db_Bln,S$6,db_Kode,$A13) -> 0 | T13: =+SUMIFS(db_Sum,db_Bln,T$6,db_Kode,$A13) -> 0 | U13: =+SUMIFS(db_Sum,db_Bln,U$6,db_Kode,$A13) -> 0 | V13: =+SUMIFS(db_Sum,db_Bln,V$6,db_Kode,$A13) -> 0 | W13: =+SUMIFS(db_Sum,db_Bln,W$6,db_Kode,$A13) -> 0 | X13: =+SUMIFS(db_Sum,db_Bln,X$6,db_Kode,$A13) -> 0 | ... AE13: =+SUMIFS(db_Sum,db_Bln,AE$6,db_Kode,$A13) -> 0 | AF13: =+SUM(T13:AE13) -> 0 | AG13: =+SUMIFS(db_Sum,db_Bln,AG$6,db_Kode,$A13) -> 0 | AH13: =+SUMIFS(db_Sum,db_Bln,AH$6,db_Kode,$A13) -> 0 | AI13: =+SUMIFS(db_Sum,db_Bln,AI$6,db_Kode,$A13) -> 0 | AJ13: =+SUMIFS(db_Sum,db_Bln,AJ$6,db_Kode,$A13) -> 0 | AK13: =+SUMIFS(db_Sum,db_Bln,AK$6,db_Kode,$A13) -> 0 | AL13: =+SUMIFS(db_Sum,db_Bln,AL$6,db_Kode,$A13) -> 0 | AM13: =+SUMIFS(db_Sum,db_Bln,AM$6,db_Kode,$A13) -> 147774300 | AN13: =+SUMIFS(db_Sum,db_Bln,AN$6,db_Kode,$A13) -> 0 | ... AR13: =+SUMIFS(db_Sum,db_Bln,AR$6,db_Kode,$A13) -> 0 | AS13: =+SUM(AG13:AR13) -> 262470500 | AT13: =+SUMIFS(db_Sum,db_Bln,AT$6,db_Kode,$A13) -> 0 | AU13: =+SUMIFS(db_Sum,db_Bln,AU$6,db_Kode,$A13) -> 0 | AV13: =+SUMIFS(db_Sum,db_Bln,AV$6,db_Kode,$A13) -> 0 | AW13: =+SUMIFS(db_Sum,db_Bln,AW$6,db_Kode,$A13) -> 0 | AX13: =+SUMIFS(db_Sum,db_Bln,AX$6,db_Kode,$A13) -> 0 | AY13: =+SUMIFS(db_Sum,db_Bln,AY$6,db_Kode,$A13) -> 0 | AZ13: =+SUMIFS(db_Sum,db_Bln,AZ$6,db_Kode,$A13) -> 0 | BA13: =+SUMIFS(db_Sum,db_Bln,BA$6,db_Kode,$A13) -> 0 | ... BE13: =+SUMIFS(db_Sum,db_Bln,BE$6,db_Kode,$A13) -> 0 | BF13: =+SUM(AT13:BE13) -> 0 | BG13: =+SUMIFS(db_Sum,db_Bln,BG$6,db_Kode,$A13) -> 0 | BH13: =+SUMIFS(db_Sum,db_Bln,BH$6,db_Kode,$A13) -> 0 | BI13: =+SUMIFS(db_Sum,db_Bln,BI$6,db_Kode,$A13) -> 0 | BJ13: =+SUMIFS(db_Sum,db_Bln,BJ$6,db_Kode,$A13) -> 0 | BK13: =+SUMIFS(db_Sum,db_Bln,BK$6,db_Kode,$A13) -> 0 | BS13: =+SUM(BG13:BR13) -> 0 | BT13: =+SUM(O13,Q13,R13,S13,AF13,AS13,BF13+BS13) -> 262470500 | BU13: =+IF(K13-BT13=0,"OK","ERROR") -> ERROR
C14: -Konsumsi Soil Investigasi | E14: 0 | H14: =E14-K14 -> -6560000 | I14: 0 | J14: 6560000 | K14: 6560000 | L14: 0
A15: A4 | B15: 4 | C15: Core Drill | D15: CV. Teknik Perdana | E15: 13875000 | F15: 19/SPK/KS-PKS/MILL-HO/VII/2022 | G15: CV. Teknik Perdana | H15: =E15-K15 -> -11453750 | I15: 25328750 | J15: 25328750 | K15: =+O15+Q15+R15+S15+AF15+AS15+BF15+BS15 -> 25328750 | L15: 0 | M15: =J15-K15 -> 0 | N15: -Sudah Lunas | O15: =+SUMIFS(db_Sum,db_Bln,O$6,db_Kode,$A15) -> 0 | P15: =+IF(H15=0,E15-K15,0) -> 0 | Q15: =+SUMIFS(db_Sum,db_Bln,Q$6,db_Kode,$A15) -> 0 | R15: =+SUMIFS(db_Sum,db_Bln,R$6,db_Kode,$A15) -> 0 | S15: =+SUMIFS(db_Sum,db_Bln,S$6,db_Kode,$A15) -> 0 | T15: =+SUMIFS(db_Sum,db_Bln,T$6,db_Kode,$A15) -> 0 | U15: =+SUMIFS(db_Sum,db_Bln,U$6,db_Kode,$A15) -> 0 | V15: =+SUMIFS(db_Sum,db_Bln,V$6,db_Kode,$A15) -> 0 | W15: =+SUMIFS(db_Sum,db_Bln,W$6,db_Kode,$A15) -> 0 | X15: =+SUMIFS(db_Sum,db_Bln,X$6,db_Kode,$A15) -> 0 | ... AE15: =+SUMIFS(db_Sum,db_Bln,AE$6,db_Kode,$A15) -> 0 | AF15: =+SUM(T15:AE15) -> 0 | AG15: =+SUMIFS(db_Sum,db_Bln,AG$6,db_Kode,$A15) -> 0 | AH15: =+SUMIFS(db_Sum,db_Bln,AH$6,db_Kode,$A15) -> 0 | AI15: =+SUMIFS(db_Sum,db_Bln,AI$6,db_Kode,$A15) -> 0 | AJ15: =+SUMIFS(db_Sum,db_Bln,AJ$6,db_Kode,$A15) -> 0 | AK15: =+SUMIFS(db_Sum,db_Bln,AK$6,db_Kode,$A15) -> 0 | AL15: =+SUMIFS(db_Sum,db_Bln,AL$6,db_Kode,$A15) -> 0 | AM15: =+SUMIFS(db_Sum,db_Bln,AM$6,db_Kode,$A15) -> 0 | AN15: =+SUMIFS(db_Sum,db_Bln,AN$6,db_Kode,$A15) -> 6937500 | ... AR15: =+SUMIFS(db_Sum,db_Bln,AR$6,db_Kode,$A15) -> 0 | AS15: =+SUM(AG15:AR15) -> 25328750 | AT15: =+SUMIFS(db_Sum,db_Bln,AT$6,db_Kode,$A15) -> 0 | AU15: =+SUMIFS(db_Sum,db_Bln,AU$6,db_Kode,$A15) -> 0 | AV15: =+SUMIFS(db_Sum,db_Bln,AV$6,db_Kode,$A15) -> 0 | AW15: =+SUMIFS(db_Sum,db_Bln,AW$6,db_Kode,$A15) -> 0 | AX15: =+SUMIFS(db_Sum,db_Bln,AX$6,db_Kode,$A15) -> 0 | AY15: =+SUMIFS(db_Sum,db_Bln,AY$6,db_Kode,$A15) -> 0 | AZ15: =+SUMIFS(db_Sum,db_Bln,AZ$6,db_Kode,$A15) -> 0 | BA15: =+SUMIFS(db_Sum,db_Bln,BA$6,db_Kode,$A15) -> 0 | ... BE15: =+SUMIFS(db_Sum,db_Bln,BE$6,db_Kode,$A15) -> 0 | BF15: =+SUM(AT15:BE15) -> 0 | BG15: =+SUMIFS(db_Sum,db_Bln,BG$6,db_Kode,$A15) -> 0 | BH15: =+SUMIFS(db_Sum,db_Bln,BH$6,db_Kode,$A15) -> 0 | BI15: =+SUMIFS(db_Sum,db_Bln,BI$6,db_Kode,$A15) -> 0 | BJ15: =+SUMIFS(db_Sum,db_Bln,BJ$6,db_Kode,$A15) -> 0 | BK15: =+SUMIFS(db_Sum,db_Bln,BK$6,db_Kode,$A15) -> 0 | BS15: =+SUM(BG15:BR15) -> 0 | BT15: =+SUM(O15,Q15,R15,S15,AF15,AS15,BF15+BS15) -> 25328750 | BU15: =+IF(K15-BT15=0,"OK","ERROR") -> OK
A16: A5 | B16: 5 | C16: PDA Test | D16: PT. Klaton Jaya Mandiri | E16: 39960000 | F16: 20/SPK/KS-PKS/MILL-HO/VII/2022 | G16: PT. Klaton Jaya Mandiri | H16: =E16-K16 -> 0 | I16: 39960000 | J16: 39960000 | K16: =+O16+Q16+R16+S16+AF16+AS16+BF16+BS16 -> 39960000 | L16: 0 | M16: =J16-K16 -> 0 | N16: -Sudah Lunas | O16: =+SUMIFS(db_Sum,db_Bln,O$6,db_Kode,$A16) -> 0 | P16: =+IF(H16=0,E16-K16,0) -> 0 | Q16: =+SUMIFS(db_Sum,db_Bln,Q$6,db_Kode,$A16) -> 0 | R16: =+SUMIFS(db_Sum,db_Bln,R$6,db_Kode,$A16) -> 0 | S16: =+SUMIFS(db_Sum,db_Bln,S$6,db_Kode,$A16) -> 0 | T16: =+SUMIFS(db_Sum,db_Bln,T$6,db_Kode,$A16) -> 0 | U16: =+SUMIFS(db_Sum,db_Bln,U$6,db_Kode,$A16) -> 0 | V16: =+SUMIFS(db_Sum,db_Bln,V$6,db_Kode,$A16) -> 0 | W16: =+SUMIFS(db_Sum,db_Bln,W$6,db_Kode,$A16) -> 0 | X16: =+SUMIFS(db_Sum,db_Bln,X$6,db_Kode,$A16) -> 0 | ... AE16: =+SUMIFS(db_Sum,db_Bln,AE$6,db_Kode,$A16) -> 0 | AF16: =+SUM(T16:AE16) -> 0 | AG16: =+SUMIFS(db_Sum,db_Bln,AG$6,db_Kode,$A16) -> 0 | AH16: =+SUMIFS(db_Sum,db_Bln,AH$6,db_Kode,$A16) -> 0 | AI16: =+SUMIFS(db_Sum,db_Bln,AI$6,db_Kode,$A16) -> 0 | AJ16: =+SUMIFS(db_Sum,db_Bln,AJ$6,db_Kode,$A16) -> 0 | AK16: =+SUMIFS(db_Sum,db_Bln,AK$6,db_Kode,$A16) -> 0 | AL16: =+SUMIFS(db_Sum,db_Bln,AL$6,db_Kode,$A16) -> 0 | AM16: =+SUMIFS(db_Sum,db_Bln,AM$6,db_Kode,$A16) -> 0 | AN16: =+SUMIFS(db_Sum,db_Bln,AN$6,db_Kode,$A16) -> 39960000 | ... AR16: =+SUMIFS(db_Sum,db_Bln,AR$6,db_Kode,$A16) -> 0 | AS16: =+SUM(AG16:AR16) -> 39960000 | AT16: =+SUMIFS(db_Sum,db_Bln,AT$6,db_Kode,$A16) -> 0 | AU16: =+SUMIFS(db_Sum,db_Bln,AU$6,db_Kode,$A16) -> 0 | AV16: =+SUMIFS(db_Sum,db_Bln,AV$6,db_Kode,$A16) -> 0 | AW16: =+SUMIFS(db_Sum,db_Bln,AW$6,db_Kode,$A16) -> 0 | AX16: =+SUMIFS(db_Sum,db_Bln,AX$6,db_Kode,$A16) -> 0 | AY16: =+SUMIFS(db_Sum,db_Bln,AY$6,db_Kode,$A16) -> 0 | AZ16: =+SUMIFS(db_Sum,db_Bln,AZ$6,db_Kode,$A16) -> 0 | BA16: =+SUMIFS(db_Sum,db_Bln,BA$6,db_Kode,$A16) -> 0 | ... BE16: =+SUMIFS(db_Sum,db_Bln,BE$6,db_Kode,$A16) -> 0 | BF16: =+SUM(AT16:BE16) -> 0 | BG16: =+SUMIFS(db_Sum,db_Bln,BG$6,db_Kode,$A16) -> 0 | BH16: =+SUMIFS(db_Sum,db_Bln,BH$6,db_Kode,$A16) -> 0 | BI16: =+SUMIFS(db_Sum,db_Bln,BI$6,db_Kode,$A16) -> 0 | BJ16: =+SUMIFS(db_Sum,db_Bln,BJ$6,db_Kode,$A16) -> 0 | BK16: =+SUMIFS(db_Sum,db_Bln,BK$6,db_Kode,$A16) -> 0 | BS16: =+SUM(BG16:BR16) -> 0 | BT16: =+SUM(O16,Q16,R16,S16,AF16,AS16,BF16+BS16) -> 39960000 | BU16: =+IF(K16-BT16=0,"OK","ERROR") -> OK
A17: A6 | B17: 6 | C17: Static Load Test | D17: PT. Geotes Regio Inti | E17: 111000000 | G17: PT. Geotes Regio Inti | H17: =E17-K17 -> -37740000 | I17: 148740000 | J17: 148740000 | K17: =+O17+Q17+R17+S17+AF17+AS17+BF17+BS17 -> 148740000 | L17: 0 | M17: =J17-K17 -> 0 | N17: -Sudah Lunas+Transport | O17: =+SUMIFS(db_Sum,db_Bln,O$6,db_Kode,$A17) -> 0 | P17: =+IF(H17=0,E17-K17,0) -> 0 | Q17: =+SUMIFS(db_Sum,db_Bln,Q$6,db_Kode,$A17) -> 0 | R17: =+SUMIFS(db_Sum,db_Bln,R$6,db_Kode,$A17) -> 0 | S17: =+SUMIFS(db_Sum,db_Bln,S$6,db_Kode,$A17) -> 0 | T17: =+SUMIFS(db_Sum,db_Bln,T$6,db_Kode,$A17) -> 0 | U17: =+SUMIFS(db_Sum,db_Bln,U$6,db_Kode,$A17) -> 0 | V17: =+SUMIFS(db_Sum,db_Bln,V$6,db_Kode,$A17) -> 0 | W17: =+SUMIFS(db_Sum,db_Bln,W$6,db_Kode,$A17) -> 0 | X17: =+SUMIFS(db_Sum,db_Bln,X$6,db_Kode,$A17) -> 0 | ... AE17: =+SUMIFS(db_Sum,db_Bln,AE$6,db_Kode,$A17) -> 0 | AF17: =+SUM(T17:AE17) -> 0 | AG17: =+SUMIFS(db_Sum,db_Bln,AG$6,db_Kode,$A17) -> 0 | AH17: =+SUMIFS(db_Sum,db_Bln,AH$6,db_Kode,$A17) -> 0 | AI17: =+SUMIFS(db_Sum,db_Bln,AI$6,db_Kode,$A17) -> 0 | AJ17: =+SUMIFS(db_Sum,db_Bln,AJ$6,db_Kode,$A17) -> 0 | AK17: =+SUMIFS(db_Sum,db_Bln,AK$6,db_Kode,$A17) -> 0 | AL17: =+SUMIFS(db_Sum,db_Bln,AL$6,db_Kode,$A17) -> 0 | AM17: =+SUMIFS(db_Sum,db_Bln,AM$6,db_Kode,$A17) -> 0 | AN17: =+SUMIFS(db_Sum,db_Bln,AN$6,db_Kode,$A17) -> 36075000 | ... AR17: =+SUMIFS(db_Sum,db_Bln,AR$6,db_Kode,$A17) -> 0 | AS17: =+SUM(AG17:AR17) -> 148740000 | AT17: =+SUMIFS(db_Sum,db_Bln,AT$6,db_Kode,$A17) -> 0 | AU17: =+SUMIFS(db_Sum,db_Bln,AU$6,db_Kode,$A17) -> 0 | AV17: =+SUMIFS(db_Sum,db_Bln,AV$6,db_Kode,$A17) -> 0 | AW17: =+SUMIFS(db_Sum,db_Bln,AW$6,db_Kode,$A17) -> 0 | AX17: =+SUMIFS(db_Sum,db_Bln,AX$6,db_Kode,$A17) -> 0 | AY17: =+SUMIFS(db_Sum,db_Bln,AY$6,db_Kode,$A17) -> 0 | AZ17: =+SUMIFS(db_Sum,db_Bln,AZ$6,db_Kode,$A17) -> 0 | BA17: =+SUMIFS(db_Sum,db_Bln,BA$6,db_Kode,$A17) -> 0 | ... BE17: =+SUMIFS(db_Sum,db_Bln,BE$6,db_Kode,$A17) -> 0 | BF17: =+SUM(AT17:BE17) -> 0 | BG17: =+SUMIFS(db_Sum,db_Bln,BG$6,db_Kode,$A17) -> 0 | BH17: =+SUMIFS(db_Sum,db_Bln,BH$6,db_Kode,$A17) -> 0 | BI17: =+SUMIFS(db_Sum,db_Bln,BI$6,db_Kode,$A17) -> 0 | BJ17: =+SUMIFS(db_Sum,db_Bln,BJ$6,db_Kode,$A17) -> 0 | BK17: =+SUMIFS(db_Sum,db_Bln,BK$6,db_Kode,$A17) -> 0 | BS17: =+SUM(BG17:BR17) -> 0 | BT17: =+SUM(O17,Q17,R17,S17,AF17,AS17,BF17+BS17) -> 148740000 | BU17: =+IF(K17-BT17=0,"OK","ERROR") -> OK
A18: A7 | B18: 7 | C18: Konsultan Lainnya | O18: =+SUMIFS(db_Sum,db_Bln,O$6,db_Kode,$A18) -> 0 | P18: =+IF(H18=0,E18-K18,0) -> 0 | Q18: =+SUMIFS(db_Sum,db_Bln,Q$6,db_Kode,$A18) -> 0 | R18: =+SUMIFS(db_Sum,db_Bln,R$6,db_Kode,$A18) -> 0 | S18: =+SUMIFS(db_Sum,db_Bln,S$6,db_Kode,$A18) -> 50000000 | T18: =+SUMIFS(db_Sum,db_Bln,T$6,db_Kode,$A18) -> 0 | U18: =+SUMIFS(db_Sum,db_Bln,U$6,db_Kode,$A18) -> 23650000 | V18: =+SUMIFS(db_Sum,db_Bln,V$6,db_Kode,$A18) -> 0 | W18: =+SUMIFS(db_Sum,db_Bln,W$6,db_Kode,$A18) -> 23650000 | X18: =+SUMIFS(db_Sum,db_Bln,X$6,db_Kode,$A18) -> 0 | ... AE18: =+SUMIFS(db_Sum,db_Bln,AE$6,db_Kode,$A18) -> 10000000 | AF18: =+SUM(T18:AE18) -> 87300000 | AG18: =+SUMIFS(db_Sum,db_Bln,AG$6,db_Kode,$A18) -> 0 | AH18: =+SUMIFS(db_Sum,db_Bln,AH$6,db_Kode,$A18) -> 0 | AI18: =+SUMIFS(db_Sum,db_Bln,AI$6,db_Kode,$A18) -> 0 | AJ18: =+SUMIFS(db_Sum,db_Bln,AJ$6,db_Kode,$A18) -> 0 | AK18: =+SUMIFS(db_Sum,db_Bln,AK$6,db_Kode,$A18) -> 10000000 | AL18: =+SUMIFS(db_Sum,db_Bln,AL$6,db_Kode,$A18) -> 0 | AM18: =+SUMIFS(db_Sum,db_Bln,AM$6,db_Kode,$A18) -> 0 | AN18: =+SUMIFS(db_Sum,db_Bln,AN$6,db_Kode,$A18) -> 11100000 | ... AR18: =+SUMIFS(db_Sum,db_Bln,AR$6,db_Kode,$A18) -> 0 | AS18: =+SUM(AG18:AR18) -> 32200000 | AT18: =+SUMIFS(db_Sum,db_Bln,AT$6,db_Kode,$A18) -> 0 | AU18: =+SUMIFS(db_Sum,db_Bln,AU$6,db_Kode,$A18) -> 15000000 | AV18: =+SUMIFS(db_Sum,db_Bln,AV$6,db_Kode,$A18) -> 0 | AW18: =+SUMIFS(db_Sum,db_Bln,AW$6,db_Kode,$A18) -> 15000000 | AX18: =+SUMIFS(db_Sum,db_Bln,AX$6,db_Kode,$A18) -> 0 | AY18: =+SUMIFS(db_Sum,db_Bln,AY$6,db_Kode,$A18) -> 0 | AZ18: =+SUMIFS(db_Sum,db_Bln,AZ$6,db_Kode,$A18) -> 0 | BA18: =+SUMIFS(db_Sum,db_Bln,BA$6,db_Kode,$A18) -> 0 | ... BE18: =+SUMIFS(db_Sum,db_Bln,BE$6,db_Kode,$A18) -> 0 | BF18: =+SUM(AT18:BE18) -> 30000000 | BG18: =+SUMIFS(db_Sum,db_Bln,BG$6,db_Kode,$A18) -> 0 | BH18: =+SUMIFS(db_Sum,db_Bln,BH$6,db_Kode,$A18) -> 0 | BI18: =+SUMIFS(db_Sum,db_Bln,BI$6,db_Kode,$A18) -> 0 | BJ18: =+SUMIFS(db_Sum,db_Bln,BJ$6,db_Kode,$A18) -> 0 | BK18: =+SUMIFS(db_Sum,db_Bln,BK$6,db_Kode,$A18) -> 0 | BS18: =+SUM(BG18:BR18) -> 0 | BT18: =+SUM(O18,Q18,R18,S18,AF18,AS18,BF18+BS18) -> 199500000 | BU18: =+IF(K18-BT18=0,"OK","ERROR") -> ERROR
C19: -Dr. Rusdiansyah, ST., MT. | H19: =E19-K19 -> -55000000 | I19: 55000000 | J19: 55000000 | K19: 55000000 | M19: 0 | N19: -Sudah Lunas
C20: -Joni Irawan, ST., MT. | H20: =E20-K20 -> -25000000 | I20: 25000000 | J20: 25000000 | K20: 25000000 | M20: 0 | N20: -Sudah Lunas
C21: -Said Abdurahman | H21: =E21-K21 -> -50000000 | I21: 50000000 | J21: 50000000 | K21: 50000000 | M21: 0 | N21: -Sudah Lunas
C22: -KJPP MPBRU & Rekan | H22: =E22-K22 -> -69500000 | I22: 69500000 | J22: =69500000 -> 69500000 | K22: 69500000 | M22: 0 | N22: -Sudah Lunas
A23: A8 | B23: 8 | C23: Perizinan HGB | H23: =E23-K23 -> -61580600 | J23: 61580600 | K23: =+O23+Q23+R23+S23+AF23+AS23+BF23+BS23 -> 61580600 | L23: 0 | M23: =J23-K23 -> 0 | N23: -Sudah Lunas | O23: =+SUMIFS(db_Sum,db_Bln,O$6,db_Kode,$A23) -> 0 | P23: =+IF(H23=0,E23-K23,0) -> 0 | Q23: =+SUMIFS(db_Sum,db_Bln,Q$6,db_Kode,$A23) -> 0 | R23: =+SUMIFS(db_Sum,db_Bln,R$6,db_Kode,$A23) -> 61580600 | S23: =+SUMIFS(db_Sum,db_Bln,S$6,db_Kode,$A23) -> 0 | T23: =+SUMIFS(db_Sum,db_Bln,T$6,db_Kode,$A23) -> 0 | U23: =+SUMIFS(db_Sum,db_Bln,U$6,db_Kode,$A23) -> 0 | V23: =+SUMIFS(db_Sum,db_Bln,V$6,db_Kode,$A23) -> 0 | W23: =+SUMIFS(db_Sum,db_Bln,W$6,db_Kode,$A23) -> 0 | X23: =+SUMIFS(db_Sum,db_Bln,X$6,db_Kode,$A23) -> 0 | ... AE23: =+SUMIFS(db_Sum,db_Bln,AE$6,db_Kode,$A23) -> 0 | AF23: =+SUM(T23:AE23) -> 0 | AG23: =+SUMIFS(db_Sum,db_Bln,AG$6,db_Kode,$A23) -> 0 | AH23: =+SUMIFS(db_Sum,db_Bln,AH$6,db_Kode,$A23) -> 0 | AI23: =+SUMIFS(db_Sum,db_Bln,AI$6,db_Kode,$A23) -> 0 | AJ23: =+SUMIFS(db_Sum,db_Bln,AJ$6,db_Kode,$A23) -> 0 | AK23: =+SUMIFS(db_Sum,db_Bln,AK$6,db_Kode,$A23) -> 0 | AL23: =+SUMIFS(db_Sum,db_Bln,AL$6,db_Kode,$A23) -> 0 | AM23: =+SUMIFS(db_Sum,db_Bln,AM$6,db_Kode,$A23) -> 0 | AN23: =+SUMIFS(db_Sum,db_Bln,AN$6,db_Kode,$A23) -> 0 | ... AR23: =+SUMIFS(db_Sum,db_Bln,AR$6,db_Kode,$A23) -> 0 | AS23: =+SUM(AG23:AR23) -> 0 | AT23: =+SUMIFS(db_Sum,db_Bln,AT$6,db_Kode,$A23) -> 0 | AU23: =+SUMIFS(db_Sum,db_Bln,AU$6,db_Kode,$A23) -> 0 | AV23: =+SUMIFS(db_Sum,db_Bln,AV$6,db_Kode,$A23) -> 0 | AW23: =+SUMIFS(db_Sum,db_Bln,AW$6,db_Kode,$A23) -> 0 | AX23: =+SUMIFS(db_Sum,db_Bln,AX$6,db_Kode,$A23) -> 0 | AY23: =+SUMIFS(db_Sum,db_Bln,AY$6,db_Kode,$A23) -> 0 | AZ23: =+SUMIFS(db_Sum,db_Bln,AZ$6,db_Kode,$A23) -> 0 | BA23: =+SUMIFS(db_Sum,db_Bln,BA$6,db_Kode,$A23) -> 0 | ... BE23: =+SUMIFS(db_Sum,db_Bln,BE$6,db_Kode,$A23) -> 0 | BF23: =+SUM(AT23:BE23) -> 0 | BG23: =+SUMIFS(db_Sum,db_Bln,BG$6,db_Kode,$A23) -> 0 | BH23: =+SUMIFS(db_Sum,db_Bln,BH$6,db_Kode,$A23) -> 0 | BI23: =+SUMIFS(db_Sum,db_Bln,BI$6,db_Kode,$A23) -> 0 | BJ23: =+SUMIFS(db_Sum,db_Bln,BJ$6,db_Kode,$A23) -> 0 | BK23: =+SUMIFS(db_Sum,db_Bln,BK$6,db_Kode,$A23) -> 0 | BS23: =+SUM(BG23:BR23) -> 0 | BT23: =+SUM(O23,Q23,R23,S23,AF23,AS23,BF23+BS23) -> 61580600 | BU23: =+IF(K23-BT23=0,"OK","ERROR") -> OK
A24: A9 | B24: 9 | C24: Dokumen Tender Mekanikal | D24: PT. Pasifik Arta Indonesia | E24: 0 | H24: =E24-K24 -> -187000000 | I24: 1.87e+08 | J24: 1.87e+08 | K24: =+O24+Q24+R24+S24+AF24+AS24+BF24+BS24 -> 187000000 | L24: 0 | M24: =J24-K24 -> 0 | N24: -Sudah Lunas | Q24: =+SUMIFS(db_Sum,db_Bln,Q$6,db_Kode,$A24) -> 0 | R24: =+SUMIFS(db_Sum,db_Bln,R$6,db_Kode,$A24) -> 0 | S24: =+SUMIFS(db_Sum,db_Bln,S$6,db_Kode,$A24) -> 0 | T24: =+SUMIFS(db_Sum,db_Bln,T$6,db_Kode,$A24) -> 0 | U24: =+SUMIFS(db_Sum,db_Bln,U$6,db_Kode,$A24) -> 0 | V24: =+SUMIFS(db_Sum,db_Bln,V$6,db_Kode,$A24) -> 0 | W24: =+SUMIFS(db_Sum,db_Bln,W$6,db_Kode,$A24) -> 0 | X24: =+SUMIFS(db_Sum,db_Bln,X$6,db_Kode,$A24) -> 0 | ... AE24: =+SUMIFS(db_Sum,db_Bln,AE$6,db_Kode,$A24) -> 0 | AF24: =+SUM(T24:AE24) -> 0 | AG24: =+SUMIFS(db_Sum,db_Bln,AG$6,db_Kode,$A24) -> 0 | AH24: =+SUMIFS(db_Sum,db_Bln,AH$6,db_Kode,$A24) -> 0 | AI24: =+SUMIFS(db_Sum,db_Bln,AI$6,db_Kode,$A24) -> 187000000 | AJ24: =+SUMIFS(db_Sum,db_Bln,AJ$6,db_Kode,$A24) -> 0 | AK24: =+SUMIFS(db_Sum,db_Bln,AK$6,db_Kode,$A24) -> 0 | AL24: =+SUMIFS(db_Sum,db_Bln,AL$6,db_Kode,$A24) -> 0 | AM24: =+SUMIFS(db_Sum,db_Bln,AM$6,db_Kode,$A24) -> 0 | AN24: =+SUMIFS(db_Sum,db_Bln,AN$6,db_Kode,$A24) -> 0 | ... AR24: =+SUMIFS(db_Sum,db_Bln,AR$6,db_Kode,$A24) -> 0 | AS24: =+SUM(AG24:AR24) -> 187000000 | AT24: =+SUMIFS(db_Sum,db_Bln,AT$6,db_Kode,$A24) -> 0 | AU24: =+SUMIFS(db_Sum,db_Bln,AU$6,db_Kode,$A24) -> 0 | AV24: =+SUMIFS(db_Sum,db_Bln,AV$6,db_Kode,$A24) -> 0 | AW24: =+SUMIFS(db_Sum,db_Bln,AW$6,db_Kode,$A24) -> 0 | AX24: =+SUMIFS(db_Sum,db_Bln,AX$6,db_Kode,$A24) -> 0 | AY24: =+SUMIFS(db_Sum,db_Bln,AY$6,db_Kode,$A24) -> 0 | AZ24: =+SUMIFS(db_Sum,db_Bln,AZ$6,db_Kode,$A24) -> 0 | BA24: =+SUMIFS(db_Sum,db_Bln,BA$6,db_Kode,$A24) -> 0 | ... BE24: =+SUMIFS(db_Sum,db_Bln,BE$6,db_Kode,$A24) -> 0 | BF24: =+SUM(AT24:BE24) -> 0 | BG24: =+SUMIFS(db_Sum,db_Bln,BG$6,db_Kode,$A24) -> 0 | BH24: =+SUMIFS(db_Sum,db_Bln,BH$6,db_Kode,$A24) -> 0 | BI24: =+SUMIFS(db_Sum,db_Bln,BI$6,db_Kode,$A24) -> 0 | BJ24: =+SUMIFS(db_Sum,db_Bln,BJ$6,db_Kode,$A24) -> 0 | BK24: =+SUMIFS(db_Sum,db_Bln,BK$6,db_Kode,$A24) -> 0 | BS24: =+SUM(BG24:BR24) -> 0
A25: A10 | B25: 10 | C25: Soil Investigasi | D25: PT. Tiyasa Total Rekayasa | E25: 0 | H25: =E25-K25 -> -77880000 | I25: 77880000 | J25: 77880000 | K25: =+O25+Q25+R25+S25+AF25+AS25+BF25+BS25 -> 77880000 | L25: 0 | M25: 0 | N25: -Sudah Lunas | Q25: =+SUMIFS(db_Sum,db_Bln,Q$6,db_Kode,$A25) -> 0 | R25: =+SUMIFS(db_Sum,db_Bln,R$6,db_Kode,$A25) -> 0 | S25: =+SUMIFS(db_Sum,db_Bln,S$6,db_Kode,$A25) -> 0 | T25: =+SUMIFS(db_Sum,db_Bln,T$6,db_Kode,$A25) -> 0 | U25: =+SUMIFS(db_Sum,db_Bln,U$6,db_Kode,$A25) -> 0 | V25: =+SUMIFS(db_Sum,db_Bln,V$6,db_Kode,$A25) -> 0 | W25: =+SUMIFS(db_Sum,db_Bln,W$6,db_Kode,$A25) -> 38940000 | X25: =+SUMIFS(db_Sum,db_Bln,X$6,db_Kode,$A25) -> 0 | ... AE25: =+SUMIFS(db_Sum,db_Bln,AE$6,db_Kode,$A25) -> 0 | AF25: =+SUM(T25:AE25) -> 77880000 | AG25: =+SUMIFS(db_Sum,db_Bln,AG$6,db_Kode,$A25) -> 0 | AH25: =+SUMIFS(db_Sum,db_Bln,AH$6,db_Kode,$A25) -> 0 | AI25: =+SUMIFS(db_Sum,db_Bln,AI$6,db_Kode,$A25) -> 0 | AJ25: =+SUMIFS(db_Sum,db_Bln,AJ$6,db_Kode,$A25) -> 0 | AK25: =+SUMIFS(db_Sum,db_Bln,AK$6,db_Kode,$A25) -> 0 | AL25: =+SUMIFS(db_Sum,db_Bln,AL$6,db_Kode,$A25) -> 0 | AM25: =+SUMIFS(db_Sum,db_Bln,AM$6,db_Kode,$A25) -> 0 | AN25: =+SUMIFS(db_Sum,db_Bln,AN$6,db_Kode,$A25) -> 0 | ... AR25: =+SUMIFS(db_Sum,db_Bln,AR$6,db_Kode,$A25) -> 0 | AS25: =+SUM(AG25:AR25) -> 0 | AT25: =+SUMIFS(db_Sum,db_Bln,AT$6,db_Kode,$A25) -> 0 | AU25: =+SUMIFS(db_Sum,db_Bln,AU$6,db_Kode,$A25) -> 0 | AV25: =+SUMIFS(db_Sum,db_Bln,AV$6,db_Kode,$A25) -> 0 | AW25: =+SUMIFS(db_Sum,db_Bln,AW$6,db_Kode,$A25) -> 0 | AX25: =+SUMIFS(db_Sum,db_Bln,AX$6,db_Kode,$A25) -> 0 | AY25: =+SUMIFS(db_Sum,db_Bln,AY$6,db_Kode,$A25) -> 0 | AZ25: =+SUMIFS(db_Sum,db_Bln,AZ$6,db_Kode,$A25) -> 0 | BA25: =+SUMIFS(db_Sum,db_Bln,BA$6,db_Kode,$A25) -> 0 | ... BE25: =+SUMIFS(db_Sum,db_Bln,BE$6,db_Kode,$A25) -> 0 | BF25: =+SUM(AT25:BE25) -> 0 | BG25: =+SUMIFS(db_Sum,db_Bln,BG$6,db_Kode,$A25) -> 0 | BH25: =+SUMIFS(db_Sum,db_Bln,BH$6,db_Kode,$A25) -> 0 | BI25: =+SUMIFS(db_Sum,db_Bln,BI$6,db_Kode,$A25) -> 0 | BJ25: =+SUMIFS(db_Sum,db_Bln,BJ$6,db_Kode,$A25) -> 0 | BK25: =+SUMIFS(db_Sum,db_Bln,BK$6,db_Kode,$A25) -> 0
A26: A11 | B26: 11 | C26: Survey Penyelidikan Tanah | D26: PT. Geo Inti Perkasa | E26: 0 | H26: =E26-K26 -> -385000000 | I26: 385000000 | J26: 385000000 | K26: =+O26+Q26+R26+S26+AF26+AS26+BF26+BS26 -> 385000000 | L26: 0 | M26: 0 | N26: -Sudah Lunas | Q26: =+SUMIFS(db_Sum,db_Bln,Q$6,db_Kode,$A26) -> 0 | R26: =+SUMIFS(db_Sum,db_Bln,R$6,db_Kode,$A26) -> 385000000 | S26: =+SUMIFS(db_Sum,db_Bln,S$6,db_Kode,$A26) -> 0 | T26: =+SUMIFS(db_Sum,db_Bln,T$6,db_Kode,$A26) -> 0 | U26: =+SUMIFS(db_Sum,db_Bln,U$6,db_Kode,$A26) -> 0 | V26: =+SUMIFS(db_Sum,db_Bln,V$6,db_Kode,$A26) -> 0 | W26: =+SUMIFS(db_Sum,db_Bln,W$6,db_Kode,$A26) -> 0 | X26: =+SUMIFS(db_Sum,db_Bln,X$6,db_Kode,$A26) -> 0 | ... AE26: =+SUMIFS(db_Sum,db_Bln,AE$6,db_Kode,$A26) -> 0 | AF26: =+SUM(T26:AE26) -> 0 | AG26: =+SUMIFS(db_Sum,db_Bln,AG$6,db_Kode,$A26) -> 0 | AH26: =+SUMIFS(db_Sum,db_Bln,AH$6,db_Kode,$A26) -> 0 | AI26: =+SUMIFS(db_Sum,db_Bln,AI$6,db_Kode,$A26) -> 0 | AJ26: =+SUMIFS(db_Sum,db_Bln,AJ$6,db_Kode,$A26) -> 0 | AK26: =+SUMIFS(db_Sum,db_Bln,AK$6,db_Kode,$A26) -> 0 | AL26: =+SUMIFS(db_Sum,db_Bln,AL$6,db_Kode,$A26) -> 0 | AM26: =+SUMIFS(db_Sum,db_Bln,AM$6,db_Kode,$A26) -> 0 | AN26: =+SUMIFS(db_Sum,db_Bln,AN$6,db_Kode,$A26) -> 0 | ... AR26: =+SUMIFS(db_Sum,db_Bln,AR$6,db_Kode,$A26) -> 0 | AS26: =+SUM(AG26:AR26) -> 0 | AT26: =+SUMIFS(db_Sum,db_Bln,AT$6,db_Kode,$A26) -> 0 | AU26: =+SUMIFS(db_Sum,db_Bln,AU$6,db_Kode,$A26) -> 0 | AV26: =+SUMIFS(db_Sum,db_Bln,AV$6,db_Kode,$A26) -> 0 | AW26: =+SUMIFS(db_Sum,db_Bln,AW$6,db_Kode,$A26) -> 0 | AX26: =+SUMIFS(db_Sum,db_Bln,AX$6,db_Kode,$A26) -> 0 | AY26: =+SUMIFS(db_Sum,db_Bln,AY$6,db_Kode,$A26) -> 0 | AZ26: =+SUMIFS(db_Sum,db_Bln,AZ$6,db_Kode,$A26) -> 0 | BA26: =+SUMIFS(db_Sum,db_Bln,BA$6,db_Kode,$A26) -> 0 | ... BE26: =+SUMIFS(db_Sum,db_Bln,BE$6,db_Kode,$A26) -> 0 | BF26: =+SUM(AT26:BE26) -> 0 | BG26: =+SUMIFS(db_Sum,db_Bln,BG$6,db_Kode,$A26) -> 0 | BH26: =+SUMIFS(db_Sum,db_Bln,BH$6,db_Kode,$A26) -> 0 | BI26: =+SUMIFS(db_Sum,db_Bln,BI$6,db_Kode,$A26) -> 0 | BJ26: =+SUMIFS(db_Sum,db_Bln,BJ$6,db_Kode,$A26) -> 0 | BK26: =+SUMIFS(db_Sum,db_Bln,BK$6,db_Kode,$A26) -> 0
A27: C5 | B27: 12 | C27: Pengukuran Base Meter | D27: PT. JBP | E27: 0 | H27: =E27-K27 -> -164755855 | I27: 164755855 | J27: 164755855 | K27: =+O27+Q27+R27+S27+AF27+AS27+BF27+BS27-1 -> 164755855 | L27: 0 | M27: =J27-K27 -> 0 | N27: -Sudah Lunas | Q27: =+SUMIFS(db_Sum,db_Bln,Q$6,db_Kode,$A27) -> 0 | R27: =+SUMIFS(db_Sum,db_Bln,R$6,db_Kode,$A27) -> 0 | S27: =+SUMIFS(db_Sum,db_Bln,S$6,db_Kode,$A27) -> 0 | T27: =+SUMIFS(db_Sum,db_Bln,T$6,db_Kode,$A27) -> 0 | U27: =+SUMIFS(db_Sum,db_Bln,U$6,db_Kode,$A27) -> 0 | V27: =+SUMIFS(db_Sum,db_Bln,V$6,db_Kode,$A27) -> 0 | W27: =+SUMIFS(db_Sum,db_Bln,W$6,db_Kode,$A27) -> 0 | X27: =+SUMIFS(db_Sum,db_Bln,X$6,db_Kode,$A27) -> 0 | ... AE27: =+SUMIFS(db_Sum,db_Bln,AE$6,db_Kode,$A27) -> 156446950 | AF27: =+SUM(T27:AE27) -> 156446950 | AG27: =+SUMIFS(db_Sum,db_Bln,AG$6,db_Kode,$A27) -> 0 | AH27: =+SUMIFS(db_Sum,db_Bln,AH$6,db_Kode,$A27) -> 0 | AI27: =+SUMIFS(db_Sum,db_Bln,AI$6,db_Kode,$A27) -> 0 | AJ27: =+SUMIFS(db_Sum,db_Bln,AJ$6,db_Kode,$A27) -> 0 | AK27: =+SUMIFS(db_Sum,db_Bln,AK$6,db_Kode,$A27) -> 0 | AL27: =+SUMIFS(db_Sum,db_Bln,AL$6,db_Kode,$A27) -> 0 | AM27: =+SUMIFS(db_Sum,db_Bln,AM$6,db_Kode,$A27) -> 0 | AN27: =+SUMIFS(db_Sum,db_Bln,AN$6,db_Kode,$A27) -> 0 | ... AR27: =+SUMIFS(db_Sum,db_Bln,AR$6,db_Kode,$A27) -> 0 | AS27: =+SUM(AG27:AR27) -> 0 | AT27: =+SUMIFS(db_Sum,db_Bln,AT$6,db_Kode,$A27) -> 0 | AU27: =+SUMIFS(db_Sum,db_Bln,AU$6,db_Kode,$A27) -> 0 | AV27: =+SUMIFS(db_Sum,db_Bln,AV$6,db_Kode,$A27) -> 8308906 | AW27: =+SUMIFS(db_Sum,db_Bln,AW$6,db_Kode,$A27) -> 0 | AX27: =+SUMIFS(db_Sum,db_Bln,AX$6,db_Kode,$A27) -> 0 | AY27: =+SUMIFS(db_Sum,db_Bln,AY$6,db_Kode,$A27) -> 0 | AZ27: =+SUMIFS(db_Sum,db_Bln,AZ$6,db_Kode,$A27) -> 0 | BA27: =+SUMIFS(db_Sum,db_Bln,BA$6,db_Kode,$A27) -> 0 | ... BE27: =+SUMIFS(db_Sum,db_Bln,BE$6,db_Kode,$A27) -> 0 | BF27: =+SUM(AT27:BE27) -> 8308906 | BG27: =+SUMIFS(db_Sum,db_Bln,BG$6,db_Kode,$A27) -> 0 | BH27: =+SUMIFS(db_Sum,db_Bln,BH$6,db_Kode,$A27) -> 0 | BI27: =+SUMIFS(db_Sum,db_Bln,BI$6,db_Kode,$A27) -> 0 | BJ27: =+SUMIFS(db_Sum,db_Bln,BJ$6,db_Kode,$A27) -> 0 | BK27: =+SUMIFS(db_Sum,db_Bln,BK$6,db_Kode,$A27) -> 0
A28: A12 | B28: 13 | C28: -GA (Dinas Luar dll) | H28: =E28-K28 -> -216283200 | J28: 216283200 | K28: =+O28+Q28+R28+S28+AF28+AS28+BF28+BS28 -> 216283200 | L28: 0 | M28: =J28-K28 -> 0 | N28: -Dinas Luar dan Kunjungan | O28: =+SUMIFS(db_Sum,db_Bln,O$6,db_Kode,$A28) -> 0 | P28: =+IF(H28=0,E28-K28,0) -> 0 | Q28: =+SUMIFS(db_Sum,db_Bln,Q$6,db_Kode,$A28) -> 0 | R28: =+SUMIFS(db_Sum,db_Bln,R$6,db_Kode,$A28) -> 0 | S28: =+SUMIFS(db_Sum,db_Bln,S$6,db_Kode,$A28) -> 0 | T28: =+SUMIFS(db_Sum,db_Bln,T$6,db_Kode,$A28) -> 0 | U28: =+SUMIFS(db_Sum,db_Bln,U$6,db_Kode,$A28) -> 0 | V28: =+SUMIFS(db_Sum,db_Bln,V$6,db_Kode,$A28) -> 0 | W28: =+SUMIFS(db_Sum,db_Bln,W$6,db_Kode,$A28) -> 2156000 | X28: =+SUMIFS(db_Sum,db_Bln,X$6,db_Kode,$A28) -> 0 | ... AE28: =+SUMIFS(db_Sum,db_Bln,AE$6,db_Kode,$A28) -> 13924296 | AF28: =+SUM(T28:AE28) -> 18307296 | AG28: =+SUMIFS(db_Sum,db_Bln,AG$6,db_Kode,$A28) -> 15537219 | AH28: =+SUMIFS(db_Sum,db_Bln,AH$6,db_Kode,$A28) -> 17462250 | AI28: =+SUMIFS(db_Sum,db_Bln,AI$6,db_Kode,$A28) -> 19760259 | AJ28: =+SUMIFS(db_Sum,db_Bln,AJ$6,db_Kode,$A28) -> 4680900 | AK28: =+SUMIFS(db_Sum,db_Bln,AK$6,db_Kode,$A28) -> 28198800 | AL28: =+SUMIFS(db_Sum,db_Bln,AL$6,db_Kode,$A28) -> 14919400 | AM28: =+SUMIFS(db_Sum,db_Bln,AM$6,db_Kode,$A28) -> 11143700 | AN28: =+SUMIFS(db_Sum,db_Bln,AN$6,db_Kode,$A28) -> 14314850 | ... AR28: =+SUMIFS(db_Sum,db_Bln,AR$6,db_Kode,$A28) -> 2673100 | AS28: =+SUM(AG28:AR28) -> 159632534 | AT28: =+SUMIFS(db_Sum,db_Bln,AT$6,db_Kode,$A28) -> 7969099 | AU28: =+SUMIFS(db_Sum,db_Bln,AU$6,db_Kode,$A28) -> 941100 | AV28: =+SUMIFS(db_Sum,db_Bln,AV$6,db_Kode,$A28) -> 0 | AW28: =+SUMIFS(db_Sum,db_Bln,AW$6,db_Kode,$A28) -> 0 | AX28: =+SUMIFS(db_Sum,db_Bln,AX$6,db_Kode,$A28) -> 0 | AY28: =+SUMIFS(db_Sum,db_Bln,AY$6,db_Kode,$A28) -> 5240000 | AZ28: =+SUMIFS(db_Sum,db_Bln,AZ$6,db_Kode,$A28) -> 13026800 | BA28: =+SUMIFS(db_Sum,db_Bln,BA$6,db_Kode,$A28) -> 5326371 | ... BE28: =+SUMIFS(db_Sum,db_Bln,BE$6,db_Kode,$A28) -> 0 | BF28: =+SUM(AT28:BE28) -> 38343370 | BG28: =+SUMIFS(db_Sum,db_Bln,BG$6,db_Kode,$A28) -> 0 | BH28: =+SUMIFS(db_Sum,db_Bln,BH$6,db_Kode,$A28) -> 0 | BI28: =+SUMIFS(db_Sum,db_Bln,BI$6,db_Kode,$A28) -> 0 | BJ28: =+SUMIFS(db_Sum,db_Bln,BJ$6,db_Kode,$A28) -> 0 | BK28: =+SUMIFS(db_Sum,db_Bln,BK$6,db_Kode,$A28) -> 0 | BS28: =+SUM(BG28:BR28) -> 0 | BT28: =+SUM(O28,Q28,R28,S28,AF28,AS28,BF28+BS28) -> 216283200 | BU28: =+IF(K28-BT28=0,"OK","ERROR") -> OK
C29: SUB TOTAL PERSIAPAN & PENGUJIAN | E29: =SUM(E11:E26) -> 1260138600 | H29: =SUM(H11:H23) -> -270262250 | I29: =SUM(I11:I28) -> 2316534205 | J29: =SUM(J11:J28) -> 2600958005 | K29: =SUM(K11:K28) -> 2561319905 | L29: =SUM(L11:L28) -> 0 | M29: =SUM(M11:M26) -> 0 | N29: =K29+L29+M29 -> 2561319905 | O29: =SUM(O11:O23) -> 0 | P29: =SUM(P11:P23) -> 2775000 | Q29: =SUM(Q11:Q23) -> 0 | R29: =SUM(R11:R23) -> 61580600 | S29: =SUM(S11:S23) -> 50000000 | T29: =SUM(T11:T23) -> 0 | U29: =SUM(U11:U23) -> 23650000 | V29: =SUM(V11:V23) -> 0 | ... BT29: =SUM(BT11:BT23) -> 1530400850 | BU29: =+IF(K29-BT29=0,"OK","ERROR") -> ERROR | BV29: =BT29-K29 -> -1030919055
B30: B | C30: TIANG PANCANG
A31: B1 | B31: 1 | C31: Tiang Pancang Tahap 1 | D31: PT. WIKA | E31: 5907096800 | F31: TP.01.03/WB-1H.054/2021 | G31: PT. WIKA | H31: =+IF(E31>K31,E31-K31,0) -> 0 | I31: 5907096800 | J31: 5907096800 | K31: =+O31+Q31+R31+S31+AF31+AS31+BF31+BS31 -> 5907096800 | L31: 0 | M31: =J31-K31 -> 0 | N31: -Sudah Lunas | O31: =+SUMIFS(db_Sum,db_Bln,O$6,db_Kode,$A31) -> 0 | P31: =+IF(H31=0,E31-K31,0) -> 0 | Q31: =+SUMIFS(db_Sum,db_Bln,Q$6,db_Kode,$A31) -> 0 | R31: =+SUMIFS(db_Sum,db_Bln,R$6,db_Kode,$A31) -> 0 | S31: =+SUMIFS(db_Sum,db_Bln,S$6,db_Kode,$A31) -> 0 | T31: =+SUMIFS(db_Sum,db_Bln,T$6,db_Kode,$A31) -> 0 | U31: =+SUMIFS(db_Sum,db_Bln,U$6,db_Kode,$A31) -> 0 | V31: =+SUMIFS(db_Sum,db_Bln,V$6,db_Kode,$A31) -> 0 | W31: =+SUMIFS(db_Sum,db_Bln,W$6,db_Kode,$A31) -> 0 | X31: =+SUMIFS(db_Sum,db_Bln,X$6,db_Kode,$A31) -> 0 | ... AE31: =+SUMIFS(db_Sum,db_Bln,AE$6,db_Kode,$A31) -> 0 | AF31: =+SUM(T31:AE31) -> 0 | AG31: =+SUMIFS(db_Sum,db_Bln,AG$6,db_Kode,$A31) -> 0 | AH31: =+SUMIFS(db_Sum,db_Bln,AH$6,db_Kode,$A31) -> 0 | AI31: =+SUMIFS(db_Sum,db_Bln,AI$6,db_Kode,$A31) -> 0 | AJ31: =+SUMIFS(db_Sum,db_Bln,AJ$6,db_Kode,$A31) -> 0 | AK31: =+SUMIFS(db_Sum,db_Bln,AK$6,db_Kode,$A31) -> 5907096800 | AL31: =+SUMIFS(db_Sum,db_Bln,AL$6,db_Kode,$A31) -> 0 | AM31: =+SUMIFS(db_Sum,db_Bln,AM$6,db_Kode,$A31) -> 0 | AN31: =+SUMIFS(db_Sum,db_Bln,AN$6,db_Kode,$A31) -> 0 | ... AR31: =+SUMIFS(db_Sum,db_Bln,AR$6,db_Kode,$A31) -> 0 | AS31: =+SUM(AG31:AR31) -> 5907096800 | AT31: =+SUMIFS(db_Sum,db_Bln,AT$6,db_Kode,$A31) -> 0 | AU31: =+SUMIFS(db_Sum,db_Bln,AU$6,db_Kode,$A31) -> 0 | AV31: =+SUMIFS(db_Sum,db_Bln,AV$6,db_Kode,$A31) -> 0 | AW31: =+SUMIFS(db_Sum,db_Bln,AW$6,db_Kode,$A31) -> 0 | AX31: =+SUMIFS(db_Sum,db_Bln,AX$6,db_Kode,$A31) -> 0 | AY31: =+SUMIFS(db_Sum,db_Bln,AY$6,db_Kode,$A31) -> 0 | AZ31: =+SUMIFS(db_Sum,db_Bln,AZ$6,db_Kode,$A31) -> 0 | BA31: =+SUMIFS(db_Sum,db_Bln,BA$6,db_Kode,$A31) -> 0 | ... BE31: =+SUMIFS(db_Sum,db_Bln,BE$6,db_Kode,$A31) -> 0 | BF31: =+SUM(AT31:BE31) -> 0 | BG31: =+SUMIFS(db_Sum,db_Bln,BG$6,db_Kode,$A31) -> 0 | BH31: =+SUMIFS(db_Sum,db_Bln,BH$6,db_Kode,$A31) -> 0 | BI31: =+SUMIFS(db_Sum,db_Bln,BI$6,db_Kode,$A31) -> 0 | BJ31: =+SUMIFS(db_Sum,db_Bln,BJ$6,db_Kode,$A31) -> 0 | BK31: =+SUMIFS(db_Sum,db_Bln,BK$6,db_Kode,$A31) -> 0 | BS31: =+SUM(BG31:BR31) -> 0 | BT31: =+SUM(O31,Q31,R31,S31,AF31,AS31,BF31+BS31) -> 5907096800 | BU31: =+IF(K31-BT31=0,"OK","ERROR") -> OK
A32: B2 | B32: 2 | C32: Tiang Pancang Tahap 2 | D32: PT. WIKA | E32: 5973836000 | F32: TP.01.03/WB-1H.008/2022 | G32: PT. WIKA | H32: =E32-K32 -> -38015320 | I32: 6011851320 | J32: 6011851320 | K32: =+O32+Q32+R32+S32+AF32+AS32+BF32+BS32 -> 6011851320 | L32: 0 | M32: =J32-K32 -> 0 | N32: -Sudah Lunas | O32: =+SUMIFS(db_Sum,db_Bln,O$6,db_Kode,$A32) -> 0 | P32: =+IF(H32=0,E32-K32,0) -> 0 | Q32: =+SUMIFS(db_Sum,db_Bln,Q$6,db_Kode,$A32) -> 0 | R32: =+SUMIFS(db_Sum,db_Bln,R$6,db_Kode,$A32) -> 0 | S32: =+SUMIFS(db_Sum,db_Bln,S$6,db_Kode,$A32) -> 0 | T32: =+SUMIFS(db_Sum,db_Bln,T$6,db_Kode,$A32) -> 0 | U32: =+SUMIFS(db_Sum,db_Bln,U$6,db_Kode,$A32) -> 0 | V32: =+SUMIFS(db_Sum,db_Bln,V$6,db_Kode,$A32) -> 0 | W32: =+SUMIFS(db_Sum,db_Bln,W$6,db_Kode,$A32) -> 0 | X32: =+SUMIFS(db_Sum,db_Bln,X$6,db_Kode,$A32) -> 0 | ... AE32: =+SUMIFS(db_Sum,db_Bln,AE$6,db_Kode,$A32) -> 0 | AF32: =+SUM(T32:AE32) -> 0 | AG32: =+SUMIFS(db_Sum,db_Bln,AG$6,db_Kode,$A32) -> 0 | AH32: =+SUMIFS(db_Sum,db_Bln,AH$6,db_Kode,$A32) -> 0 | AI32: =+SUMIFS(db_Sum,db_Bln,AI$6,db_Kode,$A32) -> 0 | AJ32: =+SUMIFS(db_Sum,db_Bln,AJ$6,db_Kode,$A32) -> 0 | AK32: =+SUMIFS(db_Sum,db_Bln,AK$6,db_Kode,$A32) -> 6011851320 | AL32: =+SUMIFS(db_Sum,db_Bln,AL$6,db_Kode,$A32) -> 0 | AM32: =+SUMIFS(db_Sum,db_Bln,AM$6,db_Kode,$A32) -> 0 | AN32: =+SUMIFS(db_Sum,db_Bln,AN$6,db_Kode,$A32) -> 0 | ... AR32: =+SUMIFS(db_Sum,db_Bln,AR$6,db_Kode,$A32) -> 0 | AS32: =+SUM(AG32:AR32) -> 6011851320 | AT32: =+SUMIFS(db_Sum,db_Bln,AT$6,db_Kode,$A32) -> 0 | AU32: =+SUMIFS(db_Sum,db_Bln,AU$6,db_Kode,$A32) -> 0 | AV32: =+SUMIFS(db_Sum,db_Bln,AV$6,db_Kode,$A32) -> 0 | AW32: =+SUMIFS(db_Sum,db_Bln,AW$6,db_Kode,$A32) -> 0 | AX32: =+SUMIFS(db_Sum,db_Bln,AX$6,db_Kode,$A32) -> 0 | AY32: =+SUMIFS(db_Sum,db_Bln,AY$6,db_Kode,$A32) -> 0 | AZ32: =+SUMIFS(db_Sum,db_Bln,AZ$6,db_Kode,$A32) -> 0 | BA32: =+SUMIFS(db_Sum,db_Bln,BA$6,db_Kode,$A32) -> 0 | ... BE32: =+SUMIFS(db_Sum,db_Bln,BE$6,db_Kode,$A32) -> 0 | BF32: =+SUM(AT32:BE32) -> 0 | BG32: =+SUMIFS(db_Sum,db_Bln,BG$6,db_Kode,$A32) -> 0 | BH32: =+SUMIFS(db_Sum,db_Bln,BH$6,db_Kode,$A32) -> 0 | BI32: =+SUMIFS(db_Sum,db_Bln,BI$6,db_Kode,$A32) -> 0 | BJ32: =+SUMIFS(db_Sum,db_Bln,BJ$6,db_Kode,$A32) -> 0 | BK32: =+SUMIFS(db_Sum,db_Bln,BK$6,db_Kode,$A32) -> 0 | BS32: =+SUM(BG32:BR32) -> 0 | BT32: =+SUM(O32,Q32,R32,S32,AF32,AS32,BF32+BS32) -> 6011851320 | BU32: =+IF(K32-BT32=0,"OK","ERROR") -> OK
A33: B3 | B33: 3 | C33: Tiang Pancang Tahap 3 | D33: PT. WIKA | E33: 366930480 | F33: TP.01.03/WB-1H.014/2022 | G33: PT. WIKA | H33: =+IF(E33>K33,E33-K33,0) -> 0 | I33: 366930480 | J33: 366930480 | K33: =+O33+Q33+R33+S33+AF33+AS33+BF33+BS33 -> 366930480 | L33: 0 | M33: =J33-K33 -> 0 | N33: -Sudah Lunas | O33: =+SUMIFS(db_Sum,db_Bln,O$6,db_Kode,$A33) -> 0 | P33: =+IF(H33=0,E33-K33,0) -> 0 | Q33: =+SUMIFS(db_Sum,db_Bln,Q$6,db_Kode,$A33) -> 0 | R33: =+SUMIFS(db_Sum,db_Bln,R$6,db_Kode,$A33) -> 0 | S33: =+SUMIFS(db_Sum,db_Bln,S$6,db_Kode,$A33) -> 0 | T33: =+SUMIFS(db_Sum,db_Bln,T$6,db_Kode,$A33) -> 0 | U33: =+SUMIFS(db_Sum,db_Bln,U$6,db_Kode,$A33) -> 0 | V33: =+SUMIFS(db_Sum,db_Bln,V$6,db_Kode,$A33) -> 0 | W33: =+SUMIFS(db_Sum,db_Bln,W$6,db_Kode,$A33) -> 0 | X33: =+SUMIFS(db_Sum,db_Bln,X$6,db_Kode,$A33) -> 0 | ... AE33: =+SUMIFS(db_Sum,db_Bln,AE$6,db_Kode,$A33) -> 0 | AF33: =+SUM(T33:AE33) -> 0 | AG33: =+SUMIFS(db_Sum,db_Bln,AG$6,db_Kode,$A33) -> 0 | AH33: =+SUMIFS(db_Sum,db_Bln,AH$6,db_Kode,$A33) -> 0 | AI33: =+SUMIFS(db_Sum,db_Bln,AI$6,db_Kode,$A33) -> 0 | AJ33: =+SUMIFS(db_Sum,db_Bln,AJ$6,db_Kode,$A33) -> 0 | AK33: =+SUMIFS(db_Sum,db_Bln,AK$6,db_Kode,$A33) -> 366930480 | AL33: =+SUMIFS(db_Sum,db_Bln,AL$6,db_Kode,$A33) -> 0 | AM33: =+SUMIFS(db_Sum,db_Bln,AM$6,db_Kode,$A33) -> 0 | AN33: =+SUMIFS(db_Sum,db_Bln,AN$6,db_Kode,$A33) -> 0 | ... AR33: =+SUMIFS(db_Sum,db_Bln,AR$6,db_Kode,$A33) -> 0 | AS33: =+SUM(AG33:AR33) -> 366930480 | AT33: =+SUMIFS(db_Sum,db_Bln,AT$6,db_Kode,$A33) -> 0 | AU33: =+SUMIFS(db_Sum,db_Bln,AU$6,db_Kode,$A33) -> 0 | AV33: =+SUMIFS(db_Sum,db_Bln,AV$6,db_Kode,$A33) -> 0 | AW33: =+SUMIFS(db_Sum,db_Bln,AW$6,db_Kode,$A33) -> 0 | AX33: =+SUMIFS(db_Sum,db_Bln,AX$6,db_Kode,$A33) -> 0 | AY33: =+SUMIFS(db_Sum,db_Bln,AY$6,db_Kode,$A33) -> 0 | AZ33: =+SUMIFS(db_Sum,db_Bln,AZ$6,db_Kode,$A33) -> 0 | BA33: =+SUMIFS(db_Sum,db_Bln,BA$6,db_Kode,$A33) -> 0 | ... BE33: =+SUMIFS(db_Sum,db_Bln,BE$6,db_Kode,$A33) -> 0 | BF33: =+SUM(AT33:BE33) -> 0 | BG33: =+SUMIFS(db_Sum,db_Bln,BG$6,db_Kode,$A33) -> 0 | BH33: =+SUMIFS(db_Sum,db_Bln,BH$6,db_Kode,$A33) -> 0 | BI33: =+SUMIFS(db_Sum,db_Bln,BI$6,db_Kode,$A33) -> 0 | BJ33: =+SUMIFS(db_Sum,db_Bln,BJ$6,db_Kode,$A33) -> 0 | BK33: =+SUMIFS(db_Sum,db_Bln,BK$6,db_Kode,$A33) -> 0 | BS33: =+SUM(BG33:BR33) -> 0 | BT33: =+SUM(O33,Q33,R33,S33,AF33,AS33,BF33+BS33) -> 366930480 | BU33: =+IF(K33-BT33=0,"OK","ERROR") -> OK
A34: B4 | B34: 4 | C34: Tiang Pancang Tahap 4 | D34: PT. WIKA | E34: 6548560440 | F34: TP.01.03/WB-1H.022/2022 | G34: PT. WIKA | H34: =+IF(E34>K34,E34-K34,0) -> 0 | I34: 6548560440 | J34: 6548560440 | K34: =+O34+Q34+R34+S34+AF34+AS34+BF34+BS34 -> 6548560440 | L34: 0 | M34: =J34-K34 -> 0 | N34: -Sudah Lunas | O34: =+SUMIFS(db_Sum,db_Bln,O$6,db_Kode,$A34) -> 0 | P34: =+IF(H34=0,E34-K34,0) -> 0 | Q34: =+SUMIFS(db_Sum,db_Bln,Q$6,db_Kode,$A34) -> 0 | R34: =+SUMIFS(db_Sum,db_Bln,R$6,db_Kode,$A34) -> 0 | S34: =+SUMIFS(db_Sum,db_Bln,S$6,db_Kode,$A34) -> 0 | T34: =+SUMIFS(db_Sum,db_Bln,T$6,db_Kode,$A34) -> 0 | U34: =+SUMIFS(db_Sum,db_Bln,U$6,db_Kode,$A34) -> 0 | V34: =+SUMIFS(db_Sum,db_Bln,V$6,db_Kode,$A34) -> 0 | W34: =+SUMIFS(db_Sum,db_Bln,W$6,db_Kode,$A34) -> 0 | X34: =+SUMIFS(db_Sum,db_Bln,X$6,db_Kode,$A34) -> 0 | ... AE34: =+SUMIFS(db_Sum,db_Bln,AE$6,db_Kode,$A34) -> 0 | AF34: =+SUM(T34:AE34) -> 0 | AG34: =+SUMIFS(db_Sum,db_Bln,AG$6,db_Kode,$A34) -> 0 | AH34: =+SUMIFS(db_Sum,db_Bln,AH$6,db_Kode,$A34) -> 0 | AI34: =+SUMIFS(db_Sum,db_Bln,AI$6,db_Kode,$A34) -> 0 | AJ34: =+SUMIFS(db_Sum,db_Bln,AJ$6,db_Kode,$A34) -> 0 | AK34: =+SUMIFS(db_Sum,db_Bln,AK$6,db_Kode,$A34) -> 1964568132 | AL34: =+SUMIFS(db_Sum,db_Bln,AL$6,db_Kode,$A34) -> 0 | AM34: =+SUMIFS(db_Sum,db_Bln,AM$6,db_Kode,$A34) -> 4853992308 | AN34: =+SUMIFS(db_Sum,db_Bln,AN$6,db_Kode,$A34) -> 0 | ... AR34: =+SUMIFS(db_Sum,db_Bln,AR$6,db_Kode,$A34) -> 0 | AS34: =+SUM(AG34:AR34) -> 6548560440 | AT34: =+SUMIFS(db_Sum,db_Bln,AT$6,db_Kode,$A34) -> 0 | AU34: =+SUMIFS(db_Sum,db_Bln,AU$6,db_Kode,$A34) -> 0 | AV34: =+SUMIFS(db_Sum,db_Bln,AV$6,db_Kode,$A34) -> 0 | AW34: =+SUMIFS(db_Sum,db_Bln,AW$6,db_Kode,$A34) -> 0 | AX34: =+SUMIFS(db_Sum,db_Bln,AX$6,db_Kode,$A34) -> 0 | AY34: =+SUMIFS(db_Sum,db_Bln,AY$6,db_Kode,$A34) -> 0 | AZ34: =+SUMIFS(db_Sum,db_Bln,AZ$6,db_Kode,$A34) -> 0 | BA34: =+SUMIFS(db_Sum,db_Bln,BA$6,db_Kode,$A34) -> 0 | ... BE34: =+SUMIFS(db_Sum,db_Bln,BE$6,db_Kode,$A34) -> 0 | BF34: =+SUM(AT34:BE34) -> 0 | BG34: =+SUMIFS(db_Sum,db_Bln,BG$6,db_Kode,$A34) -> 0 | BH34: =+SUMIFS(db_Sum,db_Bln,BH$6,db_Kode,$A34) -> 0 | BI34: =+SUMIFS(db_Sum,db_Bln,BI$6,db_Kode,$A34) -> 0 | BJ34: =+SUMIFS(db_Sum,db_Bln,BJ$6,db_Kode,$A34) -> 0 | BK34: =+SUMIFS(db_Sum,db_Bln,BK$6,db_Kode,$A34) -> 0 | BS34: =+SUM(BG34:BR34) -> 0 | BT34: =+SUM(O34,Q34,R34,S34,AF34,AS34,BF34+BS34) -> 6548560440 | BU34: =+IF(K34-BT34=0,"OK","ERROR") -> OK
A35: B5 | B35: 5 | C35: Tiang Pancang Tahap 5 Estimasi | D35: PT. WIKA | E35: 1500000000 | H35: =+IF(E35>K35,E35-K35,0) -> 105926580 | I35: 1.3940734e+09 | J35: 1.3940734e+09 | K35: =+O35+Q35+R35+S35+AF35+AS35+BF35+BS35 -> 1394073420 | L35: 0 | M35: =J35-K35 -> 0 | N35: -Sudah Lunas | O35: =+SUMIFS(db_Sum,db_Bln,O$6,db_Kode,$A35) -> 0 | P35: =H35 -> 105926580 | Q35: =+SUMIFS(db_Sum,db_Bln,Q$6,db_Kode,$A35) -> 0 | R35: =+SUMIFS(db_Sum,db_Bln,R$6,db_Kode,$A35) -> 0 | S35: =+SUMIFS(db_Sum,db_Bln,S$6,db_Kode,$A35) -> 0 | T35: =+SUMIFS(db_Sum,db_Bln,T$6,db_Kode,$A35) -> 0 | U35: =+SUMIFS(db_Sum,db_Bln,U$6,db_Kode,$A35) -> 0 | V35: =+SUMIFS(db_Sum,db_Bln,V$6,db_Kode,$A35) -> 0 | W35: =+SUMIFS(db_Sum,db_Bln,W$6,db_Kode,$A35) -> 0 | X35: =+SUMIFS(db_Sum,db_Bln,X$6,db_Kode,$A35) -> 0 | ... AE35: =+SUMIFS(db_Sum,db_Bln,AE$6,db_Kode,$A35) -> 0 | AF35: =+SUM(T35:AE35) -> 0 | AG35: =+SUMIFS(db_Sum,db_Bln,AG$6,db_Kode,$A35) -> 0 | AH35: =+SUMIFS(db_Sum,db_Bln,AH$6,db_Kode,$A35) -> 0 | AI35: =+SUMIFS(db_Sum,db_Bln,AI$6,db_Kode,$A35) -> 0 | AJ35: =+SUMIFS(db_Sum,db_Bln,AJ$6,db_Kode,$A35) -> 0 | AK35: =+SUMIFS(db_Sum,db_Bln,AK$6,db_Kode,$A35) -> 0 | AL35: =+SUMIFS(db_Sum,db_Bln,AL$6,db_Kode,$A35) -> 0 | AM35: =+SUMIFS(db_Sum,db_Bln,AM$6,db_Kode,$A35) -> 0 | AN35: =+SUMIFS(db_Sum,db_Bln,AN$6,db_Kode,$A35) -> 0 | ... AR35: =+SUMIFS(db_Sum,db_Bln,AR$6,db_Kode,$A35) -> 0 | AS35: =+SUM(AG35:AR35) -> 1394073420 | AT35: =+SUMIFS(db_Sum,db_Bln,AT$6,db_Kode,$A35) -> 0 | AU35: =+SUMIFS(db_Sum,db_Bln,AU$6,db_Kode,$A35) -> 0 | AV35: =+SUMIFS(db_Sum,db_Bln,AV$6,db_Kode,$A35) -> 0 | AW35: =+SUMIFS(db_Sum,db_Bln,AW$6,db_Kode,$A35) -> 0 | AX35: =+SUMIFS(db_Sum,db_Bln,AX$6,db_Kode,$A35) -> 0 | AY35: =+SUMIFS(db_Sum,db_Bln,AY$6,db_Kode,$A35) -> 0 | AZ35: =+SUMIFS(db_Sum,db_Bln,AZ$6,db_Kode,$A35) -> 0 | BA35: =+SUMIFS(db_Sum,db_Bln,BA$6,db_Kode,$A35) -> 0 | ... BE35: =+SUMIFS(db_Sum,db_Bln,BE$6,db_Kode,$A35) -> 0 | BF35: =+SUM(AT35:BE35) -> 0 | BG35: =+SUMIFS(db_Sum,db_Bln,BG$6,db_Kode,$A35) -> 0 | BH35: =+SUMIFS(db_Sum,db_Bln,BH$6,db_Kode,$A35) -> 0 | BI35: =+SUMIFS(db_Sum,db_Bln,BI$6,db_Kode,$A35) -> 0 | BJ35: =+SUMIFS(db_Sum,db_Bln,BJ$6,db_Kode,$A35) -> 0 | BK35: =+SUMIFS(db_Sum,db_Bln,BK$6,db_Kode,$A35) -> 0 | BS35: =+SUM(BG35:BR35) -> 0 | BT35: =+SUM(O35,Q35,R35,S35,AF35,AS35,BF35+BS35) -> 1394073420 | BU35: =+IF(K35-BT35=0,"OK","ERROR") -> OK
A36: B6 | B36: 6 | C36: Material Lainnya | E36: 0 | H36: =E36-K36 -> -82803853 | I36: 0 | J36: 82803853 | K36: =+O36+Q36+R36+S36+AF36+AS36+BF36+BS36 -> 82803853 | L36: 0 | N36: -Atas Biaya Perbaikan SLT | O36: =+SUMIFS(db_Sum,db_Bln,O$6,db_Kode,$A36) -> 0 | P36: =+IF(H36=0,E36-K36,0) -> 0 | Q36: =+SUMIFS(db_Sum,db_Bln,Q$6,db_Kode,$A36) -> 0 | R36: =+SUMIFS(db_Sum,db_Bln,R$6,db_Kode,$A36) -> 0 | S36: =+SUMIFS(db_Sum,db_Bln,S$6,db_Kode,$A36) -> 0 | T36: =+SUMIFS(db_Sum,db_Bln,T$6,db_Kode,$A36) -> 0 | U36: =+SUMIFS(db_Sum,db_Bln,U$6,db_Kode,$A36) -> 0 | V36: =+SUMIFS(db_Sum,db_Bln,V$6,db_Kode,$A36) -> 0 | W36: =+SUMIFS(db_Sum,db_Bln,W$6,db_Kode,$A36) -> 0 | X36: =+SUMIFS(db_Sum,db_Bln,X$6,db_Kode,$A36) -> 0 | ... AE36: =+SUMIFS(db_Sum,db_Bln,AE$6,db_Kode,$A36) -> 0 | AF36: =+SUM(T36:AE36) -> 39283354 | AG36: =+SUMIFS(db_Sum,db_Bln,AG$6,db_Kode,$A36) -> 0 | AH36: =+SUMIFS(db_Sum,db_Bln,AH$6,db_Kode,$A36) -> 0 | AI36: =+SUMIFS(db_Sum,db_Bln,AI$6,db_Kode,$A36) -> 0 | AJ36: =+SUMIFS(db_Sum,db_Bln,AJ$6,db_Kode,$A36) -> 0 | AK36: =+SUMIFS(db_Sum,db_Bln,AK$6,db_Kode,$A36) -> 0 | AL36: =+SUMIFS(db_Sum,db_Bln,AL$6,db_Kode,$A36) -> 0 | AM36: =+SUMIFS(db_Sum,db_Bln,AM$6,db_Kode,$A36) -> 1364640 | AN36: =+SUMIFS(db_Sum,db_Bln,AN$6,db_Kode,$A36) -> 588000 | ... AR36: =+SUMIFS(db_Sum,db_Bln,AR$6,db_Kode,$A36) -> 13184940 | AS36: =+SUM(AG36:AR36) -> 43220499 | AT36: =+SUMIFS(db_Sum,db_Bln,AT$6,db_Kode,$A36) -> 0 | AU36: =+SUMIFS(db_Sum,db_Bln,AU$6,db_Kode,$A36) -> 0 | AV36: =+SUMIFS(db_Sum,db_Bln,AV$6,db_Kode,$A36) -> 0 | AW36: =+SUMIFS(db_Sum,db_Bln,AW$6,db_Kode,$A36) -> 0 | AX36: =+SUMIFS(db_Sum,db_Bln,AX$6,db_Kode,$A36) -> 0 | AY36: =+SUMIFS(db_Sum,db_Bln,AY$6,db_Kode,$A36) -> 300000 | AZ36: =+SUMIFS(db_Sum,db_Bln,AZ$6,db_Kode,$A36) -> 0 | BA36: =+SUMIFS(db_Sum,db_Bln,BA$6,db_Kode,$A36) -> 0 | ... BE36: =+SUMIFS(db_Sum,db_Bln,BE$6,db_Kode,$A36) -> 0 | BF36: =+SUM(AT36:BE36) -> 300000 | BG36: =+SUMIFS(db_Sum,db_Bln,BG$6,db_Kode,$A36) -> 0 | BH36: =+SUMIFS(db_Sum,db_Bln,BH$6,db_Kode,$A36) -> 0 | BI36: =+SUMIFS(db_Sum,db_Bln,BI$6,db_Kode,$A36) -> 0 | BJ36: =+SUMIFS(db_Sum,db_Bln,BJ$6,db_Kode,$A36) -> 0 | BK36: =+SUMIFS(db_Sum,db_Bln,BK$6,db_Kode,$A36) -> 0 | BS36: =+SUM(BG36:BR36) -> 0 | BT36: =+SUM(O36,Q36,R36,S36,AF36,AS36,BF36+BS36) -> 82803853 | BU36: =+IF(K36-BT36=0,"OK","ERROR") -> OK
A37: B7 | B37: 7 | C37: Shipment Slab Precast | D37: PT. Prakarsa Muda Indonesia | E37: 0 | H37: =E37-K37 -> -1237650000 | I37: 1237650000 | J37: 1237650000 | K37: =+O37+Q37+R37+S37+AF37+AS37+BF37+BS37 -> 1237650000 | M37: 0 | N37: -Biaya Shipment Probolinggo to Sei. Cabang | O37: =+SUMIFS(db_Sum,db_Bln,O$6,db_Kode,$A37) -> 0 | P37: =+IF(H37=0,E37-K37,0) -> 0 | Q37: =+SUMIFS(db_Sum,db_Bln,Q$6,db_Kode,$A37) -> 0 | R37: =+SUMIFS(db_Sum,db_Bln,R$6,db_Kode,$A37) -> 0 | S37: =+SUMIFS(db_Sum,db_Bln,S$6,db_Kode,$A37) -> 0 | T37: =+SUMIFS(db_Sum,db_Bln,T$6,db_Kode,$A37) -> 0 | U37: =+SUMIFS(db_Sum,db_Bln,U$6,db_Kode,$A37) -> 0 | V37: =+SUMIFS(db_Sum,db_Bln,V$6,db_Kode,$A37) -> 0 | W37: =+SUMIFS(db_Sum,db_Bln,W$6,db_Kode,$A37) -> 0 | X37: =+SUMIFS(db_Sum,db_Bln,X$6,db_Kode,$A37) -> 0 | ... AE37: =+SUMIFS(db_Sum,db_Bln,AE$6,db_Kode,$A37) -> 0 | AF37: =+SUM(T37:AE37) -> 0 | AG37: =+SUMIFS(db_Sum,db_Bln,AG$6,db_Kode,$A37) -> 0 | AH37: =+SUMIFS(db_Sum,db_Bln,AH$6,db_Kode,$A37) -> 0 | AI37: =+SUMIFS(db_Sum,db_Bln,AI$6,db_Kode,$A37) -> 0 | AJ37: =+SUMIFS(db_Sum,db_Bln,AJ$6,db_Kode,$A37) -> 0 | AK37: =+SUMIFS(db_Sum,db_Bln,AK$6,db_Kode,$A37) -> 0 | AL37: =+SUMIFS(db_Sum,db_Bln,AL$6,db_Kode,$A37) -> 0 | AM37: =+SUMIFS(db_Sum,db_Bln,AM$6,db_Kode,$A37) -> 0 | AN37: =+SUMIFS(db_Sum,db_Bln,AN$6,db_Kode,$A37) -> 0 | ... AR37: =+SUMIFS(db_Sum,db_Bln,AR$6,db_Kode,$A37) -> 0 | AS37: =+SUM(AG37:AR37) -> 0 | AT37: =+SUMIFS(db_Sum,db_Bln,AT$6,db_Kode,$A37) -> 0 | AU37: =+SUMIFS(db_Sum,db_Bln,AU$6,db_Kode,$A37) -> 0 | AV37: =+SUMIFS(db_Sum,db_Bln,AV$6,db_Kode,$A37) -> 618825000 | AW37: =+SUMIFS(db_Sum,db_Bln,AW$6,db_Kode,$A37) -> 618825000 | AX37: =+SUMIFS(db_Sum,db_Bln,AX$6,db_Kode,$A37) -> 0 | AY37: =+SUMIFS(db_Sum,db_Bln,AY$6,db_Kode,$A37) -> 0 | AZ37: =+SUMIFS(db_Sum,db_Bln,AZ$6,db_Kode,$A37) -> 0 | BA37: =+SUMIFS(db_Sum,db_Bln,BA$6,db_Kode,$A37) -> 0 | ... BE37: =+SUMIFS(db_Sum,db_Bln,BE$6,db_Kode,$A37) -> 0 | BF37: =+SUM(AT37:BE37) -> 1237650000 | BG37: =+SUMIFS(db_Sum,db_Bln,BG$6,db_Kode,$A37) -> 0 | BH37: =+SUMIFS(db_Sum,db_Bln,BH$6,db_Kode,$A37) -> 0 | BI37: =+SUMIFS(db_Sum,db_Bln,BI$6,db_Kode,$A37) -> 0 | BJ37: =+SUMIFS(db_Sum,db_Bln,BJ$6,db_Kode,$A37) -> 0 | BK37: =+SUMIFS(db_Sum,db_Bln,BK$6,db_Kode,$A37) -> 0 | BS37: =+SUM(BG37:BR37) -> 0 | BT37: =+SUM(O37,Q37,R37,S37,AF37,AS37,BF37+BS37) -> 1237650000 | BU37: =+IF(K37-BT37=0,"OK","ERROR") -> OK
C38: SUB TOTAL TIANG PANCANG | E38: =SUM(E31:E36) -> 20296423720 | H38: =SUM(H31:H36) -> -14892593 | I38: =SUM(I31:I36) -> 20228512460 | J38: =SUM(J31:J36) -> 20311316313 | K38: =SUM(K31:K36) -> 20311316313 | L38: =SUM(L31:L36) -> 0 | M38: =SUM(M20:M36) -> 0 | N38: =K38+L38+M38 -> 20311316313 | O38: =SUM(O31:O36) -> 0 | P38: =SUM(P31:P36) -> 105926580 | Q38: =SUM(Q31:Q36) -> 0 | R38: =SUM(R31:R36) -> 0 | S38: =SUM(S31:S36) -> 0 | T38: =SUM(T31:T36) -> 0 | U38: =SUM(U31:U36) -> 0 | V38: =SUM(V31:V36) -> 0 | ... BT38: =SUM(BT31:BT36) -> 20311316313 | BU38: =+IF(K38-BT38=0,"OK","ERROR") -> OK | BV38: =BT38-K38 -> 0
B39: C | C39: PEMANCANGAN
A40: C1 | B40: 1 | C40: Pemancangan Tahap 1 | D40: PT. JBP | E40: 10832222379 | F40: 01/SPK/KS-PKS/MILL-HO/III/2022 | G40: PT. JBP | H40: =E40-K40 -> 115001800 | I40: 10802002379 | J40: 10802002379 | K40: =+O40+Q40+R40+S40+AF40+AS40+BF40+BS40 -> 10717220579 | L40: 0 | M40: 0 | N40: -Pekerjaan Final pada 99,217% dan ada selisih nilai PPN dari 10% ke 11% (Sudah Lunas) | O40: =+SUMIFS(db_Sum,db_Bln,O$6,db_Kode,$A40) -> 0 | P40: =+IF(H40=0,E40-K40,0) -> 0 | Q40: =+SUMIFS(db_Sum,db_Bln,Q$6,db_Kode,$A40) -> 0 | R40: =+SUMIFS(db_Sum,db_Bln,R$6,db_Kode,$A40) -> 0 | S40: =+SUMIFS(db_Sum,db_Bln,S$6,db_Kode,$A40) -> 0 | T40: =+SUMIFS(db_Sum,db_Bln,T$6,db_Kode,$A40) -> 0 | U40: =+SUMIFS(db_Sum,db_Bln,U$6,db_Kode,$A40) -> 0 | V40: =+SUMIFS(db_Sum,db_Bln,V$6,db_Kode,$A40) -> 0 | W40: =+SUMIFS(db_Sum,db_Bln,W$6,db_Kode,$A40) -> 0 | X40: =+SUMIFS(db_Sum,db_Bln,X$6,db_Kode,$A40) -> 0 | ... AE40: =+SUMIFS(db_Sum,db_Bln,AE$6,db_Kode,$A40) -> 0 | AF40: =+SUM(T40:AE40) -> 0 | AG40: =+SUMIFS(db_Sum,db_Bln,AG$6,db_Kode,$A40) -> 0 | AH40: =+SUMIFS(db_Sum,db_Bln,AH$6,db_Kode,$A40) -> 0 | AI40: =+SUMIFS(db_Sum,db_Bln,AI$6,db_Kode,$A40) -> 3324200000 | AJ40: =+SUMIFS(db_Sum,db_Bln,AJ$6,db_Kode,$A40) -> 1728636300 | AK40: =+SUMIFS(db_Sum,db_Bln,AK$6,db_Kode,$A40) -> 2359618686 | AL40: =+SUMIFS(db_Sum,db_Bln,AL$6,db_Kode,$A40) -> 2165146353 | AM40: =+SUMIFS(db_Sum,db_Bln,AM$6,db_Kode,$A40) -> 1139619240 | AN40: =+SUMIFS(db_Sum,db_Bln,AN$6,db_Kode,$A40) -> 0 | ... AR40: =+SUMIFS(db_Sum,db_Bln,AR$6,db_Kode,$A40) -> 0 | AS40: =+SUM(AG40:AR40) -> 10717220579 | AT40: =+SUMIFS(db_Sum,db_Bln,AT$6,db_Kode,$A40) -> 0 | AU40: =+SUMIFS(db_Sum,db_Bln,AU$6,db_Kode,$A40) -> 0 | AV40: =+SUMIFS(db_Sum,db_Bln,AV$6,db_Kode,$A40) -> 0 | AW40: =+SUMIFS(db_Sum,db_Bln,AW$6,db_Kode,$A40) -> 0 | AX40: =+SUMIFS(db_Sum,db_Bln,AX$6,db_Kode,$A40) -> 0 | AY40: =+SUMIFS(db_Sum,db_Bln,AY$6,db_Kode,$A40) -> 0 | AZ40: =+SUMIFS(db_Sum,db_Bln,AZ$6,db_Kode,$A40) -> 0 | BA40: =+SUMIFS(db_Sum,db_Bln,BA$6,db_Kode,$A40) -> 0 | ... BE40: =+SUMIFS(db_Sum,db_Bln,BE$6,db_Kode,$A40) -> 0 | BF40: =+SUM(AT40:BE40) -> 0 | BG40: =+SUMIFS(db_Sum,db_Bln,BG$6,db_Kode,$A40) -> 0 | BH40: =+SUMIFS(db_Sum,db_Bln,BH$6,db_Kode,$A40) -> 0 | BI40: =+SUMIFS(db_Sum,db_Bln,BI$6,db_Kode,$A40) -> 0 | BJ40: =+SUMIFS(db_Sum,db_Bln,BJ$6,db_Kode,$A40) -> 0 | BK40: =+SUMIFS(db_Sum,db_Bln,BK$6,db_Kode,$A40) -> 0 | BS40: =+SUM(BG40:BR40) -> 0 | BT40: =+SUM(O40,Q40,R40,S40,AF40,AS40,BF40+BS40) -> 10717220579 | BU40: =+IF(K40-BT40=0,"OK","ERROR") -> OK
A41: C2 | B41: 2 | C41: Pemancangan Tahap 2 | D41: PT. TCN | E41: 9.7553126e+09 | F41: 05/SPK/KS-PKS/MILL-HO/IV/2022 | G41: PT. TCN | H41: =E41-K41 -> 2.0684295e+08 | I41: 9.7553126e+09 | J41: 9.7553126e+09 | K41: =+O41+Q41+R41+S41+AF41+AS41+BF41+BS41 -> 9548469662 | L41: 0 | M41: 0 | N41: -Pekerjaan Final pada 97,8797%(Sudah Lunas) | O41: =+SUMIFS(db_Sum,db_Bln,O$6,db_Kode,$A41) -> 0 | P41: =H41 -> 2.0684295e+08 | Q41: =+SUMIFS(db_Sum,db_Bln,Q$6,db_Kode,$A41) -> 0 | R41: =+SUMIFS(db_Sum,db_Bln,R$6,db_Kode,$A41) -> 0 | S41: =+SUMIFS(db_Sum,db_Bln,S$6,db_Kode,$A41) -> 0 | T41: =+SUMIFS(db_Sum,db_Bln,T$6,db_Kode,$A41) -> 0 | U41: =+SUMIFS(db_Sum,db_Bln,U$6,db_Kode,$A41) -> 0 | V41: =+SUMIFS(db_Sum,db_Bln,V$6,db_Kode,$A41) -> 0 | W41: =+SUMIFS(db_Sum,db_Bln,W$6,db_Kode,$A41) -> 0 | X41: =+SUMIFS(db_Sum,db_Bln,X$6,db_Kode,$A41) -> 0 | ... AE41: =+SUMIFS(db_Sum,db_Bln,AE$6,db_Kode,$A41) -> 0 | AF41: =+SUM(T41:AE41) -> 0 | AG41: =+SUMIFS(db_Sum,db_Bln,AG$6,db_Kode,$A41) -> 0 | AH41: =+SUMIFS(db_Sum,db_Bln,AH$6,db_Kode,$A41) -> 0 | AI41: =+SUMIFS(db_Sum,db_Bln,AI$6,db_Kode,$A41) -> 0 | AJ41: =+SUMIFS(db_Sum,db_Bln,AJ$6,db_Kode,$A41) -> 3145334805 | AK41: =+SUMIFS(db_Sum,db_Bln,AK$6,db_Kode,$A41) -> 0 | AL41: =+SUMIFS(db_Sum,db_Bln,AL$6,db_Kode,$A41) -> 0 | AM41: =+SUMIFS(db_Sum,db_Bln,AM$6,db_Kode,$A41) -> 3027379822 | AN41: =+SUMIFS(db_Sum,db_Bln,AN$6,db_Kode,$A41) -> 0 | ... AR41: =+SUMIFS(db_Sum,db_Bln,AR$6,db_Kode,$A41) -> 0 | AS41: =+SUM(AG41:AR41) -> 9501157425 | AT41: =+SUMIFS(db_Sum,db_Bln,AT$6,db_Kode,$A41) -> 0 | AU41: =+SUMIFS(db_Sum,db_Bln,AU$6,db_Kode,$A41) -> 47312237 | AV41: =+SUMIFS(db_Sum,db_Bln,AV$6,db_Kode,$A41) -> 0 | AW41: =+SUMIFS(db_Sum,db_Bln,AW$6,db_Kode,$A41) -> 0 | AX41: =+SUMIFS(db_Sum,db_Bln,AX$6,db_Kode,$A41) -> 0 | AY41: =+SUMIFS(db_Sum,db_Bln,AY$6,db_Kode,$A41) -> 0 | AZ41: =+SUMIFS(db_Sum,db_Bln,AZ$6,db_Kode,$A41) -> 0 | BA41: =+SUMIFS(db_Sum,db_Bln,BA$6,db_Kode,$A41) -> 0 | ... BE41: =+SUMIFS(db_Sum,db_Bln,BE$6,db_Kode,$A41) -> 0 | BF41: =+SUM(AT41:BE41) -> 47312237 | BG41: =+SUMIFS(db_Sum,db_Bln,BG$6,db_Kode,$A41) -> 0 | BH41: =+SUMIFS(db_Sum,db_Bln,BH$6,db_Kode,$A41) -> 0 | BI41: =+SUMIFS(db_Sum,db_Bln,BI$6,db_Kode,$A41) -> 0 | BJ41: =+SUMIFS(db_Sum,db_Bln,BJ$6,db_Kode,$A41) -> 0 | BK41: =+SUMIFS(db_Sum,db_Bln,BK$6,db_Kode,$A41) -> 0 | BS41: =+SUM(BG41:BR41) -> 0 | BT41: =+SUM(O41,Q41,R41,S41,AF41,AS41,BF41+BS41) -> 9548469662 | BU41: =+IF(K41-BT41=0,"OK","ERROR") -> OK
A42: C3 | B42: 3 | C42: Pemancangan Tahap 3 | D42: PT. JBP | E42: 1.0984848e+10 | F42: 13/SPK/KS-PKS/MILL-HO/VI/2022 | G42: PT. JBP | H42: =E42-K42 -> 56786490 | I42: 1.0984848e+10 | J42: 1.0984848e+10 | K42: =+O42+Q42+R42+S42+AF42+AS42+BF42+BS42 -> 10928061064 | L42: 0 | M42: 0 | N42: -Final di 99,483% (Sudah Lunas) | O42: =+SUMIFS(db_Sum,db_Bln,O$6,db_Kode,$A42) -> 0 | P42: =+IF(H42=0,E42-K42,0) -> 0 | Q42: =+SUMIFS(db_Sum,db_Bln,Q$6,db_Kode,$A42) -> 0 | R42: =+SUMIFS(db_Sum,db_Bln,R$6,db_Kode,$A42) -> 0 | S42: =+SUMIFS(db_Sum,db_Bln,S$6,db_Kode,$A42) -> 0 | T42: =+SUMIFS(db_Sum,db_Bln,T$6,db_Kode,$A42) -> 0 | U42: =+SUMIFS(db_Sum,db_Bln,U$6,db_Kode,$A42) -> 0 | V42: =+SUMIFS(db_Sum,db_Bln,V$6,db_Kode,$A42) -> 0 | W42: =+SUMIFS(db_Sum,db_Bln,W$6,db_Kode,$A42) -> 0 | X42: =+SUMIFS(db_Sum,db_Bln,X$6,db_Kode,$A42) -> 0 | ... AE42: =+SUMIFS(db_Sum,db_Bln,AE$6,db_Kode,$A42) -> 0 | AF42: =+SUM(T42:AE42) -> 0 | AG42: =+SUMIFS(db_Sum,db_Bln,AG$6,db_Kode,$A42) -> 0 | AH42: =+SUMIFS(db_Sum,db_Bln,AH$6,db_Kode,$A42) -> 0 | AI42: =+SUMIFS(db_Sum,db_Bln,AI$6,db_Kode,$A42) -> 0 | AJ42: =+SUMIFS(db_Sum,db_Bln,AJ$6,db_Kode,$A42) -> 0 | AK42: =+SUMIFS(db_Sum,db_Bln,AK$6,db_Kode,$A42) -> 0 | AL42: =+SUMIFS(db_Sum,db_Bln,AL$6,db_Kode,$A42) -> 3583133146 | AM42: =+SUMIFS(db_Sum,db_Bln,AM$6,db_Kode,$A42) -> 0 | AN42: =+SUMIFS(db_Sum,db_Bln,AN$6,db_Kode,$A42) -> 1772606009 | ... AR42: =+SUMIFS(db_Sum,db_Bln,AR$6,db_Kode,$A42) -> 144377700 | AS42: =+SUM(AG42:AR42) -> 10928061065 | AT42: =+SUMIFS(db_Sum,db_Bln,AT$6,db_Kode,$A42) -> 0 | AU42: =+SUMIFS(db_Sum,db_Bln,AU$6,db_Kode,$A42) -> -1 | AV42: =+SUMIFS(db_Sum,db_Bln,AV$6,db_Kode,$A42) -> 0 | AW42: =+SUMIFS(db_Sum,db_Bln,AW$6,db_Kode,$A42) -> 0 | AX42: =+SUMIFS(db_Sum,db_Bln,AX$6,db_Kode,$A42) -> 0 | AY42: =+SUMIFS(db_Sum,db_Bln,AY$6,db_Kode,$A42) -> 0 | AZ42: =+SUMIFS(db_Sum,db_Bln,AZ$6,db_Kode,$A42) -> 0 | BA42: =+SUMIFS(db_Sum,db_Bln,BA$6,db_Kode,$A42) -> 0 | ... BE42: =+SUMIFS(db_Sum,db_Bln,BE$6,db_Kode,$A42) -> 0 | BF42: =+SUM(AT42:BE42) -> -1 | BG42: =+SUMIFS(db_Sum,db_Bln,BG$6,db_Kode,$A42) -> 0 | BH42: =+SUMIFS(db_Sum,db_Bln,BH$6,db_Kode,$A42) -> 0 | BI42: =+SUMIFS(db_Sum,db_Bln,BI$6,db_Kode,$A42) -> 0 | BJ42: =+SUMIFS(db_Sum,db_Bln,BJ$6,db_Kode,$A42) -> 0 | BK42: =+SUMIFS(db_Sum,db_Bln,BK$6,db_Kode,$A42) -> 0 | BS42: =+SUM(BG42:BR42) -> 0 | BT42: =+SUM(O42,Q42,R42,S42,AF42,AS42,BF42+BS42) -> 10928061064 | BU42: =+IF(K42-BT42=0,"OK","ERROR") -> OK
A43: C4 | B43: 4 | C43: Pemancangan Tahap 4 Estimasi | D43: PT. JBP | E43: 2500000000 | H43: =E43-K43 -> -38748028 | I43: 2.6232208e+09 | J43: 2.6232208e+09 | K43: =+O43+Q43+R43+S43+AF43+AS43+BF43+BS43 -> 2538748028 | L43: 0 | M43: 0 | N43: - Biaya RKP masih estimasi, nilai kontrak adl Rp2.623.220.804 -Final di 96,78% dg nilai Rp2.538.748.028 | O43: =+SUMIFS(db_Sum,db_Bln,O$6,db_Kode,$A43) -> 0 | P43: =+IF(H43=0,E43-K43,0) -> 0 | Q43: =+SUMIFS(db_Sum,db_Bln,Q$6,db_Kode,$A43) -> 0 | R43: =+SUMIFS(db_Sum,db_Bln,R$6,db_Kode,$A43) -> 0 | S43: =+SUMIFS(db_Sum,db_Bln,S$6,db_Kode,$A43) -> 0 | T43: =+SUMIFS(db_Sum,db_Bln,T$6,db_Kode,$A43) -> 0 | U43: =+SUMIFS(db_Sum,db_Bln,U$6,db_Kode,$A43) -> 0 | V43: =+SUMIFS(db_Sum,db_Bln,V$6,db_Kode,$A43) -> 0 | W43: =+SUMIFS(db_Sum,db_Bln,W$6,db_Kode,$A43) -> 0 | X43: =+SUMIFS(db_Sum,db_Bln,X$6,db_Kode,$A43) -> 0 | ... AE43: =+SUMIFS(db_Sum,db_Bln,AE$6,db_Kode,$A43) -> 0 | AF43: =+SUM(T43:AE43) -> 0 | AG43: =+SUMIFS(db_Sum,db_Bln,AG$6,db_Kode,$A43) -> 0 | AH43: =+SUMIFS(db_Sum,db_Bln,AH$6,db_Kode,$A43) -> 0 | AI43: =+SUMIFS(db_Sum,db_Bln,AI$6,db_Kode,$A43) -> 0 | AJ43: =+SUMIFS(db_Sum,db_Bln,AJ$6,db_Kode,$A43) -> 0 | AK43: =+SUMIFS(db_Sum,db_Bln,AK$6,db_Kode,$A43) -> 0 | AL43: =+SUMIFS(db_Sum,db_Bln,AL$6,db_Kode,$A43) -> 0 | AM43: =+SUMIFS(db_Sum,db_Bln,AM$6,db_Kode,$A43) -> 0 | AN43: =+SUMIFS(db_Sum,db_Bln,AN$6,db_Kode,$A43) -> 0 | ... AR43: =+SUMIFS(db_Sum,db_Bln,AR$6,db_Kode,$A43) -> 793616589 | AS43: =+SUM(AG43:AR43) -> 2161356353 | AT43: =+SUMIFS(db_Sum,db_Bln,AT$6,db_Kode,$A43) -> 377391675 | AU43: =+SUMIFS(db_Sum,db_Bln,AU$6,db_Kode,$A43) -> 0 | AV43: =+SUMIFS(db_Sum,db_Bln,AV$6,db_Kode,$A43) -> 0 | AW43: =+SUMIFS(db_Sum,db_Bln,AW$6,db_Kode,$A43) -> 0 | AX43: =+SUMIFS(db_Sum,db_Bln,AX$6,db_Kode,$A43) -> 0 | AY43: =+SUMIFS(db_Sum,db_Bln,AY$6,db_Kode,$A43) -> 0 | AZ43: =+SUMIFS(db_Sum,db_Bln,AZ$6,db_Kode,$A43) -> 0 | BA43: =+SUMIFS(db_Sum,db_Bln,BA$6,db_Kode,$A43) -> 0 | ... BE43: =+SUMIFS(db_Sum,db_Bln,BE$6,db_Kode,$A43) -> 0 | BF43: =+SUM(AT43:BE43) -> 377391675 | BG43: =+SUMIFS(db_Sum,db_Bln,BG$6,db_Kode,$A43) -> 0 | BH43: =+SUMIFS(db_Sum,db_Bln,BH$6,db_Kode,$A43) -> 0 | BI43: =+SUMIFS(db_Sum,db_Bln,BI$6,db_Kode,$A43) -> 0 | BJ43: =+SUMIFS(db_Sum,db_Bln,BJ$6,db_Kode,$A43) -> 0 | BK43: =+SUMIFS(db_Sum,db_Bln,BK$6,db_Kode,$A43) -> 0 | BS43: =+SUM(BG43:BR43) -> 0 | BT43: =+SUM(O43,Q43,R43,S43,AF43,AS43,BF43+BS43) -> 2538748028 | BU43: =+IF(K43-BT43=0,"OK","ERROR") -> OK
C44: SUB TOTAL PEMANCANGAN | E44: =SUM(E40:E43) -> 3.4072383e+10 | H44: =SUM(H40:H43) -> 3.3988321e+08 | I44: =SUM(I40:I43) -> 3.4165383e+10 | J44: =SUM(J40:J43) -> 3.4165383e+10 | K44: =SUM(K40:K43) -> 33732499333 | L44: =SUM(L40:L43) -> 0 | M44: =SUM(M26:M43) -> 0 | N44: =K44+L44+M44 -> 33732499333 | O44: =SUM(O40:O43) -> 0 | P44: =SUM(P40:P43) -> 2.0684295e+08 | Q44: =SUM(Q40:Q43) -> 0 | R44: =SUM(R40:R43) -> 0 | S44: =SUM(S40:S43) -> 0 | T44: =SUM(T40:T43) -> 0 | U44: =SUM(U40:U43) -> 0 | V44: =SUM(V40:V43) -> 0 | ... BT44: =SUM(BT40:BT43) -> 33732499333 | BU44: =+IF(K44-BT44=0,"OK","ERROR") -> OK | BV44: =BT44-K44 -> 0
B45: D | C45: BETON BERTULANG
A46: D1 | B46: 1 | C46: Beton Bertulang | D46: PT. JBP | F46: 15/SPK/KS-PKS/MILL-HO/VI/2022 | G46: PT. JBP | H46: =E46-K47-K49-K51-K48-K50-K52-#REF! -> #REF! | O46: =+SUMIFS(db_Sum,db_Bln,O$6,db_Kode,$A46) -> 0 | P46: =+IF(H46=0,E46-K46,0) -> #REF! | Q46: =+SUMIFS(db_Sum,db_Bln,Q$6,db_Kode,$A46) -> 0 | R46: =+SUMIFS(db_Sum,db_Bln,R$6,db_Kode,$A46) -> 0 | S46: =+SUMIFS(db_Sum,db_Bln,S$6,db_Kode,$A46) -> 0 | T46: =+SUMIFS(db_Sum,db_Bln,T$6,db_Kode,$A46) -> 0 | U46: =+SUMIFS(db_Sum,db_Bln,U$6,db_Kode,$A46) -> 0 | V46: =+SUMIFS(db_Sum,db_Bln,V$6,db_Kode,$A46) -> 0 | W46: =+SUMIFS(db_Sum,db_Bln,W$6,db_Kode,$A46) -> 0 | X46: =+SUMIFS(db_Sum,db_Bln,X$6,db_Kode,$A46) -> 0 | ... AE46: =+SUMIFS(db_Sum,db_Bln,AE$6,db_Kode,$A46) -> 0 | AF46: =+SUM(T46:AE46) -> 0 | AG46: =+SUMIFS(db_Sum,db_Bln,AG$6,db_Kode,$A46) -> 0 | AH46: =+SUMIFS(db_Sum,db_Bln,AH$6,db_Kode,$A46) -> 0 | AI46: =+SUMIFS(db_Sum,db_Bln,AI$6,db_Kode,$A46) -> 0 | AJ46: =+SUMIFS(db_Sum,db_Bln,AJ$6,db_Kode,$A46) -> 0 | AK46: =+SUMIFS(db_Sum,db_Bln,AK$6,db_Kode,$A46) -> 0 | AL46: =+SUMIFS(db_Sum,db_Bln,AL$6,db_Kode,$A46) -> 0 | AM46: =+SUMIFS(db_Sum,db_Bln,AM$6,db_Kode,$A46) -> 0 | AN46: =+SUMIFS(db_Sum,db_Bln,AN$6,db_Kode,$A46) -> 0 | ... AR46: =+SUMIFS(db_Sum,db_Bln,AR$6,db_Kode,$A46) -> 6406172002 | AS46: =+SUM(AG46:AR46) -> 6406172002 | AT46: =+SUMIFS(db_Sum,db_Bln,AT$6,db_Kode,$A46) -> 9337716061 | AU46: =+SUMIFS(db_Sum,db_Bln,AU$6,db_Kode,$A46) -> 5532086828 | AV46: =+SUMIFS(db_Sum,db_Bln,AV$6,db_Kode,$A46) -> 8082904961 | AW46: =+SUMIFS(db_Sum,db_Bln,AW$6,db_Kode,$A46) -> 0 | AX46: =+SUMIFS(db_Sum,db_Bln,AX$6,db_Kode,$A46) -> 6004159618 | AY46: =+SUMIFS(db_Sum,db_Bln,AY$6,db_Kode,$A46) -> 6600672802 | AZ46: =+SUMIFS(db_Sum,db_Bln,AZ$6,db_Kode,$A46) -> 2016525146 | BA46: =+SUMIFS(db_Sum,db_Bln,BA$6,db_Kode,$A46) -> 5195999303 | ... BE46: =+SUMIFS(db_Sum,db_Bln,BE$6,db_Kode,$A46) -> 277056767 | BF46: =+SUM(AT46:BE46) -> 51431258318 | BG46: =+SUMIFS(db_Sum,db_Bln,BG$6,db_Kode,$A46) -> 20900750 | BH46: =+SUMIFS(db_Sum,db_Bln,BH$6,db_Kode,$A46) -> 3544924890 | BI46: =+SUMIFS(db_Sum,db_Bln,BI$6,db_Kode,$A46) -> 1637892081 | BJ46: =+SUMIFS(db_Sum,db_Bln,BJ$6,db_Kode,$A46) -> 309152882 | BK46: =+SUMIFS(db_Sum,db_Bln,BK$6,db_Kode,$A46) -> 0 | BS46: =+SUM(BG46:BR46) -> 5512870603 | BT46: =+SUM(O46,Q46,R46,S46,AF46,AS46,BF46+BS46) -> 63350300923 | BU46: =+IF(K46-BT46=0,"OK","ERROR") -> ERROR
B47: - | C47: Kontrak Tahap I | D47: PT. JBP | E47: 59815680000 | I47: 59815680000 | J47: 59815680000 | K47: 5.4679271e+10 | L47: 0 | M47: =J47-K47 -> 5.1364094e+09
C48: -Pengakuan A/ Pembayaran DP dan Pot. DP+Ret. | E48: 0 | I48: 0 | J48: 0 | K48: 8.6453205e+08 | L48: 0 | M48: 0
B49: - | C49: Kontrak Tahap II | D49: PT. JBP | E49: 0 | I49: 2779729670 | J49: 2779729670 | K49: 0 | L49: 2.6281468e+09 | M49: =J49-L49 -> 1.5158283e+08 | N49: -Pekerjaan Kantor PKS -Pekerjaan Pondasi Timbangan dan Pos Timbangan -Pekerjaan Pos Security -Pekerjaan Pondasi Pigging System -Pekerjaan Pondasi Solid Dryer -Pekerjaan Pondasi WTP FILTER dan Rumah Pompa WTP -Pekerjaan Pondasi dan Bundwall Tangki Solar
C50: -Pengakuan A/ Pembayaran DP dan Pot. DP+Ret. | E50: 0 | I50: 0 | J50: 0 | K50: 0 | L50: 69522039 | M50: 0
B51: - | C51: Kontrak Tahap III | D51: PT. JBP | E51: 0 | I51: 7062213879 | J51: 7062213879 | K51: 0 | L51: 4.2551604e+09 | M51: =J51-L51 -> 2.8070535e+09 | N51: -Pekerjaan Pondasi RO Boiler -Pekerjaan Parit-parit -Pekerjaan Bak Klarfikasi -Pekerjaan Bak Cooling Tower -Pekerjaan Kantor Proses -Pekerjaan Pedestal-pedestal
C52: -Pengakuan A/ Pot. DP+Ret. | I52: 0 | J52: 0 | K52: 0 | L52: 8.5366896e+08 | M52: 0
C53: SUB TOTAL BETON BERTULANG | E53: =SUM(E46:E52) -> 59815680000 | H53: =SUM(H46) -> #REF! | I53: =SUM(I47:I52) -> 69657623549 | J53: =SUM(J47:J52) -> 69657623549 | K53: =SUM(K47:K52)-K48 -> 5.4679271e+10 | L53: =SUM(L47:L52)-L52-L50 -> 6.8833073e+09 | M53: =SUM(M46:M51) -> 8.0950457e+09 | N53: =K53+L53+M53 -> 69657623549 | O53: =SUM(O46) -> 0 | P53: =SUM(P46) -> #REF! | Q53: =SUM(Q46) -> 0 | R53: =SUM(R46) -> 0 | S53: =SUM(S46) -> 0 | T53: =SUM(T46) -> 0 | U53: =SUM(U46) -> 0 | V53: =SUM(V46) -> 0 | ... BT53: =SUM(BT46) -> 63350300923 | BU53: =+IF(K53-BT53=0,"OK","ERROR") -> ERROR | BV53: =BT53-K53 -> 8.6710303e+09
B54: E | C54: MAIN BUILDING
A55: E1 | B55: 1 | C55: Main Building | D55: PT. Tri Royal Timurraya | E55: 16525680000 | F55: 16/SPK/KS-PKS/MILL-HO/VII/2022 | G55: PT. Tri Royal Timur Raya | H55: =E55-K55-K56 -> 409419999 | I55: 1.652568e+10 | J55: 1.652568e+10 | K55: 1.5699396e+10 | M55: =J55-K55 -> 8.26284e+08 | N55: -Pembayaran Retensi belum terealisasi | O55: =+SUMIFS(db_Sum,db_Bln,O$6,db_Kode,$A55) -> 0 | P55: =+IF(H55=0,E55-K55,0) -> 0 | Q55: =+SUMIFS(db_Sum,db_Bln,Q$6,db_Kode,$A55) -> 0 | R55: =+SUMIFS(db_Sum,db_Bln,R$6,db_Kode,$A55) -> 0 | S55: =+SUMIFS(db_Sum,db_Bln,S$6,db_Kode,$A55) -> 0 | T55: =+SUMIFS(db_Sum,db_Bln,T$6,db_Kode,$A55) -> 0 | U55: =+SUMIFS(db_Sum,db_Bln,U$6,db_Kode,$A55) -> 0 | V55: =+SUMIFS(db_Sum,db_Bln,V$6,db_Kode,$A55) -> 0 | W55: =+SUMIFS(db_Sum,db_Bln,W$6,db_Kode,$A55) -> 0 | X55: =+SUMIFS(db_Sum,db_Bln,X$6,db_Kode,$A55) -> 0 | ... AE55: =+SUMIFS(db_Sum,db_Bln,AE$6,db_Kode,$A55) -> 0 | AF55: =+SUM(T55:AE55) -> 0 | AG55: =+SUMIFS(db_Sum,db_Bln,AG$6,db_Kode,$A55) -> 0 | AH55: =+SUMIFS(db_Sum,db_Bln,AH$6,db_Kode,$A55) -> 0 | AI55: =+SUMIFS(db_Sum,db_Bln,AI$6,db_Kode,$A55) -> 0 | AJ55: =+SUMIFS(db_Sum,db_Bln,AJ$6,db_Kode,$A55) -> 0 | AK55: =+SUMIFS(db_Sum,db_Bln,AK$6,db_Kode,$A55) -> 0 | AL55: =+SUMIFS(db_Sum,db_Bln,AL$6,db_Kode,$A55) -> 0 | AM55: =+SUMIFS(db_Sum,db_Bln,AM$6,db_Kode,$A55) -> 0 | AN55: =+SUMIFS(db_Sum,db_Bln,AN$6,db_Kode,$A55) -> 0 | ... AR55: =+SUMIFS(db_Sum,db_Bln,AR$6,db_Kode,$A55) -> 3598599695 | AS55: =+SUM(AG55:AR55) -> 8442904404 | AT55: =+SUMIFS(db_Sum,db_Bln,AT$6,db_Kode,$A55) -> 933453779 | AU55: =+SUMIFS(db_Sum,db_Bln,AU$6,db_Kode,$A55) -> 986476275 | AV55: =+SUMIFS(db_Sum,db_Bln,AV$6,db_Kode,$A55) -> 3286105414 | AW55: =+SUMIFS(db_Sum,db_Bln,AW$6,db_Kode,$A55) -> 0 | AX55: =+SUMIFS(db_Sum,db_Bln,AX$6,db_Kode,$A55) -> 620959498 | AY55: =+SUMIFS(db_Sum,db_Bln,AY$6,db_Kode,$A55) -> 592594880 | AZ55: =+SUMIFS(db_Sum,db_Bln,AZ$6,db_Kode,$A55) -> 2162640950 | BA55: =+SUMIFS(db_Sum,db_Bln,BA$6,db_Kode,$A55) -> -846268627 | ... BE55: =+SUMIFS(db_Sum,db_Bln,BE$6,db_Kode,$A55) -> 0 | BF55: =+SUM(AT55:BE55) -> 7984837318 | BG55: =+SUMIFS(db_Sum,db_Bln,BG$6,db_Kode,$A55) -> 0 | BH55: =+SUMIFS(db_Sum,db_Bln,BH$6,db_Kode,$A55) -> 0 | BI55: =+SUMIFS(db_Sum,db_Bln,BI$6,db_Kode,$A55) -> 0 | BJ55: =+SUMIFS(db_Sum,db_Bln,BJ$6,db_Kode,$A55) -> 0 | BK55: =+SUMIFS(db_Sum,db_Bln,BK$6,db_Kode,$A55) -> 0 | BS55: =+SUM(BG55:BR55) -> 0 | BT55: =+SUM(O55,Q55,R55,S55,AF55,AS55,BF55+BS55) -> 16427741722 | BU55: =+IF(K55-BT55=0,"OK","ERROR") -> ERROR
C56: -Pengakuan A/ Pembayaran DP dan Pot. DP+Ret. | K56: 4.16864e+08
C57: -Talang Air Main Building | D57: PT. Tri Royal Timurraya | E57: 0 | H57: =E57-K57-K58 -> 0 | I57: 313032765 | J57: 313032765 | L57: 2.9738113e+08 | M57: =J57-L57 -> 15651638 | N57: -Pembayaran Retensi belum terealisasi
C58: -Pengakuan atas Retensi Talang Air | K58: 0 | L58: 14100575
A59: E2 | B59: 2 | C59: Atap bluescope & wall clading (Owner Supply) | D59: PT. Arthanindo Cemerlang | E59: 1887000000 | H59: =E59-#REF! -> #REF! | I59: 1697879640 | J59: 1.6978796e+09 | K59: 1697879640 | L59: 0 | M59: =J59-K59 -> 0 | N59: -Pemakaian Persediaan | O59: =+SUMIFS(db_Sum,db_Bln,O$6,db_Kode,$A59) -> 0 | P59: =+IF(H59=0,E59-K59,0) -> #REF! | Q59: =+SUMIFS(db_Sum,db_Bln,Q$6,db_Kode,$A59) -> 0 | R59: =+SUMIFS(db_Sum,db_Bln,R$6,db_Kode,$A59) -> 0 | S59: =+SUMIFS(db_Sum,db_Bln,S$6,db_Kode,$A59) -> 0 | T59: =+SUMIFS(db_Sum,db_Bln,T$6,db_Kode,$A59) -> 0 | U59: =+SUMIFS(db_Sum,db_Bln,U$6,db_Kode,$A59) -> 0 | V59: =+SUMIFS(db_Sum,db_Bln,V$6,db_Kode,$A59) -> 0 | W59: =+SUMIFS(db_Sum,db_Bln,W$6,db_Kode,$A59) -> 0 | X59: =+SUMIFS(db_Sum,db_Bln,X$6,db_Kode,$A59) -> 0 | ... AE59: =+SUMIFS(db_Sum,db_Bln,AE$6,db_Kode,$A59) -> 0 | AF59: =+SUM(T59:AE59) -> 0 | AG59: =+SUMIFS(db_Sum,db_Bln,AG$6,db_Kode,$A59) -> 0 | AH59: =+SUMIFS(db_Sum,db_Bln,AH$6,db_Kode,$A59) -> 0 | AI59: =+SUMIFS(db_Sum,db_Bln,AI$6,db_Kode,$A59) -> 0 | AJ59: =+SUMIFS(db_Sum,db_Bln,AJ$6,db_Kode,$A59) -> 0 | AK59: =+SUMIFS(db_Sum,db_Bln,AK$6,db_Kode,$A59) -> 0 | AL59: =+SUMIFS(db_Sum,db_Bln,AL$6,db_Kode,$A59) -> 0 | AM59: =+SUMIFS(db_Sum,db_Bln,AM$6,db_Kode,$A59) -> 0 | AN59: =+SUMIFS(db_Sum,db_Bln,AN$6,db_Kode,$A59) -> 0 | ... AR59: =+SUMIFS(db_Sum,db_Bln,AR$6,db_Kode,$A59) -> 0 | AS59: =+SUM(AG59:AR59) -> 0 | AT59: =+SUMIFS(db_Sum,db_Bln,AT$6,db_Kode,$A59) -> 0 | AU59: =+SUMIFS(db_Sum,db_Bln,AU$6,db_Kode,$A59) -> 5000000 | AV59: =+SUMIFS(db_Sum,db_Bln,AV$6,db_Kode,$A59) -> 0 | AW59: =+SUMIFS(db_Sum,db_Bln,AW$6,db_Kode,$A59) -> 498795700 | AX59: =+SUMIFS(db_Sum,db_Bln,AX$6,db_Kode,$A59) -> 567914940 | AY59: =+SUMIFS(db_Sum,db_Bln,AY$6,db_Kode,$A59) -> 127569950 | AZ59: =+SUMIFS(db_Sum,db_Bln,AZ$6,db_Kode,$A59) -> 1520000 | BA59: =+SUMIFS(db_Sum,db_Bln,BA$6,db_Kode,$A59) -> 0 | ... BE59: =+SUMIFS(db_Sum,db_Bln,BE$6,db_Kode,$A59) -> 502079050 | BF59: =+SUM(AT59:BE59) -> 1702879640 | BG59: =+SUMIFS(db_Sum,db_Bln,BG$6,db_Kode,$A59) -> 0 | BH59: =+SUMIFS(db_Sum,db_Bln,BH$6,db_Kode,$A59) -> 0 | BI59: =+SUMIFS(db_Sum,db_Bln,BI$6,db_Kode,$A59) -> 0 | BJ59: =+SUMIFS(db_Sum,db_Bln,BJ$6,db_Kode,$A59) -> 0 | BK59: =+SUMIFS(db_Sum,db_Bln,BK$6,db_Kode,$A59) -> 0 | BS59: =+SUM(BG59:BR59) -> 0 | BT59: =+SUM(O59,Q59,R59,S59,AF59,AS59,BF59+BS59) -> 1702879640 | BU59: =+IF(K59-BT59=0,"OK","ERROR") -> ERROR
C60: -Atas Packing Kayu | E60: 0 | I60: 0 | J60: 5000000 | K60: 5000000 | L60: 0 | M60: 0 | N60: -Tambahan Packing Kayu
A61: E3 | B61: 3 | C61: Material Lainnya | E61: 0 | H61: =E61-K61 -> -92696582 | I61: 0 | J61: 92696582 | K61: =+O61+Q61+R61+S61+AF61+AS61+BF61+BS61 -> 92696582 | L61: 0 | M61: 0 | N61: -Biaya Workshop, safety, asuransi dan material lainnya | P61: =+IF(H61=0,E61-K61,0) -> 0 | AU61: =+SUMIFS(db_Sum,db_Bln,AU$6,db_Kode,$A61) -> 0 | AV61: =+SUMIFS(db_Sum,db_Bln,AV$6,db_Kode,$A61) -> 0 | AW61: =+SUMIFS(db_Sum,db_Bln,AW$6,db_Kode,$A61) -> 89991 | AX61: =+SUMIFS(db_Sum,db_Bln,AX$6,db_Kode,$A61) -> 2005000 | AY61: =+SUMIFS(db_Sum,db_Bln,AY$6,db_Kode,$A61) -> 13399995 | AZ61: =+SUMIFS(db_Sum,db_Bln,AZ$6,db_Kode,$A61) -> 12376658 | BA61: =+SUMIFS(db_Sum,db_Bln,BA$6,db_Kode,$A61) -> -7490000 | BB61: =+SUMIFS(db_Sum,db_Bln,BB$6,db_Kode,$A61) -> 2112272 | ... BE61: =+SUMIFS(db_Sum,db_Bln,BE$6,db_Kode,$A61) -> 5042100 | BF61: =+SUM(AT61:BE61) -> 74338645 | BG61: =+SUMIFS(db_Sum,db_Bln,BG$6,db_Kode,$A61) -> 17772290 | BH61: =+SUMIFS(db_Sum,db_Bln,BH$6,db_Kode,$A61) -> 253000 | BI61: =+SUMIFS(db_Sum,db_Bln,BI$6,db_Kode,$A61) -> 332647 | BJ61: =+SUMIFS(db_Sum,db_Bln,BJ$6,db_Kode,$A61) -> 0 | BK61: =+SUMIFS(db_Sum,db_Bln,BK$6,db_Kode,$A61) -> 0 | BS61: =+SUM(BG61:BR61) -> 18357937 | BT61: =+SUM(O61,Q61,R61,S61,AF61,AS61,BF61+BS61) -> 92696582 | BU61: =+IF(K61-BT61=0,"OK","ERROR") -> OK
A62: E3B | C62: Pemakaian Material PT. BKB | E62: 0 | H62: =E62-K62 -> -73211558 | I62: 0 | J62: 73211558 | K62: =+O62+Q62+R62+S62+AF62+AS62+BF62+BS62 -> 73211558 | L62: 0 | M62: 0 | N62: -Pemakaian Material PT. BKB | P62: =+IF(H62=0,E62-K62,0) -> 0 | AU62: =+SUMIFS(db_Sum,db_Bln,AU$6,db_Kode,$A62) -> 0 | AV62: =+SUMIFS(db_Sum,db_Bln,AV$6,db_Kode,$A62) -> 0 | AW62: =+SUMIFS(db_Sum,db_Bln,AW$6,db_Kode,$A62) -> 0 | AX62: =+SUMIFS(db_Sum,db_Bln,AX$6,db_Kode,$A62) -> 0 | AY62: =+SUMIFS(db_Sum,db_Bln,AY$6,db_Kode,$A62) -> 0 | AZ62: =+SUMIFS(db_Sum,db_Bln,AZ$6,db_Kode,$A62) -> 0 | BA62: =+SUMIFS(db_Sum,db_Bln,BA$6,db_Kode,$A62) -> 0 | BB62: =+SUMIFS(db_Sum,db_Bln,BB$6,db_Kode,$A62) -> 0 | ... BE62: =+SUMIFS(db_Sum,db_Bln,BE$6,db_Kode,$A62) -> 73211558 | BF62: =+SUM(AT62:BE62) -> 73211558 | BG62: =+SUMIFS(db_Sum,db_Bln,BG$6,db_Kode,$A62) -> 0 | BH62: =+SUMIFS(db_Sum,db_Bln,BH$6,db_Kode,$A62) -> 0 | BI62: =+SUMIFS(db_Sum,db_Bln,BI$6,db_Kode,$A62) -> 0 | BJ62: =+SUMIFS(db_Sum,db_Bln,BJ$6,db_Kode,$A62) -> 0 | BK62: =+SUMIFS(db_Sum,db_Bln,BK$6,db_Kode,$A62) -> 0 | BS62: =+SUM(BG62:BR62) -> 0 | BT62: =+SUM(O62,Q62,R62,S62,AF62,AS62,BF62+BS62) -> 73211558 | BU62: =+IF(K62-BT62=0,"OK","ERROR") -> OK
C63: SUB TOTAL MAIN BUILDING | E63: =SUM(E55:E61) -> 18412680000 | H63: =SUM(H55:H61) -> #REF! | I63: =SUM(I55:I61) -> 18536592405 | J63: =SUM(J55:J61) -> 1.8634289e+10 | K63: =SUM(K55:K62)-K56 -> 1.7568184e+10 | L63: =SUM(L55:L61)-L58 -> 2.9738113e+08 | M63: =SUM(M55:M61) -> 8.4193564e+08 | N63: =K63+L63+M63 -> 1.8707501e+10 | O63: =SUM(O55:O61) -> 0 | P63: =SUM(P55:P61) -> #REF! | Q63: =SUM(Q55:Q59) -> 0 | R63: =SUM(R55:R59) -> 0 | S63: =SUM(S55:S59) -> 0 | T63: =SUM(T55:T59) -> 0 | U63: =SUM(U55:U59) -> 0 | V63: =SUM(V55:V59) -> 0 | W63: =SUM(W55:W59) -> 0 | X63: =SUM(X55:X59) -> 0 | ... AS63: =SUM(AS55:AS59) -> 8442904404 | AT63: =SUM(AT55:AT61) -> 933453779 | AU63: =SUM(AU55:AU61) -> 991476275 | AV63: =SUM(AV55:AV61) -> 3286105414 | AW63: =SUM(AW55:AW61) -> 498885691 | AX63: =SUM(AX55:AX61) -> 1190879438 | AY63: =SUM(AY55:AY61) -> 733564825 | AZ63: =SUM(AZ55:AZ61) -> 2176537608 | BA63: =SUM(BA55:BA61) -> -853758627 | ... BT63: =SUM(BT55:BT61) -> 1.8223318e+10 | BU63: =+IF(K63-BT63=0,"OK","ERROR") -> ERROR | BV63: =BT63-K63 -> 6.5513416e+08
B64: F | C64: OFFICE BUILDING | AY64: =+SUMIFS(db_Sum,db_Bln,AY$6,db_Kode,$A64) -> 0 | AZ64: =+SUMIFS(db_Sum,db_Bln,AZ$6,db_Kode,$A64) -> 0 | BA64: =+SUMIFS(db_Sum,db_Bln,BA$6,db_Kode,$A64) -> 0
A65: F1 | B65: 1 | C65: Office, Fencing, Pos Security, Parkir, Mushola | E65: 8880000000 | H65: =+IF(E65>K65,E65-K65,0) -> 8081446500 | I65: 798553500 | J65: 798553500 | K65: =+O65+Q65+R65+S65+AF65+AS65+BF65+BS65 -> 798553500 | M65: 0 | N65: -Pembangunan Kantor PKS | O65: =+SUMIFS(db_Sum,db_Bln,O$6,db_Kode,$A65) -> 0 | P65: =+IF(H65=0,E65-K65,0) -> 0 | Q65: =+SUMIFS(db_Sum,db_Bln,Q$6,db_Kode,$A65) -> 0 | R65: =+SUMIFS(db_Sum,db_Bln,R$6,db_Kode,$A65) -> 0 | S65: =+SUMIFS(db_Sum,db_Bln,S$6,db_Kode,$A65) -> 0 | T65: =+SUMIFS(db_Sum,db_Bln,T$6,db_Kode,$A65) -> 0 | U65: =+SUMIFS(db_Sum,db_Bln,U$6,db_Kode,$A65) -> 0 | V65: =+SUMIFS(db_Sum,db_Bln,V$6,db_Kode,$A65) -> 0 | W65: =+SUMIFS(db_Sum,db_Bln,W$6,db_Kode,$A65) -> 0 | X65: =+SUMIFS(db_Sum,db_Bln,X$6,db_Kode,$A65) -> 0 | ... AE65: =+SUMIFS(db_Sum,db_Bln,AE$6,db_Kode,$A65) -> 0 | AF65: =+SUM(T65:AE65) -> 0 | AG65: =+SUMIFS(db_Sum,db_Bln,AG$6,db_Kode,$A65) -> 0 | AH65: =+SUMIFS(db_Sum,db_Bln,AH$6,db_Kode,$A65) -> 0 | AI65: =+SUMIFS(db_Sum,db_Bln,AI$6,db_Kode,$A65) -> 0 | AJ65: =+SUMIFS(db_Sum,db_Bln,AJ$6,db_Kode,$A65) -> 0 | AK65: =+SUMIFS(db_Sum,db_Bln,AK$6,db_Kode,$A65) -> 0 | AL65: =+SUMIFS(db_Sum,db_Bln,AL$6,db_Kode,$A65) -> 0 | AM65: =+SUMIFS(db_Sum,db_Bln,AM$6,db_Kode,$A65) -> 0 | AN65: =+SUMIFS(db_Sum,db_Bln,AN$6,db_Kode,$A65) -> 0 | ... AR65: =+SUMIFS(db_Sum,db_Bln,AR$6,db_Kode,$A65) -> 0 | AS65: =+SUM(AG65:AR65) -> 0 | AT65: =+SUMIFS(db_Sum,db_Bln,AT$6,db_Kode,$A65) -> 0 | AU65: =+SUMIFS(db_Sum,db_Bln,AU$6,db_Kode,$A65) -> 0 | AV65: =+SUMIFS(db_Sum,db_Bln,AV$6,db_Kode,$A65) -> 0 | AW65: =+SUMIFS(db_Sum,db_Bln,AW$6,db_Kode,$A65) -> 0 | AX65: =+SUMIFS(db_Sum,db_Bln,AX$6,db_Kode,$A65) -> 0 | AY65: =+SUMIFS(db_Sum,db_Bln,AY$6,db_Kode,$A65) -> 0 | AZ65: =+SUMIFS(db_Sum,db_Bln,AZ$6,db_Kode,$A65) -> 0 | BA65: =+SUMIFS(db_Sum,db_Bln,BA$6,db_Kode,$A65) -> 0 | ... BE65: =+SUMIFS(db_Sum,db_Bln,BE$6,db_Kode,$A65) -> 601897500 | BF65: =+SUM(AT65:BE65) -> 601897500 | BG65: =+SUMIFS(db_Sum,db_Bln,BG$6,db_Kode,$A65) -> 0 | BH65: =+SUMIFS(db_Sum,db_Bln,BH$6,db_Kode,$A65) -> 0 | BI65: =+SUMIFS(db_Sum,db_Bln,BI$6,db_Kode,$A65) -> 196656000 | BJ65: =+SUMIFS(db_Sum,db_Bln,BJ$6,db_Kode,$A65) -> 0 | BK65: =+SUMIFS(db_Sum,db_Bln,BK$6,db_Kode,$A65) -> 0 | BS65: =+SUM(BG65:BR65) -> 196656000 | BT65: =+SUM(O65,Q65,R65,S65,AF65,AS65,BF65+BS65) -> 798553500 | BU65: =+IF(K65-BT65=0,"OK","ERROR") -> OK
A66: F2 | B66: 2 | C66: Tower | D66: CV.Apung Hotspot | G66: CV.Apung Hotspot | H66: =+IF(E66>K66,E66-K66,0) -> 0 | I66: 78100000 | J66: 78100000 | K66: =+O66+Q66+R66+S66+AF66+AS66+BF66+BS66 -> 78100000 | M66: 0 | O66: =+SUMIFS(db_Sum,db_Bln,O$6,db_Kode,$A66) -> 0 | P66: =+IF(H66=0,E66-K66,0) -> -78100000 | Q66: =+SUMIFS(db_Sum,db_Bln,Q$6,db_Kode,$A66) -> 0 | R66: =+SUMIFS(db_Sum,db_Bln,R$6,db_Kode,$A66) -> 0 | S66: =+SUMIFS(db_Sum,db_Bln,S$6,db_Kode,$A66) -> 0 | T66: =+SUMIFS(db_Sum,db_Bln,T$6,db_Kode,$A66) -> 0 | U66: =+SUMIFS(db_Sum,db_Bln,U$6,db_Kode,$A66) -> 0 | V66: =+SUMIFS(db_Sum,db_Bln,V$6,db_Kode,$A66) -> 0 | W66: =+SUMIFS(db_Sum,db_Bln,W$6,db_Kode,$A66) -> 0 | X66: =+SUMIFS(db_Sum,db_Bln,X$6,db_Kode,$A66) -> 0 | ... AE66: =+SUMIFS(db_Sum,db_Bln,AE$6,db_Kode,$A66) -> 0 | AF66: =+SUM(T66:AE66) -> 0 | AG66: =+SUMIFS(db_Sum,db_Bln,AG$6,db_Kode,$A66) -> 0 | AH66: =+SUMIFS(db_Sum,db_Bln,AH$6,db_Kode,$A66) -> 0 | AI66: =+SUMIFS(db_Sum,db_Bln,AI$6,db_Kode,$A66) -> 0 | AJ66: =+SUMIFS(db_Sum,db_Bln,AJ$6,db_Kode,$A66) -> 0 | AK66: =+SUMIFS(db_Sum,db_Bln,AK$6,db_Kode,$A66) -> 78100000 | AL66: =+SUMIFS(db_Sum,db_Bln,AL$6,db_Kode,$A66) -> 0 | AM66: =+SUMIFS(db_Sum,db_Bln,AM$6,db_Kode,$A66) -> 0 | AN66: =+SUMIFS(db_Sum,db_Bln,AN$6,db_Kode,$A66) -> 0 | ... AR66: =+SUMIFS(db_Sum,db_Bln,AR$6,db_Kode,$A66) -> 0 | AS66: =+SUM(AG66:AR66) -> 78100000 | AT66: =+SUMIFS(db_Sum,db_Bln,AT$6,db_Kode,$A66) -> 0 | AU66: =+SUMIFS(db_Sum,db_Bln,AU$6,db_Kode,$A66) -> 0 | AV66: =+SUMIFS(db_Sum,db_Bln,AV$6,db_Kode,$A66) -> 0 | AW66: =+SUMIFS(db_Sum,db_Bln,AW$6,db_Kode,$A66) -> 0 | AX66: =+SUMIFS(db_Sum,db_Bln,AX$6,db_Kode,$A66) -> 0 | AY66: =+SUMIFS(db_Sum,db_Bln,AY$6,db_Kode,$A66) -> 0 | AZ66: =+SUMIFS(db_Sum,db_Bln,AZ$6,db_Kode,$A66) -> 0 | BA66: =+SUMIFS(db_Sum,db_Bln,BA$6,db_Kode,$A66) -> 0 | ... BE66: =+SUMIFS(db_Sum,db_Bln,BE$6,db_Kode,$A66) -> 0 | BF66: =+SUM(AT66:BE66) -> 0 | BG66: =+SUMIFS(db_Sum,db_Bln,BG$6,db_Kode,$A66) -> 0 | BH66: =+SUMIFS(db_Sum,db_Bln,BH$6,db_Kode,$A66) -> 0 | BI66: =+SUMIFS(db_Sum,db_Bln,BI$6,db_Kode,$A66) -> 0 | BJ66: =+SUMIFS(db_Sum,db_Bln,BJ$6,db_Kode,$A66) -> 0 | BK66: =+SUMIFS(db_Sum,db_Bln,BK$6,db_Kode,$A66) -> 0 | BS66: =+SUM(BG66:BR66) -> 0 | BT66: =+SUM(O66,Q66,R66,S66,AF66,AS66,BF66+BS66) -> 78100000 | BU66: =+IF(K66-BT66=0,"OK","ERROR") -> OK
C67: SUB TOTAL OFFICE BUILDING | E67: =SUM(E65:E66) -> 8880000000 | H67: =SUM(H65:H66) -> 8081446500 | I67: =SUM(I65:I66) -> 876653500 | J67: =SUM(J65:J66) -> 876653500 | K67: =SUM(K65:K66) -> 876653500 | L67: =SUM(L65:L66) -> 0 | M67: =SUM(M65:M66) -> 0 | N67: =K67+L67+M67 -> 876653500 | O67: =SUM(O65:O66) -> 0 | P67: =SUM(P65:P66) -> -78100000 | Q67: =SUM(Q65:Q66) -> 0 | R67: =SUM(R65:R66) -> 0 | S67: =SUM(S65:S66) -> 0 | T67: =SUM(T65:T66) -> 0 | U67: =SUM(U65:U66) -> 0 | V67: =SUM(V65:V66) -> 0 | ... BT67: =SUM(BT65:BT66) -> 876653500 | BU67: =+IF(K67-BT67=0,"OK","ERROR") -> OK | BV67: =BT67-K67 -> 0
C68: TOTAL CIVIL WORK ( A - F ) | E68: =+E29+E38+E44+E53+E63+E67 -> 1.427373e+11 | H68: =+H29+H38+H44+H53+H63+H67 -> #REF! | I68: =+I29+I38+I44+I53+I63+I67 -> 1.457813e+11 | J68: =+J29+J38+J44+J53+J63+J67 -> 1.4624622e+11 | K68: =+K29+K38+K44+K53+K63+K67 -> 1.2972924e+11 | L68: =+L29+L38+L44+L53+L63+L67 -> 7.1806884e+09 | M68: =+M29+M38+M44+M53+M63+M67 -> 8.9369813e+09 | N68: =K68+L68+M68 -> 1.4584691e+11 | O68: =+O29+O38+O44+O53+O63+O67 -> 0 | P68: =+P29+P38+P44+P53+P63+P67 -> #REF! | Q68: =+Q29+Q38+Q44+Q53+Q63+Q67 -> 0 | R68: =+R29+R38+R44+R53+R63+R67 -> 61580600 | S68: =+S29+S38+S44+S53+S63+S67 -> 50000000 | T68: =+T29+T38+T44+T53+T63+T67 -> 0 | U68: =+U29+U38+U44+U53+U63+U67 -> 23650000 | V68: =+V29+V38+V44+V53+V63+V67 -> 0 | ... BT68: =+BT29+BT38+BT44+BT53+BT63+BT67 -> 1.3802449e+11 | BU68: =+IF(K68-BT68=0,"OK","ERROR") -> ERROR | BV68: =BT68-K68 -> 8.2952454e+09
B70: II | C70: MECHANICAL & ELECTRICAL
A71: 21 | B71: 1 | C71: Mechanical | D71: PT. Arina Karya Sentosa | F71: 14/SPK/KS-PKS/MILL-HO/VII/2022 | G71: PT. Arina Karya Sentosa | H71: =E71-K72-K74-K76-K73-#REF!-K75-#REF!-#REF! -> #REF! | O71: =+SUMIFS(db_Sum,db_Bln,O$6,db_Kode,$A71) -> 0 | P71: =+IF(H71=0,E71-K71,0) -> #REF! | Q71: =+SUMIFS(db_Sum,db_Bln,Q$6,db_Kode,$A71) -> 0 | R71: =+SUMIFS(db_Sum,db_Bln,R$6,db_Kode,$A71) -> 0 | S71: =+SUMIFS(db_Sum,db_Bln,S$6,db_Kode,$A71) -> 0 | T71: =+SUMIFS(db_Sum,db_Bln,T$6,db_Kode,$A71) -> 0 | U71: =+SUMIFS(db_Sum,db_Bln,U$6,db_Kode,$A71) -> 0 | V71: =+SUMIFS(db_Sum,db_Bln,V$6,db_Kode,$A71) -> 0 | W71: =+SUMIFS(db_Sum,db_Bln,W$6,db_Kode,$A71) -> 0 | X71: =+SUMIFS(db_Sum,db_Bln,X$6,db_Kode,$A71) -> 0 | ... AE71: =+SUMIFS(db_Sum,db_Bln,AE$6,db_Kode,$A71) -> 0 | AF71: =+SUM(T71:AE71) -> 0 | AG71: =+SUMIFS(db_Sum,db_Bln,AG$6,db_Kode,$A71) -> 0 | AH71: =+SUMIFS(db_Sum,db_Bln,AH$6,db_Kode,$A71) -> 0 | AI71: =+SUMIFS(db_Sum,db_Bln,AI$6,db_Kode,$A71) -> 0 | AJ71: =+SUMIFS(db_Sum,db_Bln,AJ$6,db_Kode,$A71) -> 0 | AK71: =+SUMIFS(db_Sum,db_Bln,AK$6,db_Kode,$A71) -> 0 | AL71: =+SUMIFS(db_Sum,db_Bln,AL$6,db_Kode,$A71) -> 0 | AM71: =+SUMIFS(db_Sum,db_Bln,AM$6,db_Kode,$A71) -> 0 | AN71: =+SUMIFS(db_Sum,db_Bln,AN$6,db_Kode,$A71) -> 0 | ... AR71: =+SUMIFS(db_Sum,db_Bln,AR$6,db_Kode,$A71) -> 3890616129 | AS71: =+SUM(AG71:AR71) -> 27731479305 | AT71: =+SUMIFS(db_Sum,db_Bln,AT$6,db_Kode,$A71) -> 5833033692 | AU71: =+SUMIFS(db_Sum,db_Bln,AU$6,db_Kode,$A71) -> 0 | AV71: =+SUMIFS(db_Sum,db_Bln,AV$6,db_Kode,$A71) -> 0 | AW71: =+SUMIFS(db_Sum,db_Bln,AW$6,db_Kode,$A71) -> 2069599665 | AX71: =+SUMIFS(db_Sum,db_Bln,AX$6,db_Kode,$A71) -> 0 | AY71: =+SUMIFS(db_Sum,db_Bln,AY$6,db_Kode,$A71) -> 953865767 | AZ71: =+SUMIFS(db_Sum,db_Bln,AZ$6,db_Kode,$A71) -> 1618681302 | BA71: =+SUMIFS(db_Sum,db_Bln,BA$6,db_Kode,$A71) -> 2.0002276e+09 | ... BE71: =+SUMIFS(db_Sum,db_Bln,BE$6,db_Kode,$A71) -> 0 | BF71: =+SUM(AT71:BE71) -> 19152468403 | BG71: =+SUMIFS(db_Sum,db_Bln,BG$6,db_Kode,$A71) -> 1202448967 | BH71: =+SUMIFS(db_Sum,db_Bln,BH$6,db_Kode,$A71) -> 1.7053964e+09 | BI71: =+SUMIFS(db_Sum,db_Bln,BI$6,db_Kode,$A71) -> 1653367329 | BJ71: =+SUMIFS(db_Sum,db_Bln,BJ$6,db_Kode,$A71) -> 3.2823341e+09 | BK71: =+SUMIFS(db_Sum,db_Bln,BK$6,db_Kode,$A71) -> 606304320 | BS71: =+SUM(BG71:BR71) -> 8.4498511e+09 | BT71: =+SUM(O71,Q71,R71,S71,AF71,AS71,BF71+BS71) -> 5.5333799e+10 | BU71: =+IF(K71-BT71=0,"OK","ERROR") -> ERROR
B72: - | C72: Kontrak Tahap I | E72: 65865180000 | I72: 65865180000 | J72: 65865180000 | K72: 5.4528795e+10 | L72: 0 | M72: =J72-K72 -> 1.1336385e+10
C73: -Pengakuan A/ Pembayaran DP dan Pot. DP+Ret. | E73: 0 | I73: 0 | J73: 0 | K73: -1488076880 | L73: 0 | M73: 0 | N73: '-Atas Pembayaran Tahap 1,27% sebesar Rp564.629.255,- yang tidak masuk dalam monitoring ini. Dimasukan disini
B74: - | C74: Kontrak Tahap II | E74: 0 | I74: 2331000000 | J74: 2331000000 | K74: 0 | L74: 1771356038 | M74: =J74-L74 -> 559643962 | N74: -Pekerjaan Struktur Solid System -Pekerjaan Struktur RO Boiler -Pekerjaan Struktur Rumah Pompa Pigging -Pekerjaan Struktur ID Fan (2 Unt) -Pekerjaan Conv. EFB No.3
C75: -Pengakuan A/ Pembayaran DP dan Pot. DP+Ret. | E75: 0 | I75: 0 | J75: 0 | K75: 0 | L75: -74261250 | M75: 0
B76: - | C76: Kontrak Tahap III | E76: 0 | I76: 1132200000 | J76: 1132200000 | K76: 0 | L76: 923761980 | M76: =J76-L76 -> 208438020 | N76: -Instalasi Turbin c/w Piping -Siku dan Anchor L. Ramp No. 3 -Struktur Monorel u/ HSS -Penambahan Fire Hydrant -Gearmotor Polishing Drum
A77: 22 | B77: 2 | C77: Electrical | D77: PT. Sinergi Indo Pratama | F77: 17/SPK/KS-PKS/MILL-HO/VII/2022 | G77: PT. Sinergi Indo Pratama | H77: =E78-K78-K80-K82-K79-K81 -> 4.6530934e+08 | O77: =+SUMIFS(db_Sum,db_Bln,O$6,db_Kode,$A77) -> 0 | P77: =+IF(H77=0,E78-K77,0) -> 0 | Q77: =+SUMIFS(db_Sum,db_Bln,Q$6,db_Kode,$A77) -> 0 | R77: =+SUMIFS(db_Sum,db_Bln,R$6,db_Kode,$A77) -> 0 | S77: =+SUMIFS(db_Sum,db_Bln,S$6,db_Kode,$A77) -> 0 | T77: =+SUMIFS(db_Sum,db_Bln,T$6,db_Kode,$A77) -> 0 | U77: =+SUMIFS(db_Sum,db_Bln,U$6,db_Kode,$A77) -> 0 | V77: =+SUMIFS(db_Sum,db_Bln,V$6,db_Kode,$A77) -> 0 | W77: =+SUMIFS(db_Sum,db_Bln,W$6,db_Kode,$A77) -> 0 | X77: =+SUMIFS(db_Sum,db_Bln,X$6,db_Kode,$A77) -> 0 | ... AE77: =+SUMIFS(db_Sum,db_Bln,AE$6,db_Kode,$A77) -> 0 | AF77: =+SUM(T77:AE77) -> 0 | AG77: =+SUMIFS(db_Sum,db_Bln,AG$6,db_Kode,$A77) -> 0 | AH77: =+SUMIFS(db_Sum,db_Bln,AH$6,db_Kode,$A77) -> 0 | AI77: =+SUMIFS(db_Sum,db_Bln,AI$6,db_Kode,$A77) -> 0 | AJ77: =+SUMIFS(db_Sum,db_Bln,AJ$6,db_Kode,$A77) -> 0 | AK77: =+SUMIFS(db_Sum,db_Bln,AK$6,db_Kode,$A77) -> 0 | AL77: =+SUMIFS(db_Sum,db_Bln,AL$6,db_Kode,$A77) -> 0 | AM77: =+SUMIFS(db_Sum,db_Bln,AM$6,db_Kode,$A77) -> 0 | AN77: =+SUMIFS(db_Sum,db_Bln,AN$6,db_Kode,$A77) -> 0 | ... AR77: =+SUMIFS(db_Sum,db_Bln,AR$6,db_Kode,$A77) -> 0 | AS77: =+SUM(AG77:AR77) -> 4433996941 | AT77: =+SUMIFS(db_Sum,db_Bln,AT$6,db_Kode,$A77) -> 0 | AU77: =+SUMIFS(db_Sum,db_Bln,AU$6,db_Kode,$A77) -> 877244012 | AV77: =+SUMIFS(db_Sum,db_Bln,AV$6,db_Kode,$A77) -> 0 | AW77: =+SUMIFS(db_Sum,db_Bln,AW$6,db_Kode,$A77) -> 0 | AX77: =+SUMIFS(db_Sum,db_Bln,AX$6,db_Kode,$A77) -> 0 | AY77: =+SUMIFS(db_Sum,db_Bln,AY$6,db_Kode,$A77) -> 197877025 | AZ77: =+SUMIFS(db_Sum,db_Bln,AZ$6,db_Kode,$A77) -> 0 | BA77: =+SUMIFS(db_Sum,db_Bln,BA$6,db_Kode,$A77) -> 3030909329 | ... BE77: =+SUMIFS(db_Sum,db_Bln,BE$6,db_Kode,$A77) -> 1063745889 | BF77: =+SUM(AT77:BE77) -> 10240592067 | BG77: =+SUMIFS(db_Sum,db_Bln,BG$6,db_Kode,$A77) -> 985264569 | BH77: =+SUMIFS(db_Sum,db_Bln,BH$6,db_Kode,$A77) -> 0 | BI77: =+SUMIFS(db_Sum,db_Bln,BI$6,db_Kode,$A77) -> 301151189 | BJ77: =+SUMIFS(db_Sum,db_Bln,BJ$6,db_Kode,$A77) -> 0 | BK77: =+SUMIFS(db_Sum,db_Bln,BK$6,db_Kode,$A77) -> 0 | BS77: =+SUM(BG77:BR77) -> 1286415758 | BT77: =+SUM(O77,Q77,R77,S77,AF77,AS77,BF77+BS77) -> 15961004766 | BU77: =+IF(K77-BT77=0,"OK","ERROR") -> ERROR
B78: - | C78: Kontrak Tahap I | E78: 13264500000 | I78: 1.32645e+10 | J78: 1.32645e+10 | K78: 1.2472491e+10 | L78: 4.8174e+08 | M78: =J78-K78 -> 7.9200948e+08 | N78: -Penambahan Panel Turbin 2 -Modifikasi Panel Capacitor Bank
C79: -Pengakuan A/ Pembayaran DP dan Pot. DP+Ret. | E79: 0 | I79: 0 | J79: 0 | K79: 3.2670014e+08 | L79: 0 | M79: 0
B80: - | C80: Kontrak Tahap II | E80: 0 | I80: 5.8687063e+08 | J80: 5.8687063e+08 | L80: 5.5752709e+08 | M80: =J80-L80 -> 29343531 | N80: -Perubahan Komponen LVMDP -Penambahan Komponen Panel untuk EFB no.3 -Penambahan AutoTrafo u/ Oil Loading -Penambahan Komponen Oil Loading -Penambahan Komponen Panel All Station
C81: -Pengakuan A/ Pembayaran DP dan Pot. DP+Ret. | E81: 0 | I81: 0 | J81: 0 | K81: 0 | L81: 14803944 | M81: 0
B82: - | C82: Kontrak Tahap III | E82: 0 | I82: 2.4499037e+08 | J82: 2.4499037e+08 | K82: 0 | L82: 0 | M82: =J82-L82 -> 2.4499037e+08 | N82: -Penambahan Material Grounding -Penambahan 1 Set Lightning Arrester -Penambahan Material dan Instalasi Tray Cable -Pengurangan Kabel Twisted -Pengurangan Instalasi Lampu dan Acc
A83: 24 | B83: 3 | C83: Material Lainnya | E83: 0 | H83: =E83-K83 -> -1.1977642e+08 | I83: 0 | J83: 1.1977642e+08 | K83: =+O83+Q83+R83+S83+AF83+AS83+BF83+BS83 -> 1.1977642e+08 | L83: 0 | M83: 0 | N83: -Material (Oli, Valve, Flowmeter dan Pipa Besi) dan konsumabel workhsop lainnya | P83: =+IF(H83=0,E83-K83,0) -> 0 | AT83: =+SUMIFS(db_Sum,db_Bln,AT$6,db_Kode,$A83) -> 196000 | AU83: =+SUMIFS(db_Sum,db_Bln,AU$6,db_Kode,$A83) -> 1109043.7 | AV83: =+SUMIFS(db_Sum,db_Bln,AV$6,db_Kode,$A83) -> 0 | AW83: =+SUMIFS(db_Sum,db_Bln,AW$6,db_Kode,$A83) -> 0 | AX83: =+SUMIFS(db_Sum,db_Bln,AX$6,db_Kode,$A83) -> 0 | AY83: =+SUMIFS(db_Sum,db_Bln,AY$6,db_Kode,$A83) -> 0 | AZ83: =+SUMIFS(db_Sum,db_Bln,AZ$6,db_Kode,$A83) -> 0 | BA83: =+SUMIFS(db_Sum,db_Bln,BA$6,db_Kode,$A83) -> 0 | ... BE83: =+SUMIFS(db_Sum,db_Bln,BE$6,db_Kode,$A83) -> 0 | BF83: =+SUM(AT83:BE83) -> 10578392 | BG83: =+SUMIFS(db_Sum,db_Bln,BG$6,db_Kode,$A83) -> 7316568 | BH83: =+SUMIFS(db_Sum,db_Bln,BH$6,db_Kode,$A83) -> 4071332 | BI83: =+SUMIFS(db_Sum,db_Bln,BI$6,db_Kode,$A83) -> 69503.04 | BJ83: =+SUMIFS(db_Sum,db_Bln,BJ$6,db_Kode,$A83) -> 4219267.8 | BK83: =+SUMIFS(db_Sum,db_Bln,BK$6,db_Kode,$A83) -> 93521362 | BS83: =+SUM(BG83:BR83) -> 1.0919803e+08 | BT83: =+SUM(O83,Q83,R83,S83,AF83,AS83,BF83+BS83) -> 1.1977642e+08 | BU83: =+IF(K83-BT83=0,"OK","ERROR") -> OK
C84: TOTAL MECHANICAL & ELECTRICAL | E84: =SUM(E71:E83) -> 79129680000 | H84: =SUM(H71:H83) -> #REF! | I84: =SUM(I71:I83) -> 8.3424741e+10 | J84: =SUM(J71:J83) -> 8.3544517e+10 | K84: =SUM(K71:K83)-K73-K79 -> 6.7121061e+10 | L84: =SUM(L71:L83)-L81-L75 -> 3.7343851e+09 | M84: =SUM(M71:M83) -> 1.3170811e+10 | N84: =K84+L84+M84 -> 8.4026257e+10 | O84: =SUM(O71:O83) -> 0 | P84: =SUM(P71:P83) -> #REF! | Q84: =SUM(Q71:Q82) -> 0 | R84: =SUM(R71:R82) -> 0 | S84: =SUM(S71:S82) -> 0 | T84: =SUM(T71:T82) -> 0 | U84: =SUM(U71:U82) -> 0 | V84: =SUM(V71:V82) -> 0 | W84: =SUM(W71:W82) -> 0 | X84: =SUM(X71:X82) -> 0 | ... AS84: =SUM(AS71:AS82) -> 32165476246 | AT84: =SUM(AT71:AT83) -> 5833229692 | AU84: =SUM(AU71:AU83) -> 8.7835306e+08 | AV84: =SUM(AV71:AV83) -> 0 | AW84: =SUM(AW71:AW83) -> 2069599665 | AX84: =SUM(AX71:AX83) -> 0 | AY84: =SUM(AY71:AY83) -> 1151742792 | AZ84: =SUM(AZ71:AZ83) -> 1618681302 | BA84: =SUM(BA71:BA83) -> 5031136937 | ... BT84: =SUM(BT71:BT83) -> 7.141458e+10 | BU84: =+IF(K84-BT84=0,"OK","ERROR") -> ERROR | BV84: =BT84-K84 -> 4.2935185e+09
B86: III | C86: OWNER SUPPLY ITEM
A87: 31 | B87: 1 | C87: Turbin Shinco | D87: PT. Kharisma Pratama | E87: 2886000000 | F87: 02/SPK/KS-PKS/MILL-HO/IV/2022 | G87: PT. Kharisma Pratama | H87: =E87-K87 -> 144300000 | I87: 2886000000 | J87: 2886000000 | K87: =+O87+Q87+R87+S87+AF87+AS87+BF87+BS87-K88 -> 2741700000 | L87: 0 | M87: =J87-K87 -> 144300000 | N87: -Pemakaian Persediaan | O87: =+SUMIFS(db_Sum,db_Bln,O$6,db_Kode,$A87) -> 0 | P87: =+IF(H87=0,E87-K87,0) -> 0 | Q87: =+SUMIFS(db_Sum,db_Bln,Q$6,db_Kode,$A87) -> 0 | R87: =+SUMIFS(db_Sum,db_Bln,R$6,db_Kode,$A87) -> 0 | S87: =+SUMIFS(db_Sum,db_Bln,S$6,db_Kode,$A87) -> 0 | T87: =+SUMIFS(db_Sum,db_Bln,T$6,db_Kode,$A87) -> 0 | U87: =+SUMIFS(db_Sum,db_Bln,U$6,db_Kode,$A87) -> 0 | V87: =+SUMIFS(db_Sum,db_Bln,V$6,db_Kode,$A87) -> 0 | W87: =+SUMIFS(db_Sum,db_Bln,W$6,db_Kode,$A87) -> 0 | X87: =+SUMIFS(db_Sum,db_Bln,X$6,db_Kode,$A87) -> 0 | ... AE87: =+SUMIFS(db_Sum,db_Bln,AE$6,db_Kode,$A87) -> 0 | AF87: =+SUM(T87:AE87) -> 0 | AG87: =+SUMIFS(db_Sum,db_Bln,AG$6,db_Kode,$A87) -> 0 | AH87: =+SUMIFS(db_Sum,db_Bln,AH$6,db_Kode,$A87) -> 0 | AI87: =+SUMIFS(db_Sum,db_Bln,AI$6,db_Kode,$A87) -> 0 | AJ87: =+SUMIFS(db_Sum,db_Bln,AJ$6,db_Kode,$A87) -> 0 | AK87: =+SUMIFS(db_Sum,db_Bln,AK$6,db_Kode,$A87) -> 0 | AL87: =+SUMIFS(db_Sum,db_Bln,AL$6,db_Kode,$A87) -> 0 | AM87: =+SUMIFS(db_Sum,db_Bln,AM$6,db_Kode,$A87) -> 0 | AN87: =+SUMIFS(db_Sum,db_Bln,AN$6,db_Kode,$A87) -> 0 | ... AR87: =+SUMIFS(db_Sum,db_Bln,AR$6,db_Kode,$A87) -> 0 | AS87: =+SUM(AG87:AR87) -> 0 | AT87: =+SUMIFS(db_Sum,db_Bln,AT$6,db_Kode,$A87) -> 0 | AU87: =+SUMIFS(db_Sum,db_Bln,AU$6,db_Kode,$A87) -> 0 | AV87: =+SUMIFS(db_Sum,db_Bln,AV$6,db_Kode,$A87) -> 0 | AW87: =+SUMIFS(db_Sum,db_Bln,AW$6,db_Kode,$A87) -> 0 | AX87: =+SUMIFS(db_Sum,db_Bln,AX$6,db_Kode,$A87) -> 0 | AY87: =+SUMIFS(db_Sum,db_Bln,AY$6,db_Kode,$A87) -> 0 | AZ87: =+SUMIFS(db_Sum,db_Bln,AZ$6,db_Kode,$A87) -> 0 | BA87: =+SUMIFS(db_Sum,db_Bln,BA$6,db_Kode,$A87) -> 0 | ... BE87: =+SUMIFS(db_Sum,db_Bln,BE$6,db_Kode,$A87) -> 2886000000 | BF87: =+SUM(AT87:BE87) -> 2886000000 | BG87: =+SUMIFS(db_Sum,db_Bln,BG$6,db_Kode,$A87) -> 0 | BH87: =+SUMIFS(db_Sum,db_Bln,BH$6,db_Kode,$A87) -> 0 | BI87: =+SUMIFS(db_Sum,db_Bln,BI$6,db_Kode,$A87) -> 0 | BJ87: =+SUMIFS(db_Sum,db_Bln,BJ$6,db_Kode,$A87) -> 0 | BK87: =+SUMIFS(db_Sum,db_Bln,BK$6,db_Kode,$A87) -> 0 | BS87: =+SUM(BG87:BR87) -> 0 | BT87: =+SUM(O87,Q87,R87,S87,AF87,AS87,BF87+BS87) -> 2886000000 | BU87: =+IF(K87-BT87=0,"OK","ERROR") -> ERROR
C88: -Retensi | K88: 144300000 | N88: -Sisa Retensi 5%
A89: 31A | C89: Turbin PRIME | D89: Jasa Aman Engineering | E89: 0 | F89: 02/SPK/KS-PKS/MILL-HO/IV/2022 | G89: PT. Kharisma Pratama | H89: =E89-K89 -> -1869345000 | I89: 1869345000 | J89: 1869345000 | K89: =+O89+Q89+R89+S89+AF89+AS89+BF89+BS89 -> 1869345000 | L89: 0 | M89: =J89-K89 -> 0 | N89: -Pemakaian Persediaan | O89: =+SUMIFS(db_Sum,db_Bln,O$6,db_Kode,$A89) -> 0 | P89: =+IF(H89=0,E89-K89,0) -> 0 | Q89: =+SUMIFS(db_Sum,db_Bln,Q$6,db_Kode,$A89) -> 0 | R89: =+SUMIFS(db_Sum,db_Bln,R$6,db_Kode,$A89) -> 0 | S89: =+SUMIFS(db_Sum,db_Bln,S$6,db_Kode,$A89) -> 0 | T89: =+SUMIFS(db_Sum,db_Bln,T$6,db_Kode,$A89) -> 0 | U89: =+SUMIFS(db_Sum,db_Bln,U$6,db_Kode,$A89) -> 0 | V89: =+SUMIFS(db_Sum,db_Bln,V$6,db_Kode,$A89) -> 0 | W89: =+SUMIFS(db_Sum,db_Bln,W$6,db_Kode,$A89) -> 0 | X89: =+SUMIFS(db_Sum,db_Bln,X$6,db_Kode,$A89) -> 0 | ... AE89: =+SUMIFS(db_Sum,db_Bln,AE$6,db_Kode,$A89) -> 0 | AF89: =+SUM(T89:AE89) -> 0 | AG89: =+SUMIFS(db_Sum,db_Bln,AG$6,db_Kode,$A89) -> 0 | AH89: =+SUMIFS(db_Sum,db_Bln,AH$6,db_Kode,$A89) -> 0 | AI89: =+SUMIFS(db_Sum,db_Bln,AI$6,db_Kode,$A89) -> 0 | AJ89: =+SUMIFS(db_Sum,db_Bln,AJ$6,db_Kode,$A89) -> 0 | AK89: =+SUMIFS(db_Sum,db_Bln,AK$6,db_Kode,$A89) -> 0 | AL89: =+SUMIFS(db_Sum,db_Bln,AL$6,db_Kode,$A89) -> 0 | AM89: =+SUMIFS(db_Sum,db_Bln,AM$6,db_Kode,$A89) -> 0 | AN89: =+SUMIFS(db_Sum,db_Bln,AN$6,db_Kode,$A89) -> 0 | ... AR89: =+SUMIFS(db_Sum,db_Bln,AR$6,db_Kode,$A89) -> 0 | AS89: =+SUM(AG89:AR89) -> 0 | AT89: =+SUMIFS(db_Sum,db_Bln,AT$6,db_Kode,$A89) -> 0 | AU89: =+SUMIFS(db_Sum,db_Bln,AU$6,db_Kode,$A89) -> 0 | AV89: =+SUMIFS(db_Sum,db_Bln,AV$6,db_Kode,$A89) -> 0 | AW89: =+SUMIFS(db_Sum,db_Bln,AW$6,db_Kode,$A89) -> 0 | AX89: =+SUMIFS(db_Sum,db_Bln,AX$6,db_Kode,$A89) -> 0 | AY89: =+SUMIFS(db_Sum,db_Bln,AY$6,db_Kode,$A89) -> 0 | AZ89: =+SUMIFS(db_Sum,db_Bln,AZ$6,db_Kode,$A89) -> 0 | BA89: =+SUMIFS(db_Sum,db_Bln,BA$6,db_Kode,$A89) -> 0 | ... BE89: =+SUMIFS(db_Sum,db_Bln,BE$6,db_Kode,$A89) -> 1869345000 | BF89: =+SUM(AT89:BE89) -> 1869345000 | BG89: =+SUMIFS(db_Sum,db_Bln,BG$6,db_Kode,$A89) -> 0 | BH89: =+SUMIFS(db_Sum,db_Bln,BH$6,db_Kode,$A89) -> 0 | BI89: =+SUMIFS(db_Sum,db_Bln,BI$6,db_Kode,$A89) -> 0 | BJ89: =+SUMIFS(db_Sum,db_Bln,BJ$6,db_Kode,$A89) -> 0 | BK89: =+SUMIFS(db_Sum,db_Bln,BK$6,db_Kode,$A89) -> 0 | BS89: =+SUM(BG89:BR89) -> 0 | BT89: =+SUM(O89,Q89,R89,S89,AF89,AS89,BF89+BS89) -> 1869345000 | BU89: =+IF(K89-BT89=0,"OK","ERROR") -> OK
C90: -Atas Bea Cukai, PPn dan PPh Turbin Prime | E90: 0 | I90: 0 | J90: 244943000 | K90: 244943000 | L90: 0 | M90: 0
A91: 32 | B91: 2 | C91: Empty Bunch Press Sunley | D91: PT. Budijaya Cemerlang | E91: 2042400000 | F91: 03/SPK/KS-PKS/MILL-HO/IV/2022 | G91: PT. Budijaya Cemerlang | H91: =E91-K91 -> 104340000 | I91: 2153400000 | J91: 2153400000 | K91: =+O91+Q91+R91+S91+AF91+AS91+BF91+BS91-K93-K92 -> 1938060000 | M91: =J91-K91 -> 215340000 | N91: -Pemakaian Persediaan | O91: =+SUMIFS(db_Sum,db_Bln,O$6,db_Kode,$A91) -> 0 | P91: =+IF(H91=0,E91-K91,0) -> 0 | Q91: =+SUMIFS(db_Sum,db_Bln,Q$6,db_Kode,$A91) -> 0 | R91: =+SUMIFS(db_Sum,db_Bln,R$6,db_Kode,$A91) -> 0 | S91: =+SUMIFS(db_Sum,db_Bln,S$6,db_Kode,$A91) -> 0 | T91: =+SUMIFS(db_Sum,db_Bln,T$6,db_Kode,$A91) -> 0 | U91: =+SUMIFS(db_Sum,db_Bln,U$6,db_Kode,$A91) -> 0 | V91: =+SUMIFS(db_Sum,db_Bln,V$6,db_Kode,$A91) -> 0 | W91: =+SUMIFS(db_Sum,db_Bln,W$6,db_Kode,$A91) -> 0 | X91: =+SUMIFS(db_Sum,db_Bln,X$6,db_Kode,$A91) -> 0 | ... AE91: =+SUMIFS(db_Sum,db_Bln,AE$6,db_Kode,$A91) -> 0 | AF91: =+SUM(T91:AE91) -> 0 | AG91: =+SUMIFS(db_Sum,db_Bln,AG$6,db_Kode,$A91) -> 0 | AH91: =+SUMIFS(db_Sum,db_Bln,AH$6,db_Kode,$A91) -> 0 | AI91: =+SUMIFS(db_Sum,db_Bln,AI$6,db_Kode,$A91) -> 0 | AJ91: =+SUMIFS(db_Sum,db_Bln,AJ$6,db_Kode,$A91) -> 0 | AK91: =+SUMIFS(db_Sum,db_Bln,AK$6,db_Kode,$A91) -> 0 | AL91: =+SUMIFS(db_Sum,db_Bln,AL$6,db_Kode,$A91) -> 0 | AM91: =+SUMIFS(db_Sum,db_Bln,AM$6,db_Kode,$A91) -> 0 | AN91: =+SUMIFS(db_Sum,db_Bln,AN$6,db_Kode,$A91) -> 0 | ... AR91: =+SUMIFS(db_Sum,db_Bln,AR$6,db_Kode,$A91) -> 0 | AS91: =+SUM(AG91:AR91) -> 0 | AT91: =+SUMIFS(db_Sum,db_Bln,AT$6,db_Kode,$A91) -> 0 | AU91: =+SUMIFS(db_Sum,db_Bln,AU$6,db_Kode,$A91) -> 0 | AV91: =+SUMIFS(db_Sum,db_Bln,AV$6,db_Kode,$A91) -> 0 | AW91: =+SUMIFS(db_Sum,db_Bln,AW$6,db_Kode,$A91) -> 0 | AX91: =+SUMIFS(db_Sum,db_Bln,AX$6,db_Kode,$A91) -> 0 | AY91: =+SUMIFS(db_Sum,db_Bln,AY$6,db_Kode,$A91) -> 0 | AZ91: =+SUMIFS(db_Sum,db_Bln,AZ$6,db_Kode,$A91) -> 0 | BA91: =+SUMIFS(db_Sum,db_Bln,BA$6,db_Kode,$A91) -> 0 | ... BE91: =+SUMIFS(db_Sum,db_Bln,BE$6,db_Kode,$A91) -> 0 | BF91: =+SUM(AT91:BE91) -> 0 | BG91: =+SUMIFS(db_Sum,db_Bln,BG$6,db_Kode,$A91) -> 0 | BH91: =+SUMIFS(db_Sum,db_Bln,BH$6,db_Kode,$A91) -> 0 | BI91: =+SUMIFS(db_Sum,db_Bln,BI$6,db_Kode,$A91) -> 0 | BJ91: =+SUMIFS(db_Sum,db_Bln,BJ$6,db_Kode,$A91) -> 0 | BK91: =+SUMIFS(db_Sum,db_Bln,BK$6,db_Kode,$A91) -> 2154321855 | BS91: =+SUM(BG91:BR91) -> 2154321855 | BT91: =+SUM(O91,Q91,R91,S91,AF91,AS91,BF91+BS91) -> 2154321855 | BU91: =+IF(K91-BT91=0,"OK","ERROR") -> ERROR
C92: -Retensi | K92: 215340000 | N92: -Sisa Retensi 5%
C93: -Oli Bunch press | E93: 0 | I93: 0 | J93: 921855 | K93: 921855 | L93: 0 | M93: 0 | N93: -Oli untuk Bunch Press
A94: 33 | B94: =B91+1 -> 3 | C94: Pengolahan Limbah | D94: PT. Prima Jaya Engineering | E94: 20535000000 | F94: 04/SPK/KS-PKS/MILL-HO/IV/2022 | G94: PT. Prima Jaya Engineering | H94: =E94-K94 -> 7187250000 | I94: 20535000000 | J94: 20535000000 | K94: =+O94+Q94+R94+S94+AF94+AS94+BF94+BS94 -> 13347750000 | L94: 0 | M94: =J94-K94 -> 7187250000 | N94: -Sisa Commisioning dan Retensi | O94: =+SUMIFS(db_Sum,db_Bln,O$6,db_Kode,$A94) -> 0 | P94: =+IF(H94=0,E94-K94,0) -> 0 | Q94: =+SUMIFS(db_Sum,db_Bln,Q$6,db_Kode,$A94) -> 0 | R94: =+SUMIFS(db_Sum,db_Bln,R$6,db_Kode,$A94) -> 0 | S94: =+SUMIFS(db_Sum,db_Bln,S$6,db_Kode,$A94) -> 0 | T94: =+SUMIFS(db_Sum,db_Bln,T$6,db_Kode,$A94) -> 0 | U94: =+SUMIFS(db_Sum,db_Bln,U$6,db_Kode,$A94) -> 0 | V94: =+SUMIFS(db_Sum,db_Bln,V$6,db_Kode,$A94) -> 0 | W94: =+SUMIFS(db_Sum,db_Bln,W$6,db_Kode,$A94) -> 0 | X94: =+SUMIFS(db_Sum,db_Bln,X$6,db_Kode,$A94) -> 0 | ... AE94: =+SUMIFS(db_Sum,db_Bln,AE$6,db_Kode,$A94) -> 0 | AF94: =+SUM(T94:AE94) -> 0 | AG94: =+SUMIFS(db_Sum,db_Bln,AG$6,db_Kode,$A94) -> 0 | AH94: =+SUMIFS(db_Sum,db_Bln,AH$6,db_Kode,$A94) -> 0 | AI94: =+SUMIFS(db_Sum,db_Bln,AI$6,db_Kode,$A94) -> 0 | AJ94: =+SUMIFS(db_Sum,db_Bln,AJ$6,db_Kode,$A94) -> 0 | AK94: =+SUMIFS(db_Sum,db_Bln,AK$6,db_Kode,$A94) -> 0 | AL94: =+SUMIFS(db_Sum,db_Bln,AL$6,db_Kode,$A94) -> 0 | AM94: =+SUMIFS(db_Sum,db_Bln,AM$6,db_Kode,$A94) -> 0 | AN94: =+SUMIFS(db_Sum,db_Bln,AN$6,db_Kode,$A94) -> 0 | ... AR94: =+SUMIFS(db_Sum,db_Bln,AR$6,db_Kode,$A94) -> 2053500000 | AS94: =+SUM(AG94:AR94) -> 7187250000 | AT94: =+SUMIFS(db_Sum,db_Bln,AT$6,db_Kode,$A94) -> 0 | AU94: =+SUMIFS(db_Sum,db_Bln,AU$6,db_Kode,$A94) -> 0 | AV94: =+SUMIFS(db_Sum,db_Bln,AV$6,db_Kode,$A94) -> 6160500000 | AW94: =+SUMIFS(db_Sum,db_Bln,AW$6,db_Kode,$A94) -> 0 | AX94: =+SUMIFS(db_Sum,db_Bln,AX$6,db_Kode,$A94) -> 0 | AY94: =+SUMIFS(db_Sum,db_Bln,AY$6,db_Kode,$A94) -> 0 | AZ94: =+SUMIFS(db_Sum,db_Bln,AZ$6,db_Kode,$A94) -> 0 | BA94: =+SUMIFS(db_Sum,db_Bln,BA$6,db_Kode,$A94) -> 0 | ... BE94: =+SUMIFS(db_Sum,db_Bln,BE$6,db_Kode,$A94) -> 0 | BF94: =+SUM(AT94:BE94) -> 6160500000 | BG94: =+SUMIFS(db_Sum,db_Bln,BG$6,db_Kode,$A94) -> 0 | BH94: =+SUMIFS(db_Sum,db_Bln,BH$6,db_Kode,$A94) -> 0 | BI94: =+SUMIFS(db_Sum,db_Bln,BI$6,db_Kode,$A94) -> 0 | BJ94: =+SUMIFS(db_Sum,db_Bln,BJ$6,db_Kode,$A94) -> 0 | BK94: =+SUMIFS(db_Sum,db_Bln,BK$6,db_Kode,$A94) -> 0 | BS94: =+SUM(BG94:BR94) -> 0 | BT94: =+SUM(O94,Q94,R94,S94,AF94,AS94,BF94+BS94) -> 13347750000 | BU94: =+IF(K94-BT94=0,"OK","ERROR") -> OK
A95: 34 | B95: =B94+1 -> 4 | C95: Valve | D95: PT. Budijaya Makmur Sentosa | E95: 2186799900 | F95: 09/SPK/KS-PKS/MILL-HO/IV/2022 | G95: PT. Budijaya Makmur Sentosa | H95: =E95-K95 -> 218679990 | I95: 2186799900 | J95: 2186799900 | K95: =2186799900-K96 -> 1968119910 | L95: 0 | M95: =J95-K95 -> 218679990 | N95: -Pemakaian Persediaan | O95: =+SUMIFS(db_Sum,db_Bln,O$6,db_Kode,$A95) -> 0 | P95: =+IF(H95=0,E95-K95,0) -> 0 | Q95: =+SUMIFS(db_Sum,db_Bln,Q$6,db_Kode,$A95) -> 0 | R95: =+SUMIFS(db_Sum,db_Bln,R$6,db_Kode,$A95) -> 0 | S95: =+SUMIFS(db_Sum,db_Bln,S$6,db_Kode,$A95) -> 0 | T95: =+SUMIFS(db_Sum,db_Bln,T$6,db_Kode,$A95) -> 0 | U95: =+SUMIFS(db_Sum,db_Bln,U$6,db_Kode,$A95) -> 0 | V95: =+SUMIFS(db_Sum,db_Bln,V$6,db_Kode,$A95) -> 0 | W95: =+SUMIFS(db_Sum,db_Bln,W$6,db_Kode,$A95) -> 0 | X95: =+SUMIFS(db_Sum,db_Bln,X$6,db_Kode,$A95) -> 0 | ... AE95: =+SUMIFS(db_Sum,db_Bln,AE$6,db_Kode,$A95) -> 0 | AF95: =+SUM(T95:AE95) -> 0 | AG95: =+SUMIFS(db_Sum,db_Bln,AG$6,db_Kode,$A95) -> 0 | AH95: =+SUMIFS(db_Sum,db_Bln,AH$6,db_Kode,$A95) -> 0 | AI95: =+SUMIFS(db_Sum,db_Bln,AI$6,db_Kode,$A95) -> 0 | AJ95: =+SUMIFS(db_Sum,db_Bln,AJ$6,db_Kode,$A95) -> 0 | AK95: =+SUMIFS(db_Sum,db_Bln,AK$6,db_Kode,$A95) -> 0 | AL95: =+SUMIFS(db_Sum,db_Bln,AL$6,db_Kode,$A95) -> 0 | AM95: =+SUMIFS(db_Sum,db_Bln,AM$6,db_Kode,$A95) -> 0 | AN95: =+SUMIFS(db_Sum,db_Bln,AN$6,db_Kode,$A95) -> 0 | ... AR95: =+SUMIFS(db_Sum,db_Bln,AR$6,db_Kode,$A95) -> 0 | AS95: =+SUM(AG95:AR95) -> 0 | AT95: =+SUMIFS(db_Sum,db_Bln,AT$6,db_Kode,$A95) -> 0 | AU95: =+SUMIFS(db_Sum,db_Bln,AU$6,db_Kode,$A95) -> 0 | AV95: =+SUMIFS(db_Sum,db_Bln,AV$6,db_Kode,$A95) -> 0 | AW95: =+SUMIFS(db_Sum,db_Bln,AW$6,db_Kode,$A95) -> 0 | AX95: =+SUMIFS(db_Sum,db_Bln,AX$6,db_Kode,$A95) -> 0 | AY95: =+SUMIFS(db_Sum,db_Bln,AY$6,db_Kode,$A95) -> 94986196 | AZ95: =+SUMIFS(db_Sum,db_Bln,AZ$6,db_Kode,$A95) -> 0 | BA95: =+SUMIFS(db_Sum,db_Bln,BA$6,db_Kode,$A95) -> 0 | ... BE95: =+SUMIFS(db_Sum,db_Bln,BE$6,db_Kode,$A95) -> 1.8289786e+09 | BF95: =+SUM(AT95:BE95) -> 2.0907255e+09 | BG95: =+SUMIFS(db_Sum,db_Bln,BG$6,db_Kode,$A95) -> 0 | BH95: =+SUMIFS(db_Sum,db_Bln,BH$6,db_Kode,$A95) -> 0 | BI95: =+SUMIFS(db_Sum,db_Bln,BI$6,db_Kode,$A95) -> 0 | BJ95: =+SUMIFS(db_Sum,db_Bln,BJ$6,db_Kode,$A95) -> 0 | BK95: =+SUMIFS(db_Sum,db_Bln,BK$6,db_Kode,$A95) -> 0 | BS95: =+SUM(BG95:BR95) -> 0 | BT95: =+SUM(O95,Q95,R95,S95,AF95,AS95,BF95+BS95) -> 2.0907255e+09 | BU95: =+IF(K95-BT95=0,"OK","ERROR") -> ERROR
C96: -Retensi | K96: 218679990 | N96: -Sisa Retensi 10%
A97: 34A | C97: -Tambahan Valve Turbin Prime | D97: PT. Budijaya Cemerlang | F97: 08/SPK/KS-PKS/MILL-HO/IV/2022 | G97: PT. Budijaya Cemerlang | H97: =E97-K97 -> -1.7018256e+08 | I97: 1.7018256e+08 | J97: 1.7018256e+08 | K97: =+O97+Q97+R97+S97+AF97+AS97+BF97+BS97 -> 1.7018256e+08 | L97: 0 | M97: =J97-K97 -> 0 | N97: -Pemakaian Persediaan | O97: =+SUMIFS(db_Sum,db_Bln,O$6,db_Kode,$A97) -> 0 | P97: =+IF(H97=0,E97-K97,0) -> 0 | Q97: =+SUMIFS(db_Sum,db_Bln,Q$6,db_Kode,$A97) -> 0 | R97: =+SUMIFS(db_Sum,db_Bln,R$6,db_Kode,$A97) -> 0 | S97: =+SUMIFS(db_Sum,db_Bln,S$6,db_Kode,$A97) -> 0 | T97: =+SUMIFS(db_Sum,db_Bln,T$6,db_Kode,$A97) -> 0 | U97: =+SUMIFS(db_Sum,db_Bln,U$6,db_Kode,$A97) -> 0 | V97: =+SUMIFS(db_Sum,db_Bln,V$6,db_Kode,$A97) -> 0 | W97: =+SUMIFS(db_Sum,db_Bln,W$6,db_Kode,$A97) -> 0 | X97: =+SUMIFS(db_Sum,db_Bln,X$6,db_Kode,$A97) -> 0 | ... AE97: =+SUMIFS(db_Sum,db_Bln,AE$6,db_Kode,$A97) -> 0 | AF97: =+SUM(T97:AE97) -> 0 | AG97: =+SUMIFS(db_Sum,db_Bln,AG$6,db_Kode,$A97) -> 0 | AH97: =+SUMIFS(db_Sum,db_Bln,AH$6,db_Kode,$A97) -> 0 | AI97: =+SUMIFS(db_Sum,db_Bln,AI$6,db_Kode,$A97) -> 0 | AJ97: =+SUMIFS(db_Sum,db_Bln,AJ$6,db_Kode,$A97) -> 0 | AK97: =+SUMIFS(db_Sum,db_Bln,AK$6,db_Kode,$A97) -> 0 | AL97: =+SUMIFS(db_Sum,db_Bln,AL$6,db_Kode,$A97) -> 0 | AM97: =+SUMIFS(db_Sum,db_Bln,AM$6,db_Kode,$A97) -> 0 | AN97: =+SUMIFS(db_Sum,db_Bln,AN$6,db_Kode,$A97) -> 0 | ... AR97: =+SUMIFS(db_Sum,db_Bln,AR$6,db_Kode,$A97) -> 0 | AS97: =+SUM(AG97:AR97) -> 0 | AT97: =+SUMIFS(db_Sum,db_Bln,AT$6,db_Kode,$A97) -> 0 | AU97: =+SUMIFS(db_Sum,db_Bln,AU$6,db_Kode,$A97) -> 0 | AV97: =+SUMIFS(db_Sum,db_Bln,AV$6,db_Kode,$A97) -> 0 | AW97: =+SUMIFS(db_Sum,db_Bln,AW$6,db_Kode,$A97) -> 0 | AX97: =+SUMIFS(db_Sum,db_Bln,AX$6,db_Kode,$A97) -> 0 | AY97: =+SUMIFS(db_Sum,db_Bln,AY$6,db_Kode,$A97) -> 0 | AZ97: =+SUMIFS(db_Sum,db_Bln,AZ$6,db_Kode,$A97) -> 0 | BA97: =+SUMIFS(db_Sum,db_Bln,BA$6,db_Kode,$A97) -> 0 | ... BE97: =+SUMIFS(db_Sum,db_Bln,BE$6,db_Kode,$A97) -> 0 | BF97: =+SUM(AT97:BE97) -> 1.7018256e+08 | BG97: =+SUMIFS(db_Sum,db_Bln,BG$6,db_Kode,$A97) -> 0 | BH97: =+SUMIFS(db_Sum,db_Bln,BH$6,db_Kode,$A97) -> 0 | BI97: =+SUMIFS(db_Sum,db_Bln,BI$6,db_Kode,$A97) -> 0 | BJ97: =+SUMIFS(db_Sum,db_Bln,BJ$6,db_Kode,$A97) -> 0 | BK97: =+SUMIFS(db_Sum,db_Bln,BK$6,db_Kode,$A97) -> 0 | BS97: =+SUM(BG97:BR97) -> 0 | BT97: =+SUM(O97,Q97,R97,S97,AF97,AS97,BF97+BS97) -> 1.7018256e+08 | BU97: =+IF(K97-BT97=0,"OK","ERROR") -> OK
A98: 35 | B98: =B95+1 -> 5 | C98: Automatic Dearator Dll | D98: PT. Budijaya Cemerlang | E98: 588200100 | F98: 08/SPK/KS-PKS/MILL-HO/IV/2022 | G98: PT. Budijaya Cemerlang | H98: =E98-K98 -> 58820010 | I98: 588200100 | J98: 588200100 | K98: =+O98+Q98+R98+S98+AF98+AS98+BF98+BS98-K99 -> 529380090 | L98: 0 | M98: =J98-K98 -> 58820010 | N98: -Pemakaian Persediaan | O98: =+SUMIFS(db_Sum,db_Bln,O$6,db_Kode,$A98) -> 0 | P98: =+IF(H98=0,E98-K98,0) -> 0 | Q98: =+SUMIFS(db_Sum,db_Bln,Q$6,db_Kode,$A98) -> 0 | R98: =+SUMIFS(db_Sum,db_Bln,R$6,db_Kode,$A98) -> 0 | S98: =+SUMIFS(db_Sum,db_Bln,S$6,db_Kode,$A98) -> 0 | T98: =+SUMIFS(db_Sum,db_Bln,T$6,db_Kode,$A98) -> 0 | U98: =+SUMIFS(db_Sum,db_Bln,U$6,db_Kode,$A98) -> 0 | V98: =+SUMIFS(db_Sum,db_Bln,V$6,db_Kode,$A98) -> 0 | W98: =+SUMIFS(db_Sum,db_Bln,W$6,db_Kode,$A98) -> 0 | X98: =+SUMIFS(db_Sum,db_Bln,X$6,db_Kode,$A98) -> 0 | ... AE98: =+SUMIFS(db_Sum,db_Bln,AE$6,db_Kode,$A98) -> 0 | AF98: =+SUM(T98:AE98) -> 0 | AG98: =+SUMIFS(db_Sum,db_Bln,AG$6,db_Kode,$A98) -> 0 | AH98: =+SUMIFS(db_Sum,db_Bln,AH$6,db_Kode,$A98) -> 0 | AI98: =+SUMIFS(db_Sum,db_Bln,AI$6,db_Kode,$A98) -> 0 | AJ98: =+SUMIFS(db_Sum,db_Bln,AJ$6,db_Kode,$A98) -> 0 | AK98: =+SUMIFS(db_Sum,db_Bln,AK$6,db_Kode,$A98) -> 0 | AL98: =+SUMIFS(db_Sum,db_Bln,AL$6,db_Kode,$A98) -> 0 | AM98: =+SUMIFS(db_Sum,db_Bln,AM$6,db_Kode,$A98) -> 0 | AN98: =+SUMIFS(db_Sum,db_Bln,AN$6,db_Kode,$A98) -> 0 | ... AR98: =+SUMIFS(db_Sum,db_Bln,AR$6,db_Kode,$A98) -> 0 | AS98: =+SUM(AG98:AR98) -> 0 | AT98: =+SUMIFS(db_Sum,db_Bln,AT$6,db_Kode,$A98) -> 0 | AU98: =+SUMIFS(db_Sum,db_Bln,AU$6,db_Kode,$A98) -> 0 | AV98: =+SUMIFS(db_Sum,db_Bln,AV$6,db_Kode,$A98) -> 0 | AW98: =+SUMIFS(db_Sum,db_Bln,AW$6,db_Kode,$A98) -> 0 | AX98: =+SUMIFS(db_Sum,db_Bln,AX$6,db_Kode,$A98) -> 0 | AY98: =+SUMIFS(db_Sum,db_Bln,AY$6,db_Kode,$A98) -> 0 | AZ98: =+SUMIFS(db_Sum,db_Bln,AZ$6,db_Kode,$A98) -> 0 | BA98: =+SUMIFS(db_Sum,db_Bln,BA$6,db_Kode,$A98) -> 0 | ... BE98: =+SUMIFS(db_Sum,db_Bln,BE$6,db_Kode,$A98) -> 0 | BF98: =+SUM(AT98:BE98) -> 0 | BG98: =+SUMIFS(db_Sum,db_Bln,BG$6,db_Kode,$A98) -> 0 | BH98: =+SUMIFS(db_Sum,db_Bln,BH$6,db_Kode,$A98) -> 0 | BI98: =+SUMIFS(db_Sum,db_Bln,BI$6,db_Kode,$A98) -> 0 | BJ98: =+SUMIFS(db_Sum,db_Bln,BJ$6,db_Kode,$A98) -> 0 | BK98: =+SUMIFS(db_Sum,db_Bln,BK$6,db_Kode,$A98) -> 588200100 | BS98: =+SUM(BG98:BR98) -> 588200100 | BT98: =+SUM(O98,Q98,R98,S98,AF98,AS98,BF98+BS98) -> 588200100 | BU98: =+IF(K98-BT98=0,"OK","ERROR") -> ERROR
C99: -Retensi | K99: 58820010 | N99: -Sisa Retensi 10%
A100: 36 | B100: =B98+1 -> 6 | C100: Vertical Sterilizer | D100: PT. Arina Karya Sentosa | E100: 8769000000 | F100: 07/SPK/KS-PKS/MILL-HO/V/2022 | G100: PT. Arina Karya Sentosa | H100: =E100-K100 -> 876900000 | I100: 8769000000 | J100: 8769000000 | K100: 7892100000 | L100: 0 | M100: =J100-K100 -> 876900000 | N100: -Kategori DP, masuk account DP | O100: =+SUMIFS(db_Sum,db_Bln,O$6,db_Kode,$A100) -> 0 | P100: =+IF(H100=0,E100-K100,0) -> 0 | Q100: =+SUMIFS(db_Sum,db_Bln,Q$6,db_Kode,$A100) -> 0 | R100: =+SUMIFS(db_Sum,db_Bln,R$6,db_Kode,$A100) -> 0 | S100: =+SUMIFS(db_Sum,db_Bln,S$6,db_Kode,$A100) -> 0 | T100: =+SUMIFS(db_Sum,db_Bln,T$6,db_Kode,$A100) -> 0 | U100: =+SUMIFS(db_Sum,db_Bln,U$6,db_Kode,$A100) -> 0 | V100: =+SUMIFS(db_Sum,db_Bln,V$6,db_Kode,$A100) -> 0 | W100: =+SUMIFS(db_Sum,db_Bln,W$6,db_Kode,$A100) -> 0 | X100: =+SUMIFS(db_Sum,db_Bln,X$6,db_Kode,$A100) -> 0 | ... AE100: =+SUMIFS(db_Sum,db_Bln,AE$6,db_Kode,$A100) -> 0 | AF100: =+SUM(T100:AE100) -> 0 | AG100: =+SUMIFS(db_Sum,db_Bln,AG$6,db_Kode,$A100) -> 0 | AH100: =+SUMIFS(db_Sum,db_Bln,AH$6,db_Kode,$A100) -> 0 | AI100: =+SUMIFS(db_Sum,db_Bln,AI$6,db_Kode,$A100) -> 0 | AJ100: =+SUMIFS(db_Sum,db_Bln,AJ$6,db_Kode,$A100) -> 0 | AK100: =+SUMIFS(db_Sum,db_Bln,AK$6,db_Kode,$A100) -> 0 | AL100: =+SUMIFS(db_Sum,db_Bln,AL$6,db_Kode,$A100) -> 0 | AM100: =+SUMIFS(db_Sum,db_Bln,AM$6,db_Kode,$A100) -> 0 | AN100: =+SUMIFS(db_Sum,db_Bln,AN$6,db_Kode,$A100) -> 0 | ... AR100: =+SUMIFS(db_Sum,db_Bln,AR$6,db_Kode,$A100) -> 0 | AS100: =+SUM(AG100:AR100) -> 0 | AT100: =+SUMIFS(db_Sum,db_Bln,AT$6,db_Kode,$A100) -> 0 | AU100: =+SUMIFS(db_Sum,db_Bln,AU$6,db_Kode,$A100) -> 0 | AV100: =+SUMIFS(db_Sum,db_Bln,AV$6,db_Kode,$A100) -> 0 | AW100: =+SUMIFS(db_Sum,db_Bln,AW$6,db_Kode,$A100) -> 0 | AX100: =+SUMIFS(db_Sum,db_Bln,AX$6,db_Kode,$A100) -> 0 | AY100: =+SUMIFS(db_Sum,db_Bln,AY$6,db_Kode,$A100) -> 0 | AZ100: =+SUMIFS(db_Sum,db_Bln,AZ$6,db_Kode,$A100) -> 0 | BA100: =+SUMIFS(db_Sum,db_Bln,BA$6,db_Kode,$A100) -> 0 | ... BE100: =+SUMIFS(db_Sum,db_Bln,BE$6,db_Kode,$A100) -> 0 | BF100: =+SUM(AT100:BE100) -> 0 | BG100: =+SUMIFS(db_Sum,db_Bln,BG$6,db_Kode,$A100) -> 0 | BH100: =+SUMIFS(db_Sum,db_Bln,BH$6,db_Kode,$A100) -> 0 | BI100: =+SUMIFS(db_Sum,db_Bln,BI$6,db_Kode,$A100) -> 0 | BJ100: =+SUMIFS(db_Sum,db_Bln,BJ$6,db_Kode,$A100) -> 0 | BK100: =+SUMIFS(db_Sum,db_Bln,BK$6,db_Kode,$A100) -> 0 | BS100: =+SUM(BG100:BR100) -> 0 | BT100: =+SUM(O100,Q100,R100,S100,AF100,AS100,BF100+BS100) -> 0 | BU100: =+IF(K100-BT100=0,"OK","ERROR") -> ERROR
A101: 37 | B101: =B100+1 -> 7 | C101: Gearbox dan Gearmotor | D101: PT. Serumpun Indah Lestari | E101: 2469750000 | F101: 06/SPK/KS-PKS/MILL-HO/IV/2022 | G101: PT. Serumpun Indah Lestari | H101: =E101-K101 -> 4.9395e+08 | I101: 2469750000 | J101: 2469750000 | K101: =+O101+Q101+R101+S101+AF101+AS101+BF101+BS101-K102-1 -> 1.9758e+09 | L101: 0 | M101: =J101-K101 -> 4.9395e+08 | N101: -Pemakaian Persediaan | O101: =+SUMIFS(db_Sum,db_Bln,O$6,db_Kode,$A101) -> 0 | P101: =+IF(H101=0,E101-K101,0) -> 0 | Q101: =+SUMIFS(db_Sum,db_Bln,Q$6,db_Kode,$A101) -> 0 | R101: =+SUMIFS(db_Sum,db_Bln,R$6,db_Kode,$A101) -> 0 | S101: =+SUMIFS(db_Sum,db_Bln,S$6,db_Kode,$A101) -> 0 | T101: =+SUMIFS(db_Sum,db_Bln,T$6,db_Kode,$A101) -> 0 | U101: =+SUMIFS(db_Sum,db_Bln,U$6,db_Kode,$A101) -> 0 | V101: =+SUMIFS(db_Sum,db_Bln,V$6,db_Kode,$A101) -> 0 | W101: =+SUMIFS(db_Sum,db_Bln,W$6,db_Kode,$A101) -> 0 | X101: =+SUMIFS(db_Sum,db_Bln,X$6,db_Kode,$A101) -> 0 | ... AE101: =+SUMIFS(db_Sum,db_Bln,AE$6,db_Kode,$A101) -> 0 | AF101: =+SUM(T101:AE101) -> 0 | AG101: =+SUMIFS(db_Sum,db_Bln,AG$6,db_Kode,$A101) -> 0 | AH101: =+SUMIFS(db_Sum,db_Bln,AH$6,db_Kode,$A101) -> 0 | AI101: =+SUMIFS(db_Sum,db_Bln,AI$6,db_Kode,$A101) -> 0 | AJ101: =+SUMIFS(db_Sum,db_Bln,AJ$6,db_Kode,$A101) -> 0 | AK101: =+SUMIFS(db_Sum,db_Bln,AK$6,db_Kode,$A101) -> 0 | AL101: =+SUMIFS(db_Sum,db_Bln,AL$6,db_Kode,$A101) -> 0 | AM101: =+SUMIFS(db_Sum,db_Bln,AM$6,db_Kode,$A101) -> 0 | AN101: =+SUMIFS(db_Sum,db_Bln,AN$6,db_Kode,$A101) -> 0 | ... AR101: =+SUMIFS(db_Sum,db_Bln,AR$6,db_Kode,$A101) -> 0 | AS101: =+SUM(AG101:AR101) -> 0 | AT101: =+SUMIFS(db_Sum,db_Bln,AT$6,db_Kode,$A101) -> 0 | AU101: =+SUMIFS(db_Sum,db_Bln,AU$6,db_Kode,$A101) -> 0 | AV101: =+SUMIFS(db_Sum,db_Bln,AV$6,db_Kode,$A101) -> 0 | AW101: =+SUMIFS(db_Sum,db_Bln,AW$6,db_Kode,$A101) -> 0 | AX101: =+SUMIFS(db_Sum,db_Bln,AX$6,db_Kode,$A101) -> 0 | AY101: =+SUMIFS(db_Sum,db_Bln,AY$6,db_Kode,$A101) -> 0 | AZ101: =+SUMIFS(db_Sum,db_Bln,AZ$6,db_Kode,$A101) -> 0 | BA101: =+SUMIFS(db_Sum,db_Bln,BA$6,db_Kode,$A101) -> 0 | ... BE101: =+SUMIFS(db_Sum,db_Bln,BE$6,db_Kode,$A101) -> 9.1244909e+08 | BF101: =+SUM(AT101:BE101) -> 2.46975e+09 | BG101: =+SUMIFS(db_Sum,db_Bln,BG$6,db_Kode,$A101) -> 0 | BH101: =+SUMIFS(db_Sum,db_Bln,BH$6,db_Kode,$A101) -> 0 | BI101: =+SUMIFS(db_Sum,db_Bln,BI$6,db_Kode,$A101) -> 0 | BJ101: =+SUMIFS(db_Sum,db_Bln,BJ$6,db_Kode,$A101) -> 0 | BK101: =+SUMIFS(db_Sum,db_Bln,BK$6,db_Kode,$A101) -> 0 | BS101: =+SUM(BG101:BR101) -> 0 | BT101: =+SUM(O101,Q101,R101,S101,AF101,AS101,BF101+BS101) -> 2.46975e+09 | BU101: =+IF(K101-BT101=0,"OK","ERROR") -> ERROR
C102: -Commisioning dan Retensi | K102: 493950000 | N102: -Comm. 15% dan Retensi 5%
A103: 38 | B103: =B101+1 -> 8 | C103: Mesin Press dan Digester 5000L | D103: GS Agro Enineering SDN.BHD | E103: 4351200000 | F103: SPK JAKARTA | G103: GS Agro Enineering SDN.BHD | H103: =E103-K103 -> 2.0792651e+08 | I103: 4.1432735e+09 | J103: 4.1432735e+09 | K103: 4.1432735e+09 | L103: 0 | M103: =J103-K103 -> 0 | N103: -Pemakaian Persediaan | O103: =+SUMIFS(db_Sum,db_Bln,O$6,db_Kode,$A103) -> 0 | P103: =+IF(H103=0,E103-K103,0) -> 0 | Q103: =+SUMIFS(db_Sum,db_Bln,Q$6,db_Kode,$A103) -> 0 | R103: =+SUMIFS(db_Sum,db_Bln,R$6,db_Kode,$A103) -> 0 | S103: =+SUMIFS(db_Sum,db_Bln,S$6,db_Kode,$A103) -> 0 | T103: =+SUMIFS(db_Sum,db_Bln,T$6,db_Kode,$A103) -> 0 | U103: =+SUMIFS(db_Sum,db_Bln,U$6,db_Kode,$A103) -> 0 | V103: =+SUMIFS(db_Sum,db_Bln,V$6,db_Kode,$A103) -> 0 | W103: =+SUMIFS(db_Sum,db_Bln,W$6,db_Kode,$A103) -> 0 | X103: =+SUMIFS(db_Sum,db_Bln,X$6,db_Kode,$A103) -> 0 | ... AE103: =+SUMIFS(db_Sum,db_Bln,AE$6,db_Kode,$A103) -> 0 | AF103: =+SUM(T103:AE103) -> 0 | AG103: =+SUMIFS(db_Sum,db_Bln,AG$6,db_Kode,$A103) -> 0 | AH103: =+SUMIFS(db_Sum,db_Bln,AH$6,db_Kode,$A103) -> 0 | AI103: =+SUMIFS(db_Sum,db_Bln,AI$6,db_Kode,$A103) -> 0 | AJ103: =+SUMIFS(db_Sum,db_Bln,AJ$6,db_Kode,$A103) -> 0 | AK103: =+SUMIFS(db_Sum,db_Bln,AK$6,db_Kode,$A103) -> 0 | AL103: =+SUMIFS(db_Sum,db_Bln,AL$6,db_Kode,$A103) -> 0 | AM103: =+SUMIFS(db_Sum,db_Bln,AM$6,db_Kode,$A103) -> 0 | AN103: =+SUMIFS(db_Sum,db_Bln,AN$6,db_Kode,$A103) -> 0 | ... AR103: =+SUMIFS(db_Sum,db_Bln,AR$6,db_Kode,$A103) -> 0 | AS103: =+SUM(AG103:AR103) -> 0 | AT103: =+SUMIFS(db_Sum,db_Bln,AT$6,db_Kode,$A103) -> 0 | AU103: =+SUMIFS(db_Sum,db_Bln,AU$6,db_Kode,$A103) -> 0 | AV103: =+SUMIFS(db_Sum,db_Bln,AV$6,db_Kode,$A103) -> 0 | AW103: =+SUMIFS(db_Sum,db_Bln,AW$6,db_Kode,$A103) -> 0 | AX103: =+SUMIFS(db_Sum,db_Bln,AX$6,db_Kode,$A103) -> 0 | AY103: =+SUMIFS(db_Sum,db_Bln,AY$6,db_Kode,$A103) -> 0 | AZ103: =+SUMIFS(db_Sum,db_Bln,AZ$6,db_Kode,$A103) -> 0 | BA103: =+SUMIFS(db_Sum,db_Bln,BA$6,db_Kode,$A103) -> 0 | ... BE103: =+SUMIFS(db_Sum,db_Bln,BE$6,db_Kode,$A103) -> 0 | BF103: =+SUM(AT103:BE103) -> 4144482420 | BG103: =+SUMIFS(db_Sum,db_Bln,BG$6,db_Kode,$A103) -> 0 | BH103: =+SUMIFS(db_Sum,db_Bln,BH$6,db_Kode,$A103) -> 0 | BI103: =+SUMIFS(db_Sum,db_Bln,BI$6,db_Kode,$A103) -> 0 | BJ103: =+SUMIFS(db_Sum,db_Bln,BJ$6,db_Kode,$A103) -> 0 | BK103: =+SUMIFS(db_Sum,db_Bln,BK$6,db_Kode,$A103) -> 0 | BS103: =+SUM(BG103:BR103) -> 0 | BT103: =+SUM(O103,Q103,R103,S103,AF103,AS103,BF103+BS103) -> 4144482420 | BU103: =+IF(K103-BT103=0,"OK","ERROR") -> ERROR
C104: -Biaya Material Penunjang Lainnya | E104: 0 | H104: =E104-K104 -> -1206000 | I104: 0 | J104: 1206000 | K104: 1206000 | L104: 0 | M104: 0 | P104: =+IF(H104=0,E104-K104,0) -> 0
...

Sheet Sheet1
A1: B6: Material Lainnya Tiang Pancang | D1: 84300934
B3: Pembelian Hydraulic Hose Enerpac Keperluan Pabrik PKS | D3: =db!H84 -> 5426700
B4: Via BKB PEMBUATAN ALAT PANCANG PKS SEI CABANG | D4: =db!H95+db!H96+db!H97 -> 33838654
B5: Pemakaian Persediaan | D5: =db!H94+db!H237+db!H410+db!H443+db!H444 -> 22594680
B6: Buruh angkut | D6: =db!H283 -> 200000
B7: BY.PENGUJIAN SAMPLE BETON DI POLITEKNIK NEGERI BANJARMASIN | D7: =db!H700 -> 300000
B8: KJPP MBPRU & Rekan By.Pelunasan atas Pekerjaan Studi KelayakanPembangunan Pabrik Kelapa Sawit | D8: 11100000
B9: Pembelian Lokal | D9: =SUM(D10:D32) -> 10840900
B10: Via. FIka Aditya Pratama | C10: By. Pembelian Carbon Brush | D10: 70000
B11: Via. FIka Aditya Pratama | C11: By. Pembelian Tali Tambang & Rafia | D11: 75000
B12: Via. Fika Aditya Pratama | C12: By. Pembelian WD-40 untuk Perbaikan Alat SLT Test | D12: 75000
B13: Via. Nur Wijaya | C13: By. Pembelian Tabung Gas 12 Kg untuk Las Alat SLT | D13: 275000
B14: Via. Fika Aditya Pratama | C14: By. Pembelian Bor Drill u/ Perbaikan SLT Test | D14: 944900
B15: Via. Fika Aditya Pratama | C15: By. Pembelian Konsumsi Lembur Petugas Perbaikan SLT Test | D15: 559000
B16: Via.Fika Aditya Pratama | C16: By. Konsumsi u/ Petugas Perbaikan SLT Test | D16: 152000
B17: Via. Fika Aditya Pratama | C17: By. Pembelian Mata Potong U/ Perbaikan SLT Test | D17: 102000
B18: Via. Fika Aditya Pratama | C18: By. Pembelian Matabor u/ Perbaikan SLT Test | D18: 600000
B19: Via. Fika Aditya Pratama | C19: By. Pembelian Baut dan Ring u/ Perbaikan SLT Test | D19: 436000
B20: Via. Fika Aditya Pratama | C20: By. Pembelian Sarung Tangan U/ Perbaikan SLT | D20: 25000
B21: Via. Fika Aditya Pratama | C21: By. Pembelian Tabung LPG 12kg U/ Perbaikan SLT | D21: 275000
... B32: Via. Fika Aditya Pratama | C32: By. Pembelian Plang Safety, Plang Evakuasi dan Banner | D32: 2920000
A35: B6: Material Lainnya Main Building | D35: 3.1019323e+09
B37: Prakarsa Muda Indonesia, PT atas Shipment Probolinggo ke Sungai Cab. Kumai | D37: =db!H564+db!H567+db!H618 -> 1237650000
B38: Pembelian Lokal | D38: =SUM(D39:D52) -> 4509500
B39: By. Pembelian Keperluan Pembuatan Papan Nama Stasiun | D39: 223000
B40: - By. Pembayaran Konsumsi Bongkaran HMD 01 | D40: 1164000
B41: By. Pembelian Konsumsi Bongkaran HMD 01 | D41: 515000
B42: By. Pembelian Material u/ Plang Nama Stasiun | D42: 375000
B43: By. Pembelian Baut & Ring Plat U/ Mesin Pemanas | D43: 15500
B44: By. Pembelian Sepatu Boots U/ GM | D44: 196000
B45: By. Pembelian Refil Gas 12 KG U/ Workshop | D45: 560000
B46: By. Pembelian Spatula Lab U/ Laboratorium | D46: 96000
B47: By. Pembelian Nippel 1/2" U/ Instalasi dossing pump WTP | D47: 200000
B48: By. Pembelian Selang benang 1/2" U/ Instalasi dossing pump WTP | D48: 450000
B49: By. Pembelian klem stainless 3/4" U/ Instalasi dossing pump WTP | D49: 60000
B50: By. Pembelian Gas LPG 12 Kg U/ Pengelasan di WTP | D50: 275000
... B52: By. Pembelian Baut U/ Klarifikasi | D52: 60000
B53: Pembayaran Jasa Pengikatan di Pelindo | D53: =db!H676+db!H679 -> 2005000
B54: Pemakaian Persediaan | D54: =SUM(D55:D61) -> 1.844673e+09
B55: ADK BANGUNAN KERJA - PEMBANGUNAN PABRIK KELAPA SAWIT | D55: =3696300+db!H1184-db!H825-db!H827+db!H962+db!H992 -> 15162869
B56: ADK BANGUNAN KERJA - PEMBANGUNAN PABRIK KELAPA SAWIT KONTRAKTOR | D56: 91741.5
B57: ADK BANGUNAN KERJA - PEMBANGUNAN PABRIK KELAPA SAWIT MATERIAL | D57: =1361263663.81+db!H667+db!H818+db!H905+db!H976 -> 1.3680735e+09
B58: ADK BANGUNAN KERJA - PEMBANGUNAN PABRIK KELAPA SAWIT LAIN - LAIN | D58: =49905527.48+db!H975+db!H977+db!H978+db!H1037+db!H1347+db!H1038 -> 87050779
B59: ADK MESIN PENUNJANG - PEMASANGAN MESIN STATION BOILER | D59: =12336662-db!H869 -> 19826662
B60: ADK MESIN PENUNJANG - PEMASANGAN MESIN WATER TREATMENT PLANT MATERIAL | D60: 74986771
B61: ADK PERALATAN PENUNJANG - PERALATAN LABORATORIUM PKS | D61: 279480713
B62: Angkutan | D62: =db!H1445+db!H1446+db!H1542 -> 12784000
B63: Alat berat | D63: =db!H715 -> 310800
A65: 24: Material Lainnya MECHANICAL & ELECTRICAL | D65: =SUM(D67:D83) -> 4.7974701e+09 | E65: 2469750000 | F65: =D65-E65 -> 2.3277201e+09
B67: ADK BANGUNAN KERJA - PEMBANGUNAN PABRIK KELAPA SAWIT | D67: 73418221
B68: ADK BANGUNAN KERJA - PEMBANGUNAN OIL STORAGE TANK CAP 3000 TON MATERIAL | D68: 17304345
B69: ADK MESIN PENUNJANG - GENERAL WORKS & ENGINEERING ALL STATION | D69: 1474746
B70: ADK MESIN PENUNJANG - PEMASANGAN MESIN STATION LOADING RAMP | D70: 9.7565315e+08
B71: ADK MESIN PENUNJANG - PEMASANGAN MESIN STATION STERILIZATION | D71: 6280186.8
B72: ADK MESIN PENUNJANG - PEMASANGAN MESIN STATION THRESING | D72: 6.0808712e+08
B73: ADK MESIN PENUNJANG - PEMASANGAN MESIN STATION NUT & KERNEL | D73: =1313670761.75+363750-db!H1241 -> 1.261587e+09
B74: ADK MESIN PENUNJANG - PEMASANGAN MESIN STATION CLARIFICATION | D74: 3.5014845e+08
B75: ADK MESIN PENUNJANG - PEMASANGAN MESIN STATION POWER HOUSE | D75: =94986196.5+db!H1636 -> 1.5083825e+08
B76: ADK MESIN PENUNJANG - PEMASANGAN MESIN STATION BOILER | D76: 353398434
B77: ADK MESIN PENUNJANG - PEMASANGAN MESIN WATER TREATMENT PLANT | D77: 63691075
B78: ADK MESIN PENUNJANG - PEMASANGAN MESIN PENGOLAHAN LIMBAH | D78: 338242
B79: ADK MESIN PENUNJANG - PEMASANGAN MESIN STATION DIGESTER & PRESS | D79: =4485217669.86+3454320-db!H933 -> 3.4539557e+08
B80: ADK MESIN PENUNJANG - PEMASANGAN MESIN STATION DESPATCH OIL | D80: 43630651
B81: ADK PRASARANA UMUM - PEMASANGAN JARINGAN LISTRIK PKS | D81: 7874706
B82: ADK PERALATAN PENUNJANG - PEMBUATAN MESIN ROOL PKS MATERIAL | D82: 514484982
B83: ADK KONSTRUKSI LAINNYA - PANCANG PIGING 28 UNIT PKS KONTRAKTOR | D83: 23865000

Sheet db
H1: 1.1242631e+11
G2: =+H2-H1 -> 2.0585328e+11 | H2: =+SUBTOTAL(9,H$4:H$1048576) -> 3.1827959e+11 | I2: -3.2591772e+10
B3: TGL | C3: KODE | D3: COA | E3: SUB | F3: REMARK | G3: FREMARK | H3: AMOUNT | I3: BLN | J3: KODE
B4: 43465 | C4: KSA.M09005-1218 | D4: 116204001001 | E4: 0002 | F4: RAcct @ ADK - BANGUNAN - PABRIK KELAPA S | G4: Cost fr 111904005323 EXCAVATOR HITACHI (JBP-03) | H4: 74137012 | I4: 2018 | J4: 42
B5: 43496 | C5: KSA.M03076-0119 | D5: 116204001001 | E5: 0002 | F5: ALOKASI BY.LCT UD MAULIDA SPK 021 TGL.11/10/18 | G5: KOBELCO PC-200 (PT. JBP) | H5: 49500000 | I5: 2019 | J5: 42
B6: 43496 | C6: KSA.M03077-0119 | D6: 116204001001 | E6: 0002 | F6: ALOKASI BY.LCT UD MAULIDA SPK 090 TGL.27/11/18 | G6: DUMP TRUCK (PT.JBP) | H6: 16500000 | I6: 2019 | J6: 42
B7: 43496 | C7: KSA.M03077-0119 | D7: 116204001001 | E7: 0002 | F7: ALOKASI BY.LCT UD MAULIDA SPK 090 TGL.27/11/18 | G7: DUMP TRUCK (PT.JBP) | H7: 16500000 | I7: 2019 | J7: 42
B8: 43496 | C8: KSA.M03076-0119 | D8: 116204001001 | E8: 0002 | F8: ALOKASI BY.LCT UD MAULIDA SPK 021 TGL.11/10/18 | G8: TRUCK COLT DIESEL (PT.JBP) | H8: 16500000 | I8: 2019 | J8: 42
B9: 43496 | C9: KSA.M09005-0119 | D9: 116204001001 | E9: 0002 | F9: RAcct @ ADK - BANGUNAN - PABRIK KELAPA S | G9: Cost fr 111904005323 EXCAVATOR HITACHI (JBP-03) | H9: 144226500 | I9: 2019 | J9: 42
B10: 43524 | C10: KSA.M09005-0219 | D10: 116204001001 | E10: 0002 | F10: RAcct @ ADK - BANGUNAN - PABRIK KELAPA S | G10: Cost fr 111904005323 EXCAVATOR HITACHI (JBP-03) | H10: 542591454 | I10: 2019 | J10: 42
B11: 43555 | C11: KSA.M09005-0319 | D11: 116204001001 | E11: 0002 | F11: RAcct @ ADK - BANGUNAN - PABRIK KELAPA S | G11: Cost fr 111904005323 EXCAVATOR HITACHI (JBP-03) | H11: 121464200 | I11: 2019 | J11: 42
B12: 43555 | C12: KSA.M05008-0319 | D12: 116204001001 | E12: 0002 | F12: GAJI PHL AFD LAND CLEARING MASA II BULAN MARET 2019 | H12: 118620 | I12: 2019 | J12: 329
B13: 43585 | C13: KSA.M04080-0419 | D13: 116204001001 | E13: 0002 | F13: KOREKSI MEMO M04078-0319 TGL. 31-03-19 | G13: KOREKSI PRESTASI KERJA | H13: -10725000 | I13: 2019 | J13: 42
B14: 43585 | C14: KSA.M09005-0419 | D14: 116204001001 | E14: 0002 | F14: RAcct @ ADK - BANGUNAN - PABRIK KELAPA S | G14: Cost fr 111904005323 EXCAVATOR HITACHI (JBP-03) | H14: 3.8550571e+08 | I14: 2019 | J14: 42
B15: 43585 | C15: KSA.M05003-0419 | D15: 116204001001 | E15: 0002 | F15: GAJI PL AFD LAND CLEARING MASA I BULAN APRIL 2019 | H15: 237240 | I15: 2019 | J15: 329
B16: 43585 | C16: KSA.M05003-0419 | D16: 116204001001 | E16: 0002 | F16: GAJI PL AFD LAND CLEARING MASA I BULAN APRIL 2019 | H16: 237240 | I16: 2019 | J16: 329
B17: 43585 | C17: KSA.M05003-0419 | D17: 116204001001 | E17: 0002 | F17: GAJI PL AFD LAND CLEARING MASA I BULAN APRIL 2019 | H17: 106758 | I17: 2019 | J17: 329
B18: 43587 | C18: KSA.B021007-0519 | D18: 116204001001 | E18: 0002 | F18: PT.Geo Inti Perkasa | G18: By.Pelunasan atas Pekerjaan Survey Penyelidikan TanahProyek Pembangunan Pabrik Kelapa Sawit di KumaiInv.018 SPK.008 BAST.017 | H18: 192500000 | I18: 2019 | J18: A11
B19: 43587 | C19: KSA.B021011-0519 | D19: 116204001001 | E19: 0002 | F19: PT.Geo Inti Perkasa | G19: By.DP 50% atas Pekerjaan Survey Penyelidikan TanahPreliminary Survey 2, Proyek Pembangunan Pabrik Kelapa Sawit di KumaiInv.022 SPK.004 | H19: 27500000 | I19: 2019 | J19: A11
B20: 43587 | C20: KSA.B021013-0519 | D20: 116204001001 | E20: 0002 | F20: PT.Geo Inti Perkasa | G20: By.DP 50% atas Pekerjaan Survey Penyelidikan TanahRelokasi ke Lokasi 2, Proyek Pembangunan Pabrik Kelapa Sawit di Kumai Inv.023 SPK.005 | H20: 165000000 | I20: 2019 | J20: A11
B21: 43616 | C21: KSA.M09005-0519 | D21: 116204001001 | E21: 0002 | F21: RAcct @ ADK - BANGUNAN - PABRIK KELAPA S | G21: Cost fr 111904005305 EXCAVATOR KOBELCO SK200-10/SK200XDL-10 (33-18) | H21: 6723816 | I21: 2019 | J21: 327
B22: 43616 | C22: KSA.M09005-0519 | D22: 116204001001 | E22: 0002 | F22: RAcct @ ADK - BANGUNAN - PABRIK KELAPA S | G22: Cost fr 111904005318 EXCAVATOR KOBELCO SK200-10/SK200XDL-10 (33-24) | H22: 6723816 | I22: 2019 | J22: 327
B23: 43616 | C23: KSA.M05003-0519 | D23: 116204001001 | E23: 0002 | F23: GAJI PHL AFD LAND CLEARING MASA I BULAN MEI 2019 | H23: 118620 | I23: 2019 | J23: 329
B24: 43616 | C24: KSA.M05008-0519 | D24: 116204001001 | E24: 0002 | F24: GAJI PHL AFD LAND CLEARING MASA II BULAN MEI 2019 | H24: 237240 | I24: 2019 | J24: 329
B25: 43646 | C25: KSA.M09005-0619 | D25: 116204001001 | E25: 0002 | F25: RAcct @ ADK - BANGUNAN - PABRIK KELAPA S | G25: Cost fr 111904005305 EXCAVATOR KOBELCO SK200-10/SK200XDL-10 (33-18) | H25: 22289425 | I25: 2019 | J25: 327
B26: 43646 | C26: KSA.M09005-0619 | D26: 116204001001 | E26: 0002 | F26: RAcct @ ADK - BANGUNAN - PABRIK KELAPA S | G26: Cost fr 111904005306 EXCAVATOR KOBELCO SK200-10/SK200XDL-10 (33-19) | H26: 1.2471985e+08 | I26: 2019 | J26: 327
B27: 43646 | C27: KSA.M09005-0619 | D27: 116204001001 | E27: 0002 | F27: RAcct @ ADK - BANGUNAN - PABRIK KELAPA S | G27: Cost fr 111904005318 EXCAVATOR KOBELCO SK200-10/SK200XDL-10 (33-24) | H27: 92223142 | I27: 2019 | J27: 327
B28: 43646 | C28: KSA.M09005-0619 | D28: 116204001001 | E28: 0002 | F28: RAcct @ ADK - BANGUNAN - PABRIK KELAPA S | G28: Cost fr 111904005325 EXCAVATOR KOBELCO SK200-10 (33-25) | H28: 82252497 | I28: 2019 | J28: 327
B29: 43646 | C29: KSA.M09005-0619 | D29: 116204001001 | E29: 0002 | F29: RAcct @ ADK - BANGUNAN - PABRIK KELAPA S | G29: Cost fr 111904005323 EXCAVATOR HITACHI (JBP-03) | H29: 5423000 | I29: 2019 | J29: 42
B30: 43646 | C30: KSA.M05003-0619 | D30: 116204001001 | E30: 0002 | F30: GAJI PHL AFD LAND CLEARING BULAN JUNI 2019 | H30: 118620 | I30: 2019 | J30: 329
B31: 43646 | C31: KSA.M05003-0619 | D31: 116204001001 | E31: 0002 | F31: GAJI PHL AFD LAND CLEARING BULAN JUNI 2019 | H31: 474480 | I31: 2019 | J31: 329
B32: 43646 | C32: KSA.M05008-0619 | D32: 116204001001 | E32: 0002 | F32: GAJI PHL AFD LAND CLEARING MASA II BULAN JUNI 2019 | H32: 474480 | I32: 2019 | J32: 329
B33: 43650 | C33: KSA.M05003-0719 | D33: 116204001001 | E33: 0002 | F33: GAJI PHL LC MASA I BULAN JULI 2019 | H33: 711720 | I33: 2019 | J33: 329
B34: 43650 | C34: KSA.M05003-0719 | D34: 116204001001 | E34: 0002 | F34: GAJI PHL LC MASA I BULAN JULI 2019 | H34: 474480 | I34: 2019 | J34: 329
B35: 43677 | C35: KSA.M09005-0719 | D35: 116204001001 | E35: 0002 | F35: RAcct @ ADK - BANGUNAN - PABRIK KELAPA S | G35: Cost fr 111904005323 EXCAVATOR HITACHI (JBP-03) | H35: 54994500 | I35: 2019 | J35: 42
B36: 43677 | C36: KSA.M09005-0719 | D36: 116204001001 | E36: 0002 | F36: RAcct @ ADK - BANGUNAN - PABRIK KELAPA S | G36: Cost fr 111904005319 EXCAVATOR HITACHI (JBP-01) | H36: 42523502 | I36: 2019 | J36: 42
B37: 43677 | C37: KSA.M09005-0719 | D37: 116204001001 | E37: 0002 | F37: RAcct @ ADK - BANGUNAN - PABRIK KELAPA S | G37: Cost fr 111904005320 EXCAVATOR HITACHI (JBP-02) | H37: 32636863 | I37: 2019 | J37: 42
B38: 43708 | C38: KSA.M09005-0819 | D38: 116204001001 | E38: 0002 | F38: RAcct @ ADK - BANGUNAN - PABRIK KELAPA S | G38: Cost fr 111904005319 EXCAVATOR HITACHI (JBP-01) | H38: 121440000 | I38: 2019 | J38: 42
B39: 43708 | C39: KSA.M09005-0819 | D39: 116204001001 | E39: 0002 | F39: RAcct @ ADK - BANGUNAN - PABRIK KELAPA S | G39: Cost fr 111904005320 EXCAVATOR HITACHI (JBP-02) | H39: 128920000 | I39: 2019 | J39: 42
B40: 43708 | C40: KSA.M09005-0819 | D40: 116204001001 | E40: 0002 | F40: RAcct @ ADK - BANGUNAN - PABRIK KELAPA S | G40: Cost fr 111904005323 EXCAVATOR HITACHI (JBP-03) | H40: 145640000 | I40: 2019 | J40: 42
B41: 43708 | C41: KSA.M04084-0819 | D41: 116204001001 | E41: 0002 | F41: KOREKSI CATAT KURANG MEMO M04079-0719 | G41: GALIAN WADUK | H41: 22000 | I41: 2019 | J41: 42
B42: 43708 | C42: KSA.M05183-0819 | D42: 116204001001 | E42: 0002 | F42: BY. MAKAN TAMU DINAS | G42: MENGURUS HGB PABRIK, DERMAGA DAN REDIS KEBUN PLASMA KUMAI TGL 16 S/D 31 AGUSTUS 2019 | H42: 673000 | I42: 2019 | J42: A8
B43: 43726 | C43: KSA.B021039-0919 | D43: 116204001001 | E43: 0002 | F43: Via. Joko Purwito | G43: By.Pengurusan HGB Pabrik, Dermaga dan Redis Kebun Plasma | H43: 25000000 | I43: 2019 | J43: A8
B44: 43726 | C44: KSA.B021040-0919 | D44: 116204001001 | E44: 0002 | F44: Via. Joko Purwito | G44: Biaya pelayanan pengukuran dan pemetaan bidang tanah Inv.9240/2019 tgl 13 agustus 2019 Inv.9239/2019 tgl 13 agustus 2019 Inv.9242/2019 tgl 13 agustus 2019 | H44: 12300000 | I44: 2019 | J44: A8
B45: 43742 | C45: KSA.B021019-1019 | D45: 116204001001 | E45: 0002 | F45: Via Joko Purwito | G45: Biaya pengurusan sertifikasi HGB dermaga dan pabrik PT. Kumai Sentosa | H45: 25000000 | I45: 2019 | J45: A8
B46: 43753 | C46: KSA.K021038-1019 | D46: 116204001001 | E46: 0002 | F46: Via. Joko Purwito | G46: By.Permohonan SK Pemberian Hak Guna Bangunan Badan Hukum No.Invoice 10787/2019, 10789/2019 & 10788/2019 Tgl 07 Oktober 2019 | H46: 2257600 | I46: 2019 | J46: A8
B47: 43761 | C47: KSA.B021066-1019 | D47: 116204001001 | E47: 0002 | F47: Via. Joko Purwito | G47: Terima koreksi atas kelebihan biaya pengurusan HGB Dermaga dan Pabrik U/BBK No.019 Tgl. 04 Oktober 2019 | H47: -7500000 | I47: 2019 | J47: A8
B48: 43766 | C48: KSA.B021086-1019 | D48: 116204001001 | E48: 0002 | F48: Via. Joko Purwito | G48: By.Pengurusan HGB Pabrik dan Dermaga PT. KS Tgl. 22 Oktober 2019 | H48: 3850000 | I48: 2019 | J48: A8
B49: 43769 | C49: KSA.M09005-1019 | D49: 116204001001 | E49: 0002 | F49: RAcct @ ADK - BANGUNAN - PABRIK KELAPA S | G49: Cost fr 111904005323 EXCAVATOR HITACHI (JBP-03) | H49: 4.4673067e+08 | I49: 2019 | J49: 42
B50: 43799 | C50: KSA.M09005-1119 | D50: 116204001001 | E50: 0002 | F50: RAcct @ ADK - BANGUNAN - PABRIK KELAPA S | G50: Cost fr 111904005323 EXCAVATOR HITACHI (JBP-03) | H50: 342100630 | I50: 2019 | J50: 42
B51: 43830 | C51: KSA.M09005-1219 | D51: 116204001001 | E51: 0002 | F51: RAcct @ ADK - BANGUNAN - PABRIK KELAPA S | G51: Cost fr 111904005323 EXCAVATOR HITACHI (JBP-03) | H51: 81297445 | I51: 2019 | J51: 42
B52: 43890 | C52: KSA.M09005-0220 | D52: 116204001001 | E52: 0002 | F52: RAcct @ ADK - BANGUNAN - PABRIK KELAPA S | G52: Cost fr 111904005323 EXCAVATOR HITACHI (JBP-03) | H52: 0 | I52: 2020 | J52: 42
B53: 43921 | C53: KSA.M09005-0320 | D53: 116204001001 | E53: 0002 | F53: RAcct @ ADK - BANGUNAN - PABRIK KELAPA S | G53: Cost fr 111904005323 EXCAVATOR HITACHI (JBP-03) | H53: 308000000 | I53: 2020 | J53: 42
B54: 43951 | C54: KSA.M09005-0420 | D54: 116204001001 | E54: 0002 | F54: RAcct @ ADK - BANGUNAN - PABRIK KELAPA S | G54: Cost fr 111904005323 EXCAVATOR HITACHI (JBP-03) | H54: 220000000 | I54: 2020 | J54: 42
B55: 43982 | C55: KSA.M09005-0520 | D55: 116204001001 | E55: 0002 | F55: RAcct @ ADK - BANGUNAN - PABRIK KELAPA S | G55: Cost fr 111904005323 EXCAVATOR HITACHI (JBP-03) | H55: 176000000 | I55: 2020 | J55: 42
B56: 44012 | C56: KSA.M09005-0620 | D56: 116204001001 | E56: 0002 | F56: RAcct @ ADK - BANGUNAN - PABRIK KELAPA S | G56: Cost fr 111904005323 EXCAVATOR HITACHI (JBP-03) | H56: 56312802 | I56: 2020 | J56: 42
B57: 44043 | C57: KSA.M09005-0720 | D57: 116204001001 | E57: 0002 | F57: RAcct @ ADK - BANGUNAN - PABRIK KELAPA S | G57: Cost fr 111904005323 EXCAVATOR HITACHI (JBP-03) | H57: 44000000 | I57: 2020 | J57: 42
B58: 44056 | C58: KSA.B051033-0820 | D58: 116204001001 | E58: 0002 | F58: Said Abdurrahman | G58: By.Tahap I 20% atas Pekerjaan Pengolahan Data & Penyusunan DokumenSAP (Structural Analysis Program) Pabrik Pengolahan Kelapa SawitPT. Kumai Sentosa di Kab. Kotawaringin Barat Kal-Teng. Kwt. 05 SPK. 066 | H58: 10000000 | I58: 2020 | J58: A7
B59: 44074 | C59: KSA.M09005-0820 | D59: 116204001001 | E59: 0002 | F59: RAcct @ ADK - BANGUNAN - PABRIK KELAPA S | G59: Cost fr 111904005323 EXCAVATOR HITACHI (JBP-03) | H59: 176000000 | I59: 2020 | J59: 42
B60: 44077 | C60: KSA.B051021-0920 | D60: 116204001001 | E60: 0002 | F60: Said Abdurrahman | G60: By.Tahap II 80%(Pelunasan) atas Pekerjaan Pengolahan Data & Penyusunan Dokumen SAP (Structural Analysis Program) Pabrik Pengolahan Kelapa SawitPT. Kumai Sentosa di Kab. Kotawaringin Barat Kal-Teng. Inv. 24082020 SPK. 066 | H60: 40000000 | I60: 2020 | J60: A7
B61: 44104 | C61: KSA.M09005-0920 | D61: 116204001001 | E61: 0002 | F61: RAcct @ ADK - BANGUNAN - PABRIK KELAPA S | G61: Cost fr 111904005309 EXCAVATOR KOBELCO (BSA-01) | H61: 3321305.7 | I61: 2020 | J61: 327
B62: 44104 | C62: KSA.M09005-0920 | D62: 116204001001 | E62: 0002 | F62: RAcct @ ADK - BANGUNAN - PABRIK KELAPA S | G62: Cost fr 111904005323 EXCAVATOR HITACHI (JBP-03) | H62: 1.7076217e+08 | I62: 2020 | J62: 327
B63: 44135 | C63: KSA.M09005-1020 | D63: 116204001001 | E63: 0002 | F63: RAcct @ ADK - BANGUNAN - PABRIK KELAPA S | G63: Cost fr 111904005602 FARM TRACTOR - KUBOTA M9540 (FT-02)/32-03 | H63: 490939.83 | I63: 2020 | J63: 327
B64: 44135 | C64: KSA.M09005-1020 | D64: 116204001001 | E64: 0002 | F64: RAcct @ ADK - BANGUNAN - PABRIK KELAPA S | G64: Cost fr 111904005802 TRAILER - TRAILER 02 (TLR-02) | H64: 3309.64 | I64: 2020 | J64: 327
B65: 44135 | C65: KSA.M09005-1020 | D65: 116204001001 | E65: 0002 | F65: RAcct @ ADK - BANGUNAN - PABRIK KELAPA S | G65: Cost fr 111904005812 TRAILER - TRAILER 08 (TLR-08) | H65: 4331.57 | I65: 2020 | J65: 327
B66: 44135 | C66: KSA.M09005-1020 | D66: 116204001001 | E66: 0002 | F66: RAcct @ ADK - BANGUNAN - PABRIK KELAPA S | G66: Cost fr 111904005323 EXCAVATOR HITACHI (JBP-03) | H66: 1.5292142e+08 | I66: 2020 | J66: 42
B67: 44165 | C67: KSA.M09005-1120 | D67: 116204001001 | E67: 0002 | F67: RAcct @ ADK - BANGUNAN - PABRIK KELAPA S | G67: Cost fr 111904005323 EXCAVATOR HITACHI (JBP-03) | H67: 2.415298e+08 | I67: 2020 | J67: 42
B68: 44196 | C68: KSA.M09005-1220 | D68: 116204001001 | E68: 0002 | F68: RAcct @ ADK - BANGUNAN - PABRIK KELAPA S | G68: Cost fr 111904005323 EXCAVATOR HITACHI (JBP-03) | H68: 2.9460853e+08 | I68: 2020 | J68: 42
